Workbook

Sheet Original Data
A1: Empresa | B1: BLOOOMBERG TICKER | C1: ISiN Code | D1: Indicadores
D2: Moeda | E2: Preço Ação Primeira Abertura | F2: Preço Ação Último Fechamento | G2: Market Cap em bi | H2: Volume Médio em mi | I2: Índice P/L | J2: Rend. Dividendos | K2: ROI 5YA | L2: ROA 5YA | M2: ROE 5YA | N2: Lucro por Ação | P2: Receita Total em bi | S2: EBITDA em bi | W2: Pontuação CDP | AC2: ESG Ratings | AG2: Controversy Level
O3: 2018 | P3: 2019 | Q3: 2020 | R3: 2021 | S3: 2018 | T3: 2019 | U3: 2020 | V3: 2021 | W3: Climate Change 2020 | X3: Climate Change 2021 | Y3: Forests 2020 | Z3: Forests 2021 | AA3: Water Security 2020 | AB3: Water Security 2021 | AC3: Total ESG Risk Score | AD3: Environment Risk Score | AE3: Social Risk Score | AF3: Governance Risk Score
A4: BMW AG | B4: BMW GY Equity | C4: DE0005190003 | D4: Euro | E4: 14.1 | F4: 76.67 | G4: 49.57 | H4: 2.44 | I4: 4.22 | J4: 0.0766 | K4: 0.0541 | L4: 0.035 | M4: 0.1255 | N4: 18.77 | O4: 96.86 | P4: 104.21 | Q4: 98.99 | R4: 111.24 | S4: 17.4 | T4: 17.98 | U4: 11 | V4: 19.94 | W4: A | X4: A- | Y4: Declined to participate | Z4: Declined to participate | AA4: Declined to participate | AB4: Declined to participate | AC4: 24 | AD4: 7.2 | AE4: 7.5 | AF4: 9.2 | AG4: 3
A5: WALT DISNEY CO | B5: DIS US Equity | C5: US2546871060 | D5: Dolar | E5: 1.19 | F5: 138.62 | G5: 255.09 | H5: 12.41 | I5: 83.15 | J5: - | K5: 0.0554 | L5: 0.043 | M5: 0.0897 | N5: 1.11 | O5: 59.47 | P5: 69.42 | Q5: 65.13 | R5: 67.39 | S5: 17.93 | T5: 15.88 | U5: 8.92 | V5: 8.85 | W5: B- | X5: B | Y5: Not Scored | Z5: Not Scored | AA5: - | AB5: - | AC5: 14 | AD5: 0.1 | AE5: 7.1 | AF5: 7.2 | AG5: 2
A6: ACCENTURE PLC-A | B6: ACN US Equity | C6: IE00B4BNMY34 | D6: Dolar | E6: 18.31 | F6: 324.56 | G6: 214.96 | H6: 2.86 | I6: 33 | J6: 0.0118 | K6: 0.2756 | L6: 0.1648 | M6: 0.3653 | N6: 9.92 | O6: 40.99 | P6: 43.22 | Q6: 44.33 | R6: 50.53 | S6: 6.92 | T6: 7.25 | U6: 8.34 | V6: 9.62 | W6: A | X6: A- | Y6: - | Z6: - | AA6: - | AB6: - | AC6: 9 | AD6: 0.3 | AE6: 4.3 | AF6: 4.8 | AG6: 2
A7: MCDONALDS CORP | B7: MCD US Equity | C7: US5801351017 | D7: Dolar | E7: 0.81 | F7: 235.32 | G7: 177.06 | H7: 4.02 | I7: 23.73 | J7: 0.0232 | K7: 0.1595 | L7: 0.1447 | M7: -% | N7: 10.04 | O7: 21.03 | P7: 21.36 | Q7: 19.21 | R7: 23.22 | S7: 10.07 | T7: 10.5 | U7: 8.91 | V7: 11.64 | W7: C | X7: C | Y7: D/C | Z7: B-/B | AA7: C | AB7: D | AC7: 24 | AD7: 4.1 | AE7: 14.4 | AF7: 5.9 | AG7: 3
A8: HYUNDAI MOTO-GDR | B8: HYUD LI Equity | C8: USY384721251 | D8: Dolar | E8: 3.2 | F8: 34.1 | G8: 32.31 | H8: 0.007846 | I8: - | J8: 0.0521 | K8: 0.025 | L8: 0.0175 | M8: 0.0428 | N8: 18991.81 | O8: 96810 | P8: 105750 | Q8: 104000 | R8: 117611 | S8: 6180 | T8: 7620 | U8: 6780 | V8: 11440 | W8: A- | X8: B | Y8: No Response | Z8: No Response | AA8: A- | AB8: A- | AC8: - | AD8: - | AE8: - | AF8: - | AG8: -
A9: CATERPILLAR INC | B9: CAT US Equity | C9: US1491231015 | D9: Dolar | E9: 6.03 | F9: 223.67 | G9: 119.88 | H9: 4.2 | I9: 18.93 | J9: 0.0199 | K9: 0.0954 | L9: 0.0623 | M9: 0.3375 | N9: 11.86 | O9: 54.72 | P9: 53.79 | Q9: 41.75 | R9: 50.98 | S9: 11.43 | T9: 11.07 | U9: 7.41 | V9: 9.32 | W9: No Response | X9: No Response | Y9: - | Z9: - | AA9: No Response | AB9: No Response | AC9: 34 | AD9: 7.2 | AE9: 18.5 | AF9: 8.6 | AG9: 4
A10: ALIBABA GRP-ADR | B10: BABA US Equity | C10: US01609W1027 | D10: Dolar | E10: 85.88 | F10: 103.53 | G10: 281.83 | H10: 35.92 | I10: 30.63 | J10: -% | K10: 0.153 | L10: 0.1083 | M10: 0.2004 | N10: 8.75 | O10: 250.266 | P10: 376.844 | Q10: 509.711 | R10: 717.289 | S10: 108.99 | T10: 121.943 | U10: 157.659 | V10: 196.842 | W10: No Response | X10: No Response | Y10: No Response | Z10: No Response | AA10: - | AB10: - | AC10: - | AD10: - | AE10: - | AF10: - | AG10: -
A11: STARBUCKS CORP | B11: SBUX US Equity | C11: US8552441094 | D11: Dolar | E11: 0.32 | F11: 86.86 | G11: 99.92 | H11: 10.13 | I11: 23.71 | J11: 0.0223 | K11: 0.2031 | L11: 0.1481 | M11: -% | N11: 3.57 | O11: 24.72 | P11: 26.5 | Q11: 23.51 | R11: 29.06 | S11: 5.17 | T11: 5.35 | U11: 4.22 | V11: 7.44 | W11: D | X11: B | Y11: D/C | Z11: D/B- | AA11: B- | AB11: B | AC11: 25 | AD11: 6.1 | AE11: 14.2 | AF11: 4.3 | AG11: 2
A12: VIDRALA | B12: VID SM Equity | C12: ES0183746314 | D12: Euro | E12: 4.6 | F12: 64.8 | G12: 1.93 | H12: 0.03867 | I12: 13.52 | J12: 0.0176 | K12: 0.1195 | L12: 0.0908 | M12: 0.1921 | N12: 4.88 | O12: 0.95543 | P12: 1.01 | Q12: 0.98892 | R12: 1.08 | S12: 0.21737 | T12: 0.25832 | U12: 0.25789 | V12: 0.23076 | W12: No Response | X12: B | Y12: - | Z12: - | AA12: No Response | AB12: B | AC12: - | AD12: - | AE12: - | AF12: - | AG12: -
A13: ROYAL DUTCH SH-A | B13: RDSA NA Equity | C13: GB00B03MLX29 | D13: Euro | E13: 26.44 | F13: 24.14 | G13: 189.846 | H13: 15.264 | I13: 10.72 | J13: 0.0321 | K13: 0.0246 | L13: 0.0197 | M13: 0.0401 | N13: 2.33 | O13: 388.379 | P13: 344.877 | Q13: 180.543 | R13: 261.504 | S13: 36.758 | T13: 21.447 | U13: 10.758 | V13: 31.734 | W13: B | X13: B | Y13: No Response | Z13: No Response | AA13: No Response | AB13: No Response | AC13: 35 | AD13: 19.4 | AE13: 8.2 | AF13: 7.9 | AG13: 4
A14: HOLCIM LTD | B14: HOLN SW Equity | C14: CH0012214059 | D14: Franco Suíço | E14: 29.91 | F14: 46.18 | G14: 28.44 | H14: 2.5 | I14: 12.31 | J14: -% | K14: 0.0308 | L14: 0.024 | M14: 0.0434 | N14: 3.73 | O14: 27.47 | P14: 26.72 | Q14: 23.14 | R14: 26.83 | S14: 5.5 | T14: 6.2 | U14: 5.48 | V14: 6.42 | W14: A | X14: A | Y14: - | Z14: - | AA14: A- | AB14: A- | AC14: 21 | AD14: 11.9 | AE14: 3 | AF14: 6.3 | AG14: 3
A15: MICHELIN | B15: ML FP Equity | C15: FR0000121261 | D15: Euro | E15: 31.34 | F15: 123.25 | G15: 21.97 | H15: 0.058393 | I15: 12.4 | J15: 0.0365 | K15: 0.0664 | L15: 0.0508 | M15: 0.1219 | N15: 10.31 | O15: 22.03 | P15: 24.14 | Q15: 20.47 | R15: 23.8 | S15: 4.12 | T15: 4.76 | U15: 3.73 | V15: - | W15: A- | X15: A | Y15: No Responde | Z15: Not Scored | AA15: A- | AB15: B | AC15: 13 | AD15: 3 | AE15: 4.2 | AF15: 5.4 | AG15: 2
A16: RYANAIR HLDGS | B16: RYA ID Equity | C16: IE00BYTBXV33 | D16: Euro | E16: 1.97 | F16: 13.7 | G16: 15.51 | H16: 2.67 | I16: - | J16: -% | K16: 0.0737 | L16: 0.0512 | M16: 0.1419 | N16: -0.91 | O16: 7.15 | P16: 7.7 | Q16: 8.49 | R16: 1.64 | S16: 2.23 | T16: 1.66 | U16: 1.88 | V16: - | W16: B- | X16: B | Y16: - | Z16: - | AA16: - | AB16: - | AC16: 30 | AD16: 8.8 | AE16: 15.3 | AF16: 5.4 | AG16: 3
A17: TRIGANO SA | B17: TRI FP Equity | C17: FR0005691656 | D17: Euro | E17: 2.9 | F17: 139.7 | G17: 2.73 | H17: 31.07 | I17: 12.08 | J17: 0.0308 | K17: 0.1656 | L17: 0.1101 | M17: 0.207 | N17: 11.55 | O17: 2.31 | P17: 2.33 | Q17: 2.18 | R17: 2.93 | S17: 0.25342 | T17: 0.23584 | U17: 0.23776 | V17: 0.42454 | W17: No Response | X17: No Response | Y17: - | Z17: - | AA17: - | AB17: - | AC17: - | AD17: - | AE17: - | AF17: - | AG17: -
A18: BENETEAU | B18: BEN FP Equity | C18: FR0000035164 | D18: Euro | E18: 0.18 | F18: 14.16 | G18: 1.2 | H18: 0.101 | I18: - | J18: -% | K18: -% | L18: -% | M18: -% | N18: - | O18: 1.29 | P18: 1.34 | Q18: 1.01 | R18: 1.23 | S18: 0.1536 | T18: 0.15511 | U18: 0.07146 | V18: - | W18: No Response | X18: No Response | Y18: - | Z18: - | AA18: - | AB18: - | AC18: - | AD18: - | AE18: - | AF18: - | AG18: -
A19: SAINT GOBAIN | B19: SGO FP Equity | C19: FR0000125007 | D19: Euro | E19: 36.13 | F19: 57.88 | G19: 29.72 | H19: 1.46 | I19: 12.17 | J19: 0.0287 | K19: 0.0391 | L19: 0.0279 | M19: 0.0683 | N19: 4.79 | O19: 41.77 | P19: 42.57 | Q19: 38.13 | R19: 44.16 | S19: 5.08 | T19: 5.27 | U19: 4.74 | V19: 6.44 | W19: A- | X19: A | Y19: No Response | Z19: No Response | AA19: B | AB19: A- | AC19: 20 | AD19: 8.4 | AE19: 6.1 | AF19: 5.6 | AG19: 3
A20: BEKAERT NV | B20: BEKB BB Equity | C20: BE0974258874 | D20: Euro | E20: 18.17 | F20: 36.92 | G20: 2.23 | H20: 0.09913 | I20: 5.2 | J20: 0.0286 | K20: 0.0446 | L20: 0.0276 | M20: 0.1079 | N20: 7.14 | O20: 4.31 | P20: 4.32 | Q20: 3.77 | R20: 4.84 | S20: 0.32685 | T20: 0.44446 | U20: 0.46045 | V20: 0.6433 | W20: D | X20: D | Y20: - | Z20: - | AA20: - | AB20: - | AC20: - | AD20: - | AE20: - | AF20: - | AG20: -
A21: STABILUS SA | B21: STM GY Equity | C21: LU1066226637 | D21: Euro | E21: 23.35 | F21: 50.35 | G21: 1.24 | H21: 0.03112 | I21: 15.92 | J21: 0.0253 | K21: 0.0845 | L21: 0.0701 | M21: 0.1698 | N21: 2.97 | O21: 0.96256 | P21: 0.995134 | Q21: 0.92213 | R21: 0.93767 | S21: 0.18711 | T21: 0.17702 | U21: 0.14744 | V21: 0.018202 | W21: - | X21: - | Y21: - | Z21: - | AA21: - | AB21: - | AC21: - | AD21: - | AE21: - | AF21: - | AG21: -
A22: DECEUNINCK NV | B22: DECB BB Equity | C22: BE0003789063 | D22: Euro | E22: 7.01 | F22: 2.83 | G22: 0.381 | H22: 0.22757 | I22: 11.16 | J22: -% | K22: 0.039 | L22: 0.0261 | M22: 0.0568 | N22: 0.25 | O22: 0.67423 | P22: 0.63381 | Q22: 0.64219 | R22: 0.8381 | S22: 0.06996 | T22: 0.04619 | U22: 0.08 | V22: 0.08511 | W22: No Response | X22: D | Y22: - | Z22: - | AA22: - | AB22: - | AC22: - | AD22: - | AE22: - | AF22: - | AG22: -
A23: MUENCHENER RUE-R | B23: MUV2 GY Equity | C23: DE0008430026 | D23: Euro | E23: 216.89 | F23: 240 | G23: 33.65 | H23: 0.498115 | I23: 11.47 | J23: 0.0458 | K23: -% | L23: 0.0065 | M23: 0.0695 | N23: 20.94 | O23: 57.34 | P23: 64.85 | Q23: 66.44 | R23: 70.24 | S23: - | T23: - | U23: - | V23: - | W23: B | X23: A- | Y23: - | Z23: - | AA23: - | AB23: - | AC23: 18 | AD23: 0.4 | AE23: 9.7 | AF23: 8.2 | AG23: 2
A24: AENA SME SA | B24: AENA SM Equity | C24: ES0105046009 | D24: Euro | E24: 74 | F24: 145.15 | G24: 21.86 | H24: 0.24999 | I24: - | J24: -% | K24: 0.0551 | L24: 0.0488 | M24: 0.1281 | N24: -0.4 | O24: 4.2 | P24: 4.44 | Q24: 2.18 | R24: 2.32 | S24: 2.62 | T24: 2.75 | U24: 0.85121 | V24: 0.8224 | W24: A | X24: B | Y24: - | Z24: - | AA24: - | AB24: - | AC24: 11 | AD24: 2.3 | AE24: 4.1 | AF24: 4.8 | AG24: 0
A25: CORTICEIRA AMORI | B25: COR PL Equity | C25: PTCOR0AE0006 | D25: Euro | E25: 9.35 | F25: 10.1 | G25: 1.32 | H25: 0.10593 | I25: 17.88 | J25: -% | K25: 0.1434 | L25: 0.0938 | M25: 0.1734 | N25: 0.48 | O25: 0.76312 | P25: 0.78106 | Q25: 0.74011 | R25: 0.83782 | S25: 0.12629 | T25: 0.1182 | U25: 0.10929 | V25: - | W25: Declined to participate | X25: Not Available | Y25: No Response | Z25: No Response | AA25: Declined to participate | AB25: Declined to participate | AC25: - | AD25: - | AE25: - | AF25: - | AG25: -
A26: SANOFI | B26: SAN FP Equity | C26: FR0000120578 | D26: Euro | E26: 7.19 | F26: 94.04 | G26: 119.47 | H26: 3.01 | I26: 19.08 | J26: 0.0353 | K26: 0.0623 | L26: 0.0519 | M26: 0.0975 | N26: 4.97 | O26: 34.46 | P26: 36.13 | Q26: 36.04 | R26: 37.76 | S26: 8.55 | T26: 9.82 | U26: 10.54 | V26: 11.8 | W26: A- | X26: A | Y26: No Response | Z26: No Response | AA26: A | AB26: A | AC26: 23 | AD26: 1.6 | AE26: 13.4 | AF26: 7.9 | AG26: 4
A27: KONINKLIJKE PHIL | B27: PHIA NA Equity | C27: NL0000009538 | D27: Euro | E27: 1.88 | F27: 28.28 | G27: 24.091 | H27: 3.85 | I27: 7.58 | J27: 0.0304 | K27: 0.0501 | L27: 0.0359 | M27: 0.0757 | N27: 0.67 | O27: 18.12 | P27: 19.48 | Q27: 17.31 | R27: 17.16 | S27: 3.08 | T27: 3.43 | U27: 2.87 | V27: 1.85 | W27: A | X27: A | Y27: - | Z27: - | AA27: A- | AB27: A- | AC27: 23 | AD27: 0.9 | AE27: 14.1 | AF27: 8.5 | AG27: 4
A28: ABRDN PLC | B28: ABDN LN Equity | C28: GB00BF8Q6K64 | D28: Libra Esterlina | E28: 367.36 | F28: 207 | G28: 4.46 | H28: 6.64 | I28: 4.45 | J28: 0.0718 | K28: 0.0051 | L28: 0.0049 | M28: 0.0456 | N28: 0.47 | O28: 2.17 | P28: 2.45 | Q28: 1.64 | R28: 1.8 | S28: - | T28: - | U28: - | V28: - | W28: B | X28: C | Y28: - | Z28: - | AA28: - | AB28: - | AC28: 17 | AD28: 1.4 | AE28: 8.9 | AF28: 6.9 | AG28: 2
A29: ROCHE HLDG-GENUS | B29: ROG SW Equity | C29: CH0012032048 | D29: Franco Suíço | E29: 77.36 | F29: 366.7 | G29: 319.066 | H29: 0.358 | I29: 22.74 | J29: 0.0254 | K29: 0.2377 | L29: 0.1562 | M29: 0.4135 | N29: 16.39 | O29: 56.85 | P29: 61.47 | Q29: 58.32 | R29: 62.8 | S29: 20.31 | T29: 23.21 | U29: 22.29 | V29: 21.73 | W29: Declined to participate | X29: Declined to participate | Y29: Declined to participate | Z29: Declined to participate | AA29: Declined to participate | AB29: Declined to participate | AC29: 21 | AD29: 0.9 | AE29: 12.5 | AF29: 7.7 | AG29: 2
A30: ACERINOX | B30: ACX SM Equity | C30: ES0132105018 | D30: Euro | E30: 9.35 | F30: 10.72 | G30: 2.73 | H30: 1.5 | I30: 4.86 | J30: 0.0483 | K30: 0.0605 | L30: 0.0427 | M30: 0.1085 | N30: 2.11 | O30: 5.01 | P30: 4.75 | Q30: 4.67 | R30: 6.71 | S30: 0.47354 | T30: 0.37438 | U30: 0.39784 | V30: 0.98581 | W30: B | X30: B | Y30: - | Z30: - | AA30: No Response | AB30: Not Available | AC30: - | AD30: - | AE30: - | AF30: - | AG30: -
A31: VOPAK | B31: VPK NA Equity | C31: NL0009432491 | D31: Euro | E31: 11.8 | F31: 28.05 | G31: 3.55 | H31: 0.394 | I31: 16.65 | J31: 0.0442 | K31: 0.0684 | L31: 0.0582 | M31: 0.1124 | N31: 1.71 | O31: 1.25 | P31: 1.25 | Q31: 1.19 | R31: 1.23 | S31: 0.6393 | T31: 0.7025 | U31: 0.6535 | V31: 0.67 | W31: No Response | X31: C | Y31: - | Z31: - | AA31: No Response | AB31: C | AC31: 23 | AD31: 10.6 | AE31: 8.7 | AF31: 3.8 | AG31: 1
A32: CBRE GROUP INC-A | B32: CBRE US Equity | C32: US12504L1098 | D32: Dolar | E32: 6.31 | F32: 90.27 | G32: 30.43 | H32: 1.64 | I32: 16.93 | J32: -% | K32: 0.1315 | L32: 0.0767 | M32: 0.2057 | N32: 5.48 | O32: 21.34 | P32: 23.89 | Q32: 23.83 | R32: 27.75 | S32: - | T32: - | U32: - | V32: - | W32: B- | X32: B | Y32: - | Z32: - | AA32: - | AB32: - | AC32: 7 | AD32: 1.3 | AE32: 2.5 | AF32: 3.2 | AG32: 1
A33: MEDTRONIC PLC | B33: MDT US Equity | C33: IE00BTN1Y115 | D33: Dolar | E33: 0.47 | F33: 108.97 | G33: 144.46 | H33: 6.76 | I33: 29.67 | J33: 0.0232 | K33: 0.0536 | L33: 0.0477 | M33: 0.0879 | N33: 2.6 | O33: 29.95 | P33: 30.56 | Q33: 28.91 | R33: 30.12 | S33: 9.29 | T33: 9.76 | U33: 8.28 | V33: 8.24 | W33: B | X33: B | Y33: - | Z33: - | AA33: B- | AB33: B- | AC33: 23 | AD33: 2.3 | AE33: 13.4 | AF33: 7.7 | AG33: 3
A34: ANHEUSER-BUSCH I | B34: ABI BB Equity | C34: BE0974293251 | D34: Euro | E34: 23.21 | F34: 54.44 | G34: 108.44 | H34: 2.1 | I34: 26 | J34: 0.0092 | K34: 0.0317 | L34: 0.0258 | M34: 0.0697 | N34: 2.11 | O34: 54.619 | P34: 52.329 | Q34: 46.881 | R34: 54.304 | S34: 22.08 | T34: 21.078 | U34: 17.321 | V34: 19.209 | W34: A | X34: A- | Y34: - | Z34: - | AA34: A | AB34: A | AC34: 21 | AD34: 5.9 | AE34: 7.7 | AF34: 7.5 | AG34: 3
A35: FANUC CORP | B35: 6954 JP Equity | C35: JP3802400006 | D35: Iene | E35: 10700 | F35: 21340 | G35: 4216 | H35: 0.000812 | I35: 26.78 | J35: 0.0236 | K35: 0.0871 | L35: 0.0795 | M35: 0.0902 | N35: 490.1 | O35: 726.6 | P35: 635.57 | Q35: 508.25 | R35: 551.29 | S35: 263.79 | T35: 203.01 | U35: 134.26 | V35: 157.62 | W35: B | X35: B | Y35: - | Z35: - | AA35: B | AB35: B | AC35: 26 | AD35: 7.4 | AE35: 10.6 | AF35: 7.9 | AG35: 1
A36: EURONAV NV | B36: EURN BB Equity | C36: BE0003816338 | D36: Euro | E36: 19.1 | F36: 9.9 | G36: 1.99 | H36: 0.6596 | I36: - | J36: 0.0107 | K36: 0.0081 | L36: 0.0076 | M36: 0.0129 | N36: -1.53 | O36: 0.6 | P36: 0.932 | Q36: 1.231 | R36: 0.42 | S36: 0.18 | T36: 0.515 | U36: 0.831 | V36: 0.0484 | W36: B | X36: B | Y36: - | Z36: - | AA36: - | AB36: - | AC36: - | AD36: - | AE36: - | AF36: - | AG36: -
A37: ORANGE | B37: ORA FP Equity | C37: FR0000133308 | D37: Euro | E37: 167.5 | F37: 10.69 | G37: 28.34 | H37: 9.43 | I37: 3554 | J37: 0.0658 | K37: 0.0375 | L37: 0.026 | M37: 0.066 | N37: - | O37: 41.38 | P37: 42.24 | Q37: 42.27 | R37: 42.52 | S37: 11.59 | T37: 13.6 | U37: 13.64 | V37: 12.31 | W37: B | X37: A- | Y37: - | Z37: - | AA37: - | AB37: - | AC37: 18 | AD37: 1.7 | AE37: 8.7 | AF37: 7.3 | AG37: 3
A38: LAM RESEARCH | B38: LRCX US Equity | C38: US5128071082 | D38: Dolar | E38: 2.33 | F38: 546.76 | G38: 75.73 | H38: 1.49 | I38: 16.92 | J38: 0.011 | K38: 0.2572 | L38: 0.1996 | M38: 0.4472 | N38: 27.22 | O38: 11.09 | P38: 9.64 | Q38: 10.04 | R38: 14.63 | S38: 3.55 | T38: 2.77 | U38: 2.94 | V38: 4.78 | W38: B | X38: B | Y38: - | Z38: - | AA38: B | AB38: B | AC38: 15 | AD38: 5.1 | AE38: 4.5 | AF38: 5.3 | AG38: 1
A39: GENERALI ASSIC | B39: G IM Equity | C39: IT0000062072 | D39: Euro | E39: 13.56 | F39: 18.82 | G39: 29.73 | H39: 6.09 | I39: 10.61 | J39: 0.0785 | K39: -% | L39: 0.0047 | M39: 0.0842 | N39: 1.81 | O39: 78.07 | P39: 81.91 | Q39: 78.93 | R39: 97.2 | S39: - | T39: - | U39: - | V39: - | W39: A- | X39: B | Y39: - | Z39: - | AA39: - | AB39: - | AC39: 16 | AD39: 1 | AE39: 4 | AF39: 10.8 | AG39: 2
A40: DEUTSCHE BOERSE | B40: DB1 GY Equity | C40: DE0005810055 | D40: Euro | E40: 31.8 | F40: 163.65 | G40: 29.23 | H40: 0.5657 | I40: 24.19 | J40: 0.0196 | K40: 0.0663 | L40: 0.0066 | M40: 0.1821 | N40: 6.59 | O40: 3.36 | P40: 3.52 | Q40: 4 | R40: 4.63 | S40: 1.679 | T40: 1.813 | U40: 2.025 | V40: 2.043 | W40: B | X40: B | Y40: - | Z40: - | AA40: - | AB40: - | AC40: 14 | AD40: 1.7 | AE40: 4.5 | AF40: 7.8 | AG40: 2
A41: WABTEC CORP | B41: WAB US Equity | C41: US9297401088 | D41: Dolar | E41: 9.25 | F41: 95.69 | G41: 17.76 | H41: 1.16 | I41: 32.39 | J41: 0.0053 | K41: 0.0355 | L41: 0.0288 | M41: 0.0585 | N41: 2.96 | O41: 4.36 | P41: 8.2 | Q41: 7.56 | R41: 7.82 | S41: 0.65993 | T41: 1.33 | U41: 1.33 | V41: 1.45 | W41: D | X41: B | Y41: - | Z41: - | AA41: - | AB41: - | AC41: 32 | AD41: 10.4 | AE41: 14.1 | AF41: 7.7 | AG41: 1
A42: KOMATSU LTD | B42: 6301 JP Equity | C42: JP3304200003 | D42: Iene | E42: 486 | F42: 2925.5 | G42: 2830 | H42: 3.296 | I42: 14.46 | J42: 0.0279 | K42: 0.0766 | L42: 0.0526 | M42: 0.0967 | N42: 112.52 | O42: 2500 | P42: 2730 | Q42: 2440 | R42: 2190 | S42: 433.93 | T42: 530.91 | U42: 385.45 | V42: 304.05 | W42: A | X42: A | Y42: - | Z42: - | AA42: A | AB42: A | AC42: 26 | AD42: 5.3 | AE42: 11.5 | AF42: 8.9 | AG42: 2
A43: SAF-HOLLAND SE | B43: SFQ GY Equity | C43: DE000SAFH001 | D43: Euro | E43: 15.42 | F43: 8.36 | G43: 0.369 | H43: 0.1485 | I43: 10.06 | J43: - | K43: 0.0479 | L43: 0.038 | M43: 0.11 | N43: 0.81 | O43: 1.3 | P43: 1.28 | Q43: 0.95952 | R43: 1.25 | S43: 0.10507 | T43: 0.11034 | U43: 0.09519 | V43: 0.12156 | W43: Declined to participate | X43: Not Available | Y43: - | Z43: - | AA43: - | AB43: - | AC43: - | AD43: - | AE43: - | AF43: - | AG43: -
A44: ASTRAZENECA PLC | B44: AZN LN Equity | C44: GB0009895292 | D44: Libra Esterlina | E44: 609.85 | F44: 9574 | G44: 150.761 | H44: 2.584 | I44: 1621.67 | J44: 0.0219 | K44: 0.0366 | L44: 0.0262 | M44: 0.1103 | N44: 0.06 | O44: 22.09 | P44: 24.384 | Q44: 26.617 | R44: 37.417 | S44: 7.14 | T44: 6.686 | U44: 8.311 | V44: 7.586 | W44: A | X44: A | Y44: Not Available | Z44: C | AA44: A | AB44: A | AC44: 23 | AD44: 1.2 | AE44: 14.2 | AF44: 7.8 | AG44: 3
A45: ABBOTT LABS | B45: ABT US Equity | C45: US0028241000 | D45: Dolar | E45: 1.34 | F45: 121.89 | G45: 207.791 | H45: 6.22 | I45: 29.91 | J45: 0.0154 | K45: 0.0657 | L45: 0.0559 | M45: 0.1267 | N45: 3.98 | O45: 30.58 | P45: 31.9 | Q45: 34.61 | R45: 43.08 | S45: 7.12 | T45: 7.61 | U45: 8.62 | V45: 12.74 | W45: B | X45: B | Y45: No Response | Z45: No Response | AA45: B | AB45: A- | AC45: 26 | AD45: 3 | AE45: 13.5 | AF45: 9.4 | AG45: 3
A46: DEUTSCHE POST-RG | B46: DPW GY Equity | C46: DE0005552004 | D46: Euro | E46: 23.05 | F46: 45.91 | G46: 55.721 | H46: 3.262 | I46: 11.22 | J46: 0.0392 | K46: 0.1009 | L46: 0.0665 | M46: 0.2232 | N46: 4.1 | O46: 61.55 | P46: 63.43 | Q46: 66.72 | R46: 81.75 | S46: 5.31 | T46: 6.11 | U46: 7.37 | V46: 10.29 | W46: B | X46: B | Y46: - | Z46: - | AA46: - | AB46: - | AC46: 16 | AD46: 4 | AE46: 6.7 | AF46: 4.9 | AG46: 2
A47: BOSKALIS WESTMIN | B47: BOKA NA Equity | C47: NL0000852580 | D47: Euro | E47: 10.58 | F47: 32.56 | G47: 4.208 | H47: 0.257 | I47: 27.96 | J47: 0.0154 | K47: -0.0101 | L47: -0.0066 | M47: -0.0119 | N47: 1.16 | O47: 2.57 | P47: 2.64 | Q47: 2.52 | R47: 2.96 | S47: 0.31973 | T47: 0.25255 | U47: 0.36463 | V47: 0.42716 | W47: B- | X47: C | Y47: No Response | Z47: No Response | AA47: - | AB47: - | AC47: - | AD47: - | AE47: - | AF47: - | AG47: -
A48: AXA | B48: CS FP Equity | C48: FR0000120628 | D48: Euro | E48: 6.2 | F48: 26 | G48: 61.465 | H48: 7.018 | I48: 11.08 | J48: 0.0592 | K48: -% | L48: 0.0048 | M48: 0.061 | N48: 1.25 | O48: 117.1 | P48: 124.96 | Q48: 101.71 | R48: 100.52 | S48: - | T48: - | U48: - | V48: - | W48: C | X48: A- | Y48: - | Z48: - | AA48: - | AB48: - | AC48: 13 | AD48: 0.6 | AE48: 4.8 | AF48: 7.8 | AG48: 2
A49: VISA INC-CLASS A | B49: V US Equity | C49: US92826C8394 | D49: Dolar | E49: 20.86 | F49: 218.47 | G49: 465.234 | H49: 9.331 | I49: 35.59 | J49: 0.0069 | K49: 0.1725 | L49: 0.1435 | M49: 0.344 | N49: 5.64 | O49: 20.61 | P49: 22.98 | Q49: 21.85 | R49: 24.11 | S49: 14.17 | T49: 16.06 | U49: 14.88 | V49: 16.63 | W49: A- | X49: A | Y49: - | Z49: - | AA49: - | AB49: - | AC49: 16 | AD49: 0.7 | AE49: 7.8 | AF49: 7.5 | AG49: 3
A50: PEARSON PLC | B50: PSON LN Equity | C50: GB0006776081 | D50: Libra Esterlina | E50: 312.4 | F50: 779.6 | G50: 5.904 | H50: 2.449 | I50: 37.3 | J50: 0.0259 | K50: 0.0548 | L50: 0.0437 | M50: 0.0809 | N50: 0.21 | O50: 4.13 | P50: 3.87 | Q50: 3.4 | R50: 3.43 | S50: 0.93 | T50: 0.97 | U50: 0.78 | V50: 0.983 | W50: B | X50: B | Y50: B | Z50: B | AA50: B | AB50: B | AC50: 8 | AD50: 0 | AE50: 3.3 | AF50: 4.3 | AG50: 2
A51: BBVA | B51: BBVA SM Equity | C51: ES0113211835 | D51: Euro | E51: 14.51 | F51: 5.2 | G51: 33.66 | H51: 26.465 | I51: 7.75 | J51: 0.0688 | K51: -% | L51: 0.0072 | M51: 0.0858 | N51: 0.6 | O51: 29.99 | P51: 27.91 | Q51: 22.53 | R51: 23.19 | S51: - | T51: - | U51: - | V51: - | W51: A- | X51: B | Y51: - | Z51: - | AA51: - | AB51: - | AC51: 22 | AD51: 1.2 | AE51: 10.3 | AF51: 11 | AG51: 3
A52: AVIVA PLC | B52: AV/ LN Equity | C52: GB0002162385 | D52: Libra Esterlina | E52: 299.84 | F52: 440.7 | G52: 16.117 | H52: 10.399 | I52: 8.78 | J52: 0.05 | K52: -% | L52: 0.0035 | M52: 0.0789 | N52: 0.06 | O52: 18.29 | P52: 66.38 | Q52: 31.08 | R52: 31.98 | S52: - | T52: - | U52: - | V52: - | W52: D | X52: C | Y52: - | Z52: - | AA52: - | AB52: - | AC52: 17 | AD52: 1.3 | AE52: 9.4 | AF52: 6.1 | AG52: 2
A53: DUERR AG | B53: DUE GY Equity | C53: DE0005565204 | D53: Euro | E53: 7.41 | F53: 31.7 | G53: 2.162 | H53: 0.136 | I53: 26.93 | J53: 0.0095 | K53: 0.062 | L53: 0.0303 | M53: 0.115 | N53: 1.2 | O53: 3.87 | P53: 3.92 | Q53: 3.32 | R53: 3.54 | S53: 0.34663 | T53: 0.31601 | U53: 0.11996 | V53: 0.28122 | W53: C | X53: C | Y53: - | Z53: - | AA53: C | AB53: B- | AC53: - | AD53: - | AE53: - | AF53: - | AG53: -
A54: TRIPADVISOR INC | B54: TRIP US Equity | C54: US8969452015 | D54: Dolar | E54: 32.91 | F54: 25.91 | G54: 3.719 | H54: 2.622 | I54: - | J54: -% | K54: -0.0137 | L54: -0.0114 | M54: -0.0201 | N54: -1.08 | O54: 1.62 | P54: 1.56 | Q54: 0.604 | R54: 0.902 | S54: 0.299 | T54: 0.313 | U54: -0.172 | V54: -0.029 | W54: No Response | X54: No Response | Y54: - | Z54: - | AA54: - | AB54: - | AC54: 26 | AD54: 2.8 | AE54: 14.7 | AF54: 8.3 | AG54: 2
A55: KENDRION NV | B55: KENDR NA Equity | C55: NL0000852531 | D55: Euro | E55: 96.49 | F55: 19.9 | G55: 0.296 | H55: 0.007937 | I55: 20.56 | J55: 0.0202 | K55: 0.0395 | L55: 0.0309 | M55: 0.0618 | N55: 0.97 | O55: 0.4486 | P55: 0.4124 | Q55: 0.3964 | R55: 0.464 | S55: 0.0545 | T55: 0.0452 | U55: 0.0478 | V55: 0.0591 | W55: Declined to participate | X55: No Response | Y55: - | Z55: - | AA55: - | AB55: - | AC55: - | AD55: - | AE55: - | AF55: - | AG55: -
A56: BNP PARIBAS | B56: BNP FP Equity | C56: FR0000131104 | D56: Euro | E56: 20.98 | F56: 53.6 | G56: 64.417 | H56: 4.711 | I56: 7.2 | J56: 0.0696 | K56: -% | L56: 0.0037 | M56: 0.0698 | N56: 6.98 | O56: 56.355 | P56: 54.779 | Q56: 55.005 | R56: 51.994 | S56: - | T56: - | U56: - | V56: - | W56: A- | X56: A- | Y56: - | Z56: - | AA56: - | AB56: - | AC56: 24 | AD56: 1.3 | AE56: 11.2 | AF56: 11.4 | AG56: 3
A57: SIXT SE-PRFD | B57: SIX3 GY Equity | C57: DE0007231334 | D57: Euro | E57: 24.54 | F57: 75 | G57: 5.313 | H57: 0.026347 | I57: 14.97 | J57: 0.0496 | K57: 0.0643 | L57: 0.044 | M57: 0.1534 | N57: 6.67 | O57: 2.93 | P57: 2.5 | Q57: 1.53 | R57: 2.28 | S57: 0.53656 | T57: 0.37685 | U57: -0.00944 | V57: 0.84922 | W57: Not Available | X57: No Response | Y57: - | Z57: - | AA57: - | AB57: - | AC57: - | AD57: - | AE57: - | AF57: - | AG57: -
A58: NATURGY ENERGY | B58: NTGY SM Equity | C58: ES0116870314 | D58: Euro | E58: 17.79 | F58: 25.15 | G58: 23.76 | H58: 0.842348 | I58: 19.6 | J58: 0.0795 | K58: 0.0112 | L58: 0.0083 | M58: 0.0016 | N58: 1.14 | O58: 24.34 | P58: 20.76 | Q58: 15.35 | R58: 22.14 | S58: 3.71 | T58: 4.06 | U58: 3.23 | V58: 3.61 | W58: A | X58: A- | Y58: - | Z58: - | AA58: B- | AB58: A | AC58: 18 | AD58: 7.8 | AE58: 5.2 | AF58: 5.2 | AG58: 1
A59: CENTRAL JAPAN RL | B59: 9022 JP Equity | C59: JP3566800003 | D59: Iene | E59: 6980 | F59: 16545 | G59: 3256 | H59: 0.705426 | I59: - | J59: 0.008 | K59: 0.0368 | L59: 0.0338 | M59: 0.0888 | N59: -1025.45 | O59: 1820 | P59: 1880 | Q59: 1840 | R59: 823.52 | S59: 873.21 | T59: 921.04 | U59: 874.11 | V59: 14.61 | W59: B | X59: B | Y59: - | Z59: No Response | AA59: No Response | AB59: No Response | AC59: 28 | AD59: 10.1 | AE59: 12.5 | AF59: 5.8 | AG59: 2
A60: VODAFONE GROUP | B60: VOD LN Equity | C60: GB00BH4HKS39 | D60: Libra Esterlina | E60: 14.62 | F60: 127 | G60: 35.57 | H60: 140.827 | I60: - | J60: 0.0591 | K60: -0.0021 | L60: -0.0016 | M60: -0.0092 | N60: -0.5 | O60: 46.571 | P60: 43.666 | Q60: 44.974 | R60: 43.809 | S60: 12.99 | T60: 12.27 | U60: 16.55 | V60: 16.64 | W60: A | X60: A- | Y60: - | Z60: - | AA60: - | AB60: - | AC60: 16 | AD60: 2.5 | AE60: 7.8 | AF60: 5.4 | AG60: 2
A61: DALATA HOTEL GRO | B61: DHG ID Equity | C61: IE00BJMZDW83 | D61: Euro | E61: 2.79 | F61: 3.84 | G61: 0.894 | H61: 0.43275 | I61: - | J61: -% | K61: 0.0159 | L61: 0.0151 | M61: 0.0259 | N61: -0.03 | O61: 0.39257 | P61: 0.42918 | Q61: 0.13682 | R61: 0.19199 | S61: 0.11255 | T61: 0.16094 | U61: -0.01343 | V61: 0.01452 | W61: B | X61: B | Y61: - | Z61: - | AA61: - | AB61: - | AC61: - | AD61: - | AE61: - | AF61: - | AG61: -
A62: MAPFRE SA | B62: MAP SM Equity | C62: ES0124244E34 | D62: Euro | E62: 1.2049 | F62: 1.886 | G62: 5.666 | H62: 4.083 | I62: 7.4 | J62: 0.0901 | K62: -% | L62: 0.014 | M62: 0.0732 | N62: 0.25 | O62: 21.48 | P62: 21.94 | Q62: 18.38 | R62: 19.72 | S62: - | T62: - | U62: - | V62: - | W62: B | X62: B | Y62: - | Z62: - | AA62: - | AB62: - | AC62: 21 | AD62: 2 | AE62: 8.3 | AF62: 10.9 | AG62: 2
A63: PROSIEBENSAT.1 M | B63: PSM GY Equity | C63: DE000PSM7770 | D63: Euro | E63: 17.12 | F63: 12.05 | G63: 2.67 | H63: 1.236 | I63: 5.96 | J63: 0.0664 | K63: 0.0736 | L63: 0.0551 | M63: 0.3096 | N63: 1.98 | O63: 4.01 | P63: 4.14 | Q63: 4.05 | R63: 4.49 | S63: 0.523 | T63: 0.805 | U63: 0.675 | V63: 0.83 | W63: D | X63: D | Y63: - | Z63: - | AA63: - | AB63: - | AC63: 12 | AD63: 0.1 | AE63: 5.3 | AF63: 6.1 | AG63: 2
A64: SOLUTIONS 30 SE | B64: S30 FP Equity | C64: FR0013379484 | D64: Euro | E64: 0.09 | F64: 8.05 | G64: 0.856 | H64: 1.231 | I64: 22.41 | J64: -% | K64: 0.1428 | L64: 0.0594 | M64: 0.3241 | N64: 0.32 | O64: 0.45182 | P64: 0.69141 | Q64: 0.81928 | R64: 0.8738 | S64: 0.02516 | T64: 0.06757 | U64: 0.09023 | V64: - | W64: - | X64: - | Y64: - | Z64: - | AA64: - | AB64: - | AC64: - | AD64: - | AE64: - | AF64: - | AG64: -
A65: BOOKING HOLDINGS | B65: BKNG US Equity | C65: US09857L1089 | D65: Dolar | E65: 974.25 | F65: 2201.96 | G65: 88.522 | H65: 0.46536 | I65: 78.65 | J65: -% | K65: 0.1481 | L65: 0.1214 | M65: 0.3535 | N65: 28.39 | O65: 14.53 | P65: 15.07 | Q65: 6.8 | R65: 10.96 | S65: 5.77 | T65: 5.99 | U65: 1.1 | V65: 3.24 | W65: - | X65: - | Y65: - | Z65: - | AA65: - | AB65: - | AC65: 22 | AD65: 2 | AE65: 12.4 | AF65: 7.2 | AG65: 2
A66: F-SECURE OYJ | B66: FSC1V FH Equity | C66: FI0009801310 | D66: Euro | E66: 13.6 | F66: 5.39 | G66: 0.896 | H66: 0.139815 | I66: 70.62 | J66: 0.0077 | K66: 0.067 | L66: 0.0379 | M66: 0.1072 | N66: 0.08 | O66: 0.19073 | P66: 0.21734 | Q66: 0.2202 | R66: 0.23627 | S66: 0.01413 | T66: 0.0171 | U66: 0.03359 | V66: 0.03428 | W66: - | X66: - | Y66: - | Z66: - | AA66: - | AB66: - | AC66: - | AD66: - | AE66: - | AF66: - | AG66: -
A67: CREDIT AGRICOLE | B67: ACA FP Equity | C67: FR0000045072 | D67: Euro | E67: 16.16 | F67: 11.05 | G67: 32.821 | H67: 9.026 | I67: 5.91 | J67: 0.0724 | K67: -% | L67: 0.0029 | M67: 0.0633 | N67: 1.83 | O67: 25.9 | P67: 26.61 | Q67: 24.47 | R67: 22.66 | S67: - | T67: - | U67: - | V67: - | W67: A- | X67: B | Y67: - | Z67: - | AA67: - | AB67: - | AC67: 25 | AD67: 1.5 | AE67: 10.6 | AF67: 12.9 | AG67: 3
A68: BUREAU VERITAS S | B68: BVI FP Equity | C68: FR0006174348 | D68: Euro | E68: 9.75 | F68: 26.64 | G68: 12.037 | H68: 0.809 | I68: 28.91 | J68: 0.0199 | K68: 0.0764 | L68: 0.0531 | M68: 0.2673 | N68: 0.93 | O68: 4.8 | P68: 5.1 | Q68: 4.6 | R68: 4.98 | S68: 0.8123 | T68: 1 | U68: 0.8162 | V68: 0.9732 | W68: B | X68: B | Y68: - | Z68: - | AA68: - | AB68: - | AC68: 11 | AD68: 0.1 | AE68: 6.3 | AF68: 4.8 | AG68: 2
A69: SHANGRI-LA ASIA | B69: 69 HK Equity | C69: BMG8063F1068 | D69: HKD | E69: 6.206 | F69: 6.206 | G69: 22.696 | H69: 1.646 | I69: 19.04 | J69: -% | K69: 0.0009 | L69: 0.0007 | M69: 0.0048 | N69: -1.01 | O69: 2.518 | P69: 2.431 | Q69: 1.033 | R69: 1.241 | S69: 0.665 | T69: 0.584 | U69: -0.0849 | V69: 0.133 | W69: B- | X69: C | Y69: No Response | Z69: No Response | AA69: B | AB69: C | AC69: - | AD69: - | AE69: - | AF69: - | AG69: -
A70: ARCELORMITTAL | B70: MT NA Equity | C70: LU1598757687 | D70: Euro | E70: 46.25 | F70: 30.56 | G70: 27.548 | H70: 6.279 | I70: 2.47 | J70: 0.0109 | K70: 0.0728 | L70: 0.0524 | M70: 0.1089 | N70: 12.27 | O70: 76.033 | P70: 70.615 | Q70: 53.27 | R70: 76.571 | S70: 10.265 | T70: 5.195 | U70: 4.301 | V70: 19.404 | W70: A- | X70: B | Y70: No Response | Z70: No Response | AA70: Not Scored | AB70: C | AC70: 37 | AD70: 15.6 | AE70: 14.9 | AF70: 6.5 | AG70: 4
A71: HILTON WORLDWIDE | B71: HLT US Equity | C71: US43300A2033 | D71: Dolar | E71: 45 | F71: 151.42 | G71: 41.705 | H71: 2.742 | I71: 102.33 | J71: -% | K71: 0.0273 | L71: 0.0228 | M71: 0.6547 | N71: 1.47 | O71: 8.91 | P71: 9.48 | Q71: 4.34 | R71: 5.82 | S71: 1.76 | T71: 1.95 | U71: 0.241 | V71: 1.24 | W71: B | X71: B | Y71: D- | Z71: Not Scored | AA71: A- | AB71: Not Scored | AC71: 20 | AD71: 7.9 | AE71: 8.1 | AF71: 3.9 | AG71: 2
A72: WYNN MACAU LTD | B72: 1128 HK Equity | C72: KYG981491007 | D72: HKD | E72: 9.57 | F72: 5.83 | G72: 30.091 | H72: 11.602 | I72: 5.9 | J72: -% | K72: 0.051 | L72: 0.0398 | M72: 1.077 | N72: -1.4 | O72: 39.632 | P72: 35.817 | Q72: 7.598 | R72: 11.771 | S72: 12.372 | T72: 10.701 | U72: -1.836 | V72: 0.748 | W72: No Response | X72: No Response | Y72: - | Z72: No Response | AA72: - | AB72: - | AC72: 21 | AD72: 2.2 | AE72: 9.8 | AF72: 8.6 | AG72: 3
A73: TELEFONICA | B73: TEF SM Equity | C73: ES0178430E18 | D73: Euro | E73: 29.5119 | F73: 4.245 | G73: 24.223 | H73: 18.955 | I73: 3.06 | J73: 0.0707 | K73: 0.0571 | L73: 0.038 | M73: 0.1902 | N73: 1.38 | O73: 48.69 | P73: 48.42 | Q73: 43.08 | R73: 39.28 | S73: 15.85 | T73: 15.92 | U73: 15.92 | V73: 12.39 | W73: A | X73: A | Y73: - | Z73: - | AA73: - | AB73: - | AC73: 17 | AD73: 1.6 | AE73: 9.2 | AF73: 6.6 | AG73: 2
A74: FUGRO NV | B74: FUR NA Equity | C74: NL00150003E1 | D74: Euro | E74: 10.45 | F74: 10.05 | G74: 1.035 | H74: 0.77326 | I74: 14.55 | J74: -% | K74: -0.0352 | L74: -0.0257 | M74: -0.0655 | N74: 0.59 | O74: 1.55 | P74: 1.63 | Q74: 1.39 | R74: 1.46 | S74: 0.10834 | T74: 0.16743 | U74: 0.12373 | V74: 0.15536 | W74: C | X74: B- | Y74: - | Z74: - | AA74: - | AB74: - | AC74: - | AD74: - | AE74: - | AF74: - | AG74: -
A75: OCI NV | B75: OCI NA Equity | C75: NL0010558797 | D75: Euro | E75: 37.9 | F75: 31.12 | G75: 6.761 | H75: 0.413416 | I75: 13.13 | J75: -% | K75: 0.0258 | L75: 0.0183 | M75: -0.015 | N75: 2.47 | O75: 3.253 | P75: 3.032 | Q75: 3.474 | R75: 6.319 | S75: 0.929 | T75: 0.748 | U75: 0.87 | V75: 2.527 | W75: - | X75: - | Y75: - | Z75: - | AA75: - | AB75: - | AC75: - | AD75: - | AE75: - | AF75: - | AG75: -
A76: WEST JAPAN RAILW | B76: 9021 JP Equity | C76: JP3659000008 | D76: Iene | E76: 3280 | F76: 5123 | G76: 1274 | H76: 1.43 | I76: - | J76: 0.0191 | K76: 0.0143 | L76: 0.0113 | M76: 0.032 | N76: -1219.71 | O76: 1500 | P76: 1530 | Q76: 1510 | R76: 898.17 | S76: 356.13 | T76: 361.33 | U76: 332.27 | V76: -70.88 | W76: B- | X76: B | Y76: - | Z76: - | AA76: No Response | AB76: No Response | AC76: 25 | AD76: 8.6 | AE76: 10.8 | AF76: 5.3 | AG76: 1
A77: LINDBLAD EXPEDIT | B77: LIND US Equity | C77: US5352191093 | D77: Dolar | E77: 10.1 | F77: 14.42 | G77: 0.720872 | H77: 0.273515 | I77: - | J77: -% | K77: -0.0957 | L77: -0.0654 | M77: -0.1504 | N77: -2.49 | O77: 0.30973 | P77: 0.34309 | Q77: 0.08236 | R77: 0.14711 | S77: 0.04711 | T77: 0.05906 | U77: -0.05627 | V77: -0.07029 | W77: - | X77: - | Y77: - | Z77: - | AA77: - | AB77: - | AC77: - | AD77: - | AE77: - | AF77: - | AG77: -
A78: M&G PLC | B78: MNG LN Equity | C78: GB00BKFB1C65 | D78: Libra Esterlina | E78: 225.2 | F78: 216 | G78: 5.621 | H78: 8.442 | I78: 67.56 | J78: 0.086 | K78: -% | L78: 0.0038 | M78: 0.1205 | N78: 0.03 | O78: -2.89 | P78: 32.67 | Q78: 15.76 | R78: 17.41 | S78: - | T78: - | U78: - | V78: - | W78: A- | X78: B | Y78: - | Z78: - | AA78: - | AB78: - | AC78: - | AD78: - | AE78: - | AF78: - | AG78: -
A79: IVS GROUP | B79: IVS IM Equity | C79: LU0556041001 | D79: Euro | E79: 9.5 | F79: 4.98 | G79: 0.181511 | H79: 0.007399 | I79: 34.93 | J79: -% | K79: 0.0161 | L79: 0.0127 | M79: 0.0339 | N79: 0.14 | O79: 0.41258 | P79: 0.43762 | Q79: 0.30573 | R79: 0.33661 | S79: 0.07032 | T79: 0.08029 | U79: 0.04615 | V79: 0.04571 | W79: No Response | X79: - | Y79: - | Z79: - | AA79: - | AB79: - | AC79: - | AD79: - | AE79: - | AF79: - | AG79: -
A80: KOENIG & BAUER | B80: SKB GY Equity | C80: DE0007193500 | D80: Euro | E80: 17.03 | F80: 23.4 | G80: 0.388333 | H80: 0.021835 | I80: - | J80: -% | K80: 0.0505 | L80: 0.0295 | M80: 0.0902 | N80: -6.28 | O80: 1.23 | P80: 1.25 | Q80: 1.03 | R80: - | S80: 0.1111 | T80: 0.086 | U80: -0.0272 | V80: - | W80: No Response | X80: - | Y80: - | Z80: - | AA80: - | AB80: - | AC80: - | AD80: - | AE80: - | AF80: - | AG80: -
A81: WIZZ AIR HOLDING | B81: WIZZ LN Equity | C81: JE00BN574F90 | D81: Libra Esterlina | E81: 1312 | F81: 2635 | G81: 3.522 | H81: 0.675662 | I81: - | J81: -% | K81: 0.0306 | L81: 0.0217 | M81: 0.0678 | N81: -5.56 | O81: 1.948 | P81: 2.319 | Q81: 2.761 | R81: 0.739 | S81: 0.383 | T81: 0.393 | U81: 0.783 | V81: -0.183 | W81: No Response | X81: C | Y81: - | Z81: - | AA81: - | AB81: - | AC81: - | AD81: - | AE81: - | AF81: - | AG81: -
A82: ATLANTIA SPA | B82: ATL IM Equity | C82: IT0003506190 | D82: Euro | E82: 12.6 | F82: 18.08 | G82: 14.89 | H82: 1.463 | I82: 1136.56 | J82: -% | K82: -% | L82: -% | M82: -% | N82: -0.37 | O82: 7.427 | P82: 12.615 | Q82: 5.26 | R82: 6.391 | S82: 3.768 | T82: 7.203 | U82: 3.701 | V82: 4.029 | W82: B | X82: B | Y82: - | Z82: - | AA82: - | AB82: - | AC82: 15 | AD82: 0.9 | AE82: 9.5 | AF82: 4.2 | AG82: 5
A83: AEGON NV | B83: AGN NA Equity | C83: NL0000303709 | D83: Euro | E83: 5.105 | F83: 4.543 | G83: 9.319 | H83: 11.535 | I83: 5.95 | J83: 0.0374 | K83: -% | L83: 0.003 | M83: 0.048 | N83: 0.78 | O83: 20.819 | P83: 67.489 | Q83: 51.346 | R83: 52.977 | S83: - | T83: - | U83: - | V83: - | W83: C | X83: C | Y83: - | Z83: - | AA83: - | AB83: - | AC83: 15 | AD83: 0.5 | AE83: 7.7 | AF83: 6.4 | AG83: 3
A84: ACCOR SA | B84: AC FP Equity | C84: FR0000120404 | D84: Euro | E84: 26.64 | F84: 29.02 | G84: 7.489 | H84: 0.881329 | I84: 149.74 | J84: -% | K84: -0.0283 | L84: -0.0226 | M84: -0.0591 | N84: -0.1 | O84: 3.28 | P84: 4.05 | Q84: 1.62 | R84: 2.2 | S84: 0.625 | T84: 0.862 | U84: -0.391 | V84: - | W84: A- | X84: A- | Y84: - | Z84: - | AA84: No Response | AB84: B | AC84: 18 | AD84: 6.8 | AE84: 7.2 | AF84: 4.3 | AG84: 2
A85: CARNIVAL CORP | B85: CCL US Equity | C85: PA1436583006 | D85: Dolar | E85: 4 | F85: 18.93 | G85: 21.436 | H85: 39.679 | I85: - | J85: -% | K85: -0.0599 | L85: -0.0482 | M85: -0.0982 | N85: -8.46 | O85: 18.88 | P85: 20.83 | Q85: 5.6 | R85: 1.91 | S85: 5.34 | T85: 5.44 | U85: -2.34 | V85: -3.89 | W85: C | X85: B | Y85: - | Z85: - | AA85: B | AB85: B | AC85: 24 | AD85: 10.3 | AE85: 9.7 | AF85: 3.8 | AG85: 3
A86: LAS VEGAS SANDS | B86: LVS US Equity | C86: US5178341070 | D86: Dolar | E86: 43.4 | F86: 39.02 | G86: 29.161 | H86: 9.458 | I86: - | J86: -% | K86: 0.0631 | L86: 0.0516 | M86: 0.1932 | N86: -1.51 | O86: 13.73 | P86: 13.74 | Q86: 2.94 | R86: 4.23 | S86: 5.02 | T86: 4.99 | U86: -0.304 | V86: 0.398 | W86: A | X86: A | Y86: - | Z86: - | AA86: A | AB86: A | AC86: 18 | AD86: 1.6 | AE86: 8 | AF86: 8.3 | AG86: 2
A87: JCDECAUX SA | B87: DEC FP Equity | C87: FR0000077919 | D87: Euro | E87: 13.64 | F87: 22.82 | G87: 4.883 | H87: 0.114027 | I87: - | J87: -% | K87: -0.0021 | L87: -0.0016 | M87: 0.025 | N87: -2.84 | O87: 3.18 | P87: 3.49 | Q87: 2.1 | R87: 2.52 | S87: 1.51 | T87: 1.7 | U87: 1.03 | V87: 1.15 | W87: A- | X87: A | Y87: - | Z87: - | AA87: - | AB87: - | AC87: 16 | AD87: 0.1 | AE87: 8.9 | AF87: 6.6 | AG87: 1
A88: BAUER AG | B88: B5A GY Equity | C88: DE0005168108 | D88: Euro | E88: 19.9 | F88: 9 | G88: 0.234826 | H88: 0.006008 | I88: - | J88: -% | K88: -0.0006 | L88: -0.0003 | M88: -0.0043 | N88: -0.46 | O88: 1.67 | P88: 1.59 | Q88: 1.47 | R88: 1.34 | S88: 0.20195 | T88: 0.22243 | U88: 0.13699 | V88: 0.16316 | W88: - | X88: - | Y88: - | Z88: - | AA88: - | AB88: - | AC88: - | AD88: - | AE88: - | AF88: - | AG88: -
A89: HYATT HOTELS-A | B89: H US Equity | C89: US4485791028 | D89: Dolar | E89: 29.81 | F89: 94.04 | G89: 10.248 | H89: 0.999921 | I89: - | J89: -% | K89: 0.0285 | L89: 0.0247 | M89: 0.0576 | N89: -2.14 | O89: 4.45 | P89: 5.02 | Q89: 2.07 | R89: 3.03 | S89: 0.6 | T89: 0.519 | U89: -0.348 | V89: 0.076 | W89: B- | X89: B- | Y89: - | Z89: - | AA89: - | AB89: - | AC89: 28 | AD89: 11.8 | AE89: 10.8 | AF89: 5.3 | AG89: 2

Sheet Data Converted to EUR
A1: Empresa | B1: BLOOOMBERG TICKER | C1: ISiN Code | D1: Indicadores
D2: Moeda Antiga | E2: Preço Ação Primeira Abertura | F2: Preço Ação Último Fechamento | G2: Market Cap em bi | H2: Volume Médio em mi | I2: Índice P/L | J2: Rend. Dividendos | K2: ROI 5YA | L2: ROA 5YA | M2: ROE 5YA | N2: Lucro por Ação | O2: Receita Total em bi | S2: EBITDA em bi | W2: Pontuação CDP | AC2: ESG Ratings | AG2: Controversy Level
O3: 2018 | P3: 2019 | Q3: 2020 | R3: 2021 | S3: 2018 | T3: 2019 | U3: 2020 | V3: 2021 | W3: Climate Change 2020 | X3: Climate Change 2021 | Y3: Forests 2020 | Z3: Forests 2021 | AA3: Water Security 2020 | AB3: Water Security 2021 | AC3: Total ESG Risk Score | AD3: Environment Risk Score | AE3: Social Risk Score | AF3: Governance Risk Score
A4: BMW AG | B4: BMW GY Equity | C4: DE0005190003 | D4: Euro | E4: =IFERROR(__xludf.DUMMYFUNCTION("IF($D4=""Euro"",'Original Data'!E4, IF($D4=""Dolar"",'Original Data'!E4*GOOGLEFINANCE(""Currency:USDEUR""), IF($D4=""Franco Suíço"",'Original Data'!E4*GOOGLEFINANCE(""Currency:CHFEUR""), IF($D4=""Libra Esterlina"", 'Original Data'!E4*GOOGLEFINANCE(""Curre"&"ncy:GBPEUR""), IF($D4=""Iene"",'Original Data'!E4*GOOGLEFINANCE(""Currency:JPYEUR""), IF($D4=""HKD"",'Original Data'!E4*GOOGLEFINANCE(""Currency:HKDEUR""), IF($D4=""KRW"",'Original Data'!E4*GOOGLEFINANCE(""Currency:KRWEUR""),"""")))))))"),14.1) -> 14.1 | F4: =IFERROR(__xludf.DUMMYFUNCTION("IF($D4=""Euro"",'Original Data'!F4, IF($D4=""Dolar"",'Original Data'!F4*GOOGLEFINANCE(""Currency:USDEUR""), IF($D4=""Franco Suíço"",'Original Data'!F4*GOOGLEFINANCE(""Currency:CHFEUR""), IF($D4=""Libra Esterlina"", 'Original Data'!F4*GOOGLEFINANCE(""Curre"&"ncy:GBPEUR""), IF($D4=""Iene"",'Original Data'!F4*GOOGLEFINANCE(""Currency:JPYEUR""), IF($D4=""HKD"",'Original Data'!F4*GOOGLEFINANCE(""Currency:HKDEUR""), IF($D4=""KRW"",'Original Data'!F4*GOOGLEFINANCE(""Currency:KRWEUR""),"""")))))))"),76.67) -> 76.67 | G4: =IFERROR(__xludf.DUMMYFUNCTION("IF($D4=""Euro"",'Original Data'!G4, IF($D4=""Dolar"",'Original Data'!G4*GOOGLEFINANCE(""Currency:USDEUR""), IF($D4=""Franco Suíço"",'Original Data'!G4*GOOGLEFINANCE(""Currency:CHFEUR""), IF($D4=""Libra Esterlina"", 'Original Data'!G4*GOOGLEFINANCE(""Curre"&"ncy:GBPEUR""), IF($D4=""Iene"",'Original Data'!G4*GOOGLEFINANCE(""Currency:JPYEUR""), IF($D4=""HKD"",'Original Data'!G4*GOOGLEFINANCE(""Currency:HKDEUR""), IF($D4=""KRW"",'Original Data'!G4*GOOGLEFINANCE(""Currency:KRWEUR""),"""")))))))"),49.57) -> 49.57 | H4: 2.44 | I4: 4.22 | J4: 0.0766 | K4: 0.0541 | L4: 0.035 | M4: 0.1255 | N4: =IFERROR(__xludf.DUMMYFUNCTION("IF('Original Data'!N4=""-"",""-"", IF($D4=""Euro"",'Original Data'!N4, IF($D4=""Dolar"",'Original Data'!N4*GOOGLEFINANCE(""Currency:USDEUR""), IF($D4=""Franco Suíço"",'Original Data'!N4*GOOGLEFINANCE(""Currency:CHFEUR""), IF($D4=""Libra Esterlina"", 'Orig"&"inal Data'!N4*GOOGLEFINANCE(""Currency:GBPEUR""), IF($D4=""Iene"",'Original Data'!N4*GOOGLEFINANCE(""Currency:JPYEUR""), IF($D4=""HKD"",'Original Data'!N4*GOOGLEFINANCE(""Currency:HKDEUR""), IF($D4=""KRW"",'Original Data'!N4*GOOGLEFINANCE(""Currency:KRWEU"&"R""),""""))))))))"),18.77) -> 18.77 | O4: =IFERROR(__xludf.DUMMYFUNCTION("IF('Original Data'!O4=""-"",""-"", IF($D4=""Euro"",'Original Data'!O4, IF($D4=""Dolar"",'Original Data'!O4*GOOGLEFINANCE(""Currency:USDEUR""), IF($D4=""Franco Suíço"",'Original Data'!O4*GOOGLEFINANCE(""Currency:CHFEUR""), IF($D4=""Libra Esterlina"", 'Orig"&"inal Data'!O4*GOOGLEFINANCE(""Currency:GBPEUR""), IF($D4=""Iene"",'Original Data'!O4*GOOGLEFINANCE(""Currency:JPYEUR""), IF($D4=""HKD"",'Original Data'!O4*GOOGLEFINANCE(""Currency:HKDEUR""), IF($D4=""KRW"",'Original Data'!O4*GOOGLEFINANCE(""Currency:KRWEU"&"R""),""""))))))))"),96.86) -> 96.86 | P4: =IFERROR(__xludf.DUMMYFUNCTION("IF('Original Data'!P4=""-"",""-"", IF($D4=""Euro"",'Original Data'!P4, IF($D4=""Dolar"",'Original Data'!P4*GOOGLEFINANCE(""Currency:USDEUR""), IF($D4=""Franco Suíço"",'Original Data'!P4*GOOGLEFINANCE(""Currency:CHFEUR""), IF($D4=""Libra Esterlina"", 'Orig"&"inal Data'!P4*GOOGLEFINANCE(""Currency:GBPEUR""), IF($D4=""Iene"",'Original Data'!P4*GOOGLEFINANCE(""Currency:JPYEUR""), IF($D4=""HKD"",'Original Data'!P4*GOOGLEFINANCE(""Currency:HKDEUR""), IF($D4=""KRW"",'Original Data'!P4*GOOGLEFINANCE(""Currency:KRWEU"&"R""),""""))))))))"),104.21) -> 104.21 | Q4: =IFERROR(__xludf.DUMMYFUNCTION("IF('Original Data'!Q4=""-"",""-"", IF($D4=""Euro"",'Original Data'!Q4, IF($D4=""Dolar"",'Original Data'!Q4*GOOGLEFINANCE(""Currency:USDEUR""), IF($D4=""Franco Suíço"",'Original Data'!Q4*GOOGLEFINANCE(""Currency:CHFEUR""), IF($D4=""Libra Esterlina"", 'Orig"&"inal Data'!Q4*GOOGLEFINANCE(""Currency:GBPEUR""), IF($D4=""Iene"",'Original Data'!Q4*GOOGLEFINANCE(""Currency:JPYEUR""), IF($D4=""HKD"",'Original Data'!Q4*GOOGLEFINANCE(""Currency:HKDEUR""), IF($D4=""KRW"",'Original Data'!Q4*GOOGLEFINANCE(""Currency:KRWEU"&"R""),""""))))))))"),98.99) -> 98.99 | R4: =IFERROR(__xludf.DUMMYFUNCTION("IF('Original Data'!R4=""-"",""-"", IF($D4=""Euro"",'Original Data'!R4, IF($D4=""Dolar"",'Original Data'!R4*GOOGLEFINANCE(""Currency:USDEUR""), IF($D4=""Franco Suíço"",'Original Data'!R4*GOOGLEFINANCE(""Currency:CHFEUR""), IF($D4=""Libra Esterlina"", 'Orig"&"inal Data'!R4*GOOGLEFINANCE(""Currency:GBPEUR""), IF($D4=""Iene"",'Original Data'!R4*GOOGLEFINANCE(""Currency:JPYEUR""), IF($D4=""HKD"",'Original Data'!R4*GOOGLEFINANCE(""Currency:HKDEUR""), IF($D4=""KRW"",'Original Data'!R4*GOOGLEFINANCE(""Currency:KRWEU"&"R""),""""))))))))"),111.24) -> 111.24 | S4: =IFERROR(__xludf.DUMMYFUNCTION("IF('Original Data'!S4=""-"",""-"", IF($D4=""Euro"",'Original Data'!S4, IF($D4=""Dolar"",'Original Data'!S4*GOOGLEFINANCE(""Currency:USDEUR""), IF($D4=""Franco Suíço"",'Original Data'!S4*GOOGLEFINANCE(""Currency:CHFEUR""), IF($D4=""Libra Esterlina"", 'Orig"&"inal Data'!S4*GOOGLEFINANCE(""Currency:GBPEUR""), IF($D4=""Iene"",'Original Data'!S4*GOOGLEFINANCE(""Currency:JPYEUR""), IF($D4=""HKD"",'Original Data'!S4*GOOGLEFINANCE(""Currency:HKDEUR""), IF($D4=""KRW"",'Original Data'!S4*GOOGLEFINANCE(""Currency:KRWEU"&"R""),""""))))))))"),17.4) -> 17.4 | T4: =IFERROR(__xludf.DUMMYFUNCTION("IF('Original Data'!T4=""-"",""-"", IF($D4=""Euro"",'Original Data'!T4, IF($D4=""Dolar"",'Original Data'!T4*GOOGLEFINANCE(""Currency:USDEUR""), IF($D4=""Franco Suíço"",'Original Data'!T4*GOOGLEFINANCE(""Currency:CHFEUR""), IF($D4=""Libra Esterlina"", 'Orig"&"inal Data'!T4*GOOGLEFINANCE(""Currency:GBPEUR""), IF($D4=""Iene"",'Original Data'!T4*GOOGLEFINANCE(""Currency:JPYEUR""), IF($D4=""HKD"",'Original Data'!T4*GOOGLEFINANCE(""Currency:HKDEUR""), IF($D4=""KRW"",'Original Data'!T4*GOOGLEFINANCE(""Currency:KRWEU"&"R""),""""))))))))"),17.98) -> 17.98 | U4: =IFERROR(__xludf.DUMMYFUNCTION("IF('Original Data'!U4=""-"",""-"", IF($D4=""Euro"",'Original Data'!U4, IF($D4=""Dolar"",'Original Data'!U4*GOOGLEFINANCE(""Currency:USDEUR""), IF($D4=""Franco Suíço"",'Original Data'!U4*GOOGLEFINANCE(""Currency:CHFEUR""), IF($D4=""Libra Esterlina"", 'Orig"&"inal Data'!U4*GOOGLEFINANCE(""Currency:GBPEUR""), IF($D4=""Iene"",'Original Data'!U4*GOOGLEFINANCE(""Currency:JPYEUR""), IF($D4=""HKD"",'Original Data'!U4*GOOGLEFINANCE(""Currency:HKDEUR""), IF($D4=""KRW"",'Original Data'!U4*GOOGLEFINANCE(""Currency:KRWEU"&"R""),""""))))))))"),11.0) -> 11 | V4: =IFERROR(__xludf.DUMMYFUNCTION("IF('Original Data'!V4=""-"",""-"", IF($D4=""Euro"",'Original Data'!V4, IF($D4=""Dolar"",'Original Data'!V4*GOOGLEFINANCE(""Currency:USDEUR""), IF($D4=""Franco Suíço"",'Original Data'!V4*GOOGLEFINANCE(""Currency:CHFEUR""), IF($D4=""Libra Esterlina"", 'Orig"&"inal Data'!V4*GOOGLEFINANCE(""Currency:GBPEUR""), IF($D4=""Iene"",'Original Data'!V4*GOOGLEFINANCE(""Currency:JPYEUR""), IF($D4=""HKD"",'Original Data'!V4*GOOGLEFINANCE(""Currency:HKDEUR""), IF($D4=""KRW"",'Original Data'!V4*GOOGLEFINANCE(""Currency:KRWEU"&"R""),""""))))))))"),19.94) -> 19.94 | W4: A | X4: A- | Y4: Declined to participate | Z4: Declined to participate | AA4: Declined to participate | AB4: Declined to participate | AC4: 24 | AD4: 7.2 | AE4: 7.5 | AF4: 9.2 | AG4: 3
A5: WALT DISNEY CO | B5: DIS US Equity | C5: US2546871060 | D5: Dolar | E5: =IFERROR(__xludf.DUMMYFUNCTION("IF($D5=""Euro"",'Original Data'!E5, IF($D5=""Dolar"",'Original Data'!E5*GOOGLEFINANCE(""Currency:USDEUR""), IF($D5=""Franco Suíço"",'Original Data'!E5*GOOGLEFINANCE(""Currency:CHFEUR""), IF($D5=""Libra Esterlina"", 'Original Data'!E5*GOOGLEFINANCE(""Curre"&"ncy:GBPEUR""), IF($D5=""Iene"",'Original Data'!E5*GOOGLEFINANCE(""Currency:JPYEUR""), IF($D5=""HKD"",'Original Data'!E5*GOOGLEFINANCE(""Currency:HKDEUR""), IF($D5=""KRW"",'Original Data'!E5*GOOGLEFINANCE(""Currency:KRWEUR""),"""")))))))"),1.09361) -> 1.09361 | F5: =IFERROR(__xludf.DUMMYFUNCTION("IF($D5=""Euro"",'Original Data'!F5, IF($D5=""Dolar"",'Original Data'!F5*GOOGLEFINANCE(""Currency:USDEUR""), IF($D5=""Franco Suíço"",'Original Data'!F5*GOOGLEFINANCE(""Currency:CHFEUR""), IF($D5=""Libra Esterlina"", 'Original Data'!F5*GOOGLEFINANCE(""Curre"&"ncy:GBPEUR""), IF($D5=""Iene"",'Original Data'!F5*GOOGLEFINANCE(""Currency:JPYEUR""), IF($D5=""HKD"",'Original Data'!F5*GOOGLEFINANCE(""Currency:HKDEUR""), IF($D5=""KRW"",'Original Data'!F5*GOOGLEFINANCE(""Currency:KRWEUR""),"""")))))))"),127.39178) -> 127.39178 | G5: =IFERROR(__xludf.DUMMYFUNCTION("IF($D5=""Euro"",'Original Data'!G5, IF($D5=""Dolar"",'Original Data'!G5*GOOGLEFINANCE(""Currency:USDEUR""), IF($D5=""Franco Suíço"",'Original Data'!G5*GOOGLEFINANCE(""Currency:CHFEUR""), IF($D5=""Libra Esterlina"", 'Original Data'!G5*GOOGLEFINANCE(""Curre"&"ncy:GBPEUR""), IF($D5=""Iene"",'Original Data'!G5*GOOGLEFINANCE(""Currency:JPYEUR""), IF($D5=""HKD"",'Original Data'!G5*GOOGLEFINANCE(""Currency:HKDEUR""), IF($D5=""KRW"",'Original Data'!G5*GOOGLEFINANCE(""Currency:KRWEUR""),"""")))))))"),234.42771) -> 234.42771 | H5: 12.41 | I5: 83.15 | J5: - | K5: 0.0554 | L5: 0.043 | M5: 0.0897 | N5: =IFERROR(__xludf.DUMMYFUNCTION("IF('Original Data'!N5=""-"",""-"", IF($D5=""Euro"",'Original Data'!N5, IF($D5=""Dolar"",'Original Data'!N5*GOOGLEFINANCE(""Currency:USDEUR""), IF($D5=""Franco Suíço"",'Original Data'!N5*GOOGLEFINANCE(""Currency:CHFEUR""), IF($D5=""Libra Esterlina"", 'Orig"&"inal Data'!N5*GOOGLEFINANCE(""Currency:GBPEUR""), IF($D5=""Iene"",'Original Data'!N5*GOOGLEFINANCE(""Currency:JPYEUR""), IF($D5=""HKD"",'Original Data'!N5*GOOGLEFINANCE(""Currency:HKDEUR""), IF($D5=""KRW"",'Original Data'!N5*GOOGLEFINANCE(""Currency:KRWEU"&"R""),""""))))))))"),1.02009) -> 1.02009 | O5: =IFERROR(__xludf.DUMMYFUNCTION("IF('Original Data'!O5=""-"",""-"", IF($D5=""Euro"",'Original Data'!O5, IF($D5=""Dolar"",'Original Data'!O5*GOOGLEFINANCE(""Currency:USDEUR""), IF($D5=""Franco Suíço"",'Original Data'!O5*GOOGLEFINANCE(""Currency:CHFEUR""), IF($D5=""Libra Esterlina"", 'Orig"&"inal Data'!O5*GOOGLEFINANCE(""Currency:GBPEUR""), IF($D5=""Iene"",'Original Data'!O5*GOOGLEFINANCE(""Currency:JPYEUR""), IF($D5=""HKD"",'Original Data'!O5*GOOGLEFINANCE(""Currency:HKDEUR""), IF($D5=""KRW"",'Original Data'!O5*GOOGLEFINANCE(""Currency:KRWEU"&"R""),""""))))))))"),54.65293) -> 54.65293 | P5: =IFERROR(__xludf.DUMMYFUNCTION("IF('Original Data'!P5=""-"",""-"", IF($D5=""Euro"",'Original Data'!P5, IF($D5=""Dolar"",'Original Data'!P5*GOOGLEFINANCE(""Currency:USDEUR""), IF($D5=""Franco Suíço"",'Original Data'!P5*GOOGLEFINANCE(""Currency:CHFEUR""), IF($D5=""Libra Esterlina"", 'Orig"&"inal Data'!P5*GOOGLEFINANCE(""Currency:GBPEUR""), IF($D5=""Iene"",'Original Data'!P5*GOOGLEFINANCE(""Currency:JPYEUR""), IF($D5=""HKD"",'Original Data'!P5*GOOGLEFINANCE(""Currency:HKDEUR""), IF($D5=""KRW"",'Original Data'!P5*GOOGLEFINANCE(""Currency:KRWEU"&"R""),""""))))))))"),63.79698) -> 63.79698 | Q5: =IFERROR(__xludf.DUMMYFUNCTION("IF('Original Data'!Q5=""-"",""-"", IF($D5=""Euro"",'Original Data'!Q5, IF($D5=""Dolar"",'Original Data'!Q5*GOOGLEFINANCE(""Currency:USDEUR""), IF($D5=""Franco Suíço"",'Original Data'!Q5*GOOGLEFINANCE(""Currency:CHFEUR""), IF($D5=""Libra Esterlina"", 'Orig"&"inal Data'!Q5*GOOGLEFINANCE(""Currency:GBPEUR""), IF($D5=""Iene"",'Original Data'!Q5*GOOGLEFINANCE(""Currency:JPYEUR""), IF($D5=""HKD"",'Original Data'!Q5*GOOGLEFINANCE(""Currency:HKDEUR""), IF($D5=""KRW"",'Original Data'!Q5*GOOGLEFINANCE(""Currency:KRWEU"&"R""),""""))))))))"),59.85446999999999) -> 59.85447 | R5: =IFERROR(__xludf.DUMMYFUNCTION("IF('Original Data'!R5=""-"",""-"", IF($D5=""Euro"",'Original Data'!R5, IF($D5=""Dolar"",'Original Data'!R5*GOOGLEFINANCE(""Currency:USDEUR""), IF($D5=""Franco Suíço"",'Original Data'!R5*GOOGLEFINANCE(""Currency:CHFEUR""), IF($D5=""Libra Esterlina"", 'Orig"&"inal Data'!R5*GOOGLEFINANCE(""Currency:GBPEUR""), IF($D5=""Iene"",'Original Data'!R5*GOOGLEFINANCE(""Currency:JPYEUR""), IF($D5=""HKD"",'Original Data'!R5*GOOGLEFINANCE(""Currency:HKDEUR""), IF($D5=""KRW"",'Original Data'!R5*GOOGLEFINANCE(""Currency:KRWEU"&"R""),""""))))))))"),61.93140999999999) -> 61.93141 | S5: =IFERROR(__xludf.DUMMYFUNCTION("IF('Original Data'!S5=""-"",""-"", IF($D5=""Euro"",'Original Data'!S5, IF($D5=""Dolar"",'Original Data'!S5*GOOGLEFINANCE(""Currency:USDEUR""), IF($D5=""Franco Suíço"",'Original Data'!S5*GOOGLEFINANCE(""Currency:CHFEUR""), IF($D5=""Libra Esterlina"", 'Orig"&"inal Data'!S5*GOOGLEFINANCE(""Currency:GBPEUR""), IF($D5=""Iene"",'Original Data'!S5*GOOGLEFINANCE(""Currency:JPYEUR""), IF($D5=""HKD"",'Original Data'!S5*GOOGLEFINANCE(""Currency:HKDEUR""), IF($D5=""KRW"",'Original Data'!S5*GOOGLEFINANCE(""Currency:KRWEU"&"R""),""""))))))))"),16.47767) -> 16.47767 | T5: =IFERROR(__xludf.DUMMYFUNCTION("IF('Original Data'!T5=""-"",""-"", IF($D5=""Euro"",'Original Data'!T5, IF($D5=""Dolar"",'Original Data'!T5*GOOGLEFINANCE(""Currency:USDEUR""), IF($D5=""Franco Suíço"",'Original Data'!T5*GOOGLEFINANCE(""Currency:CHFEUR""), IF($D5=""Libra Esterlina"", 'Orig"&"inal Data'!T5*GOOGLEFINANCE(""Currency:GBPEUR""), IF($D5=""Iene"",'Original Data'!T5*GOOGLEFINANCE(""Currency:JPYEUR""), IF($D5=""HKD"",'Original Data'!T5*GOOGLEFINANCE(""Currency:HKDEUR""), IF($D5=""KRW"",'Original Data'!T5*GOOGLEFINANCE(""Currency:KRWEU"&"R""),""""))))))))"),14.59372) -> 14.59372 | U5: =IFERROR(__xludf.DUMMYFUNCTION("IF('Original Data'!U5=""-"",""-"", IF($D5=""Euro"",'Original Data'!U5, IF($D5=""Dolar"",'Original Data'!U5*GOOGLEFINANCE(""Currency:USDEUR""), IF($D5=""Franco Suíço"",'Original Data'!U5*GOOGLEFINANCE(""Currency:CHFEUR""), IF($D5=""Libra Esterlina"", 'Orig"&"inal Data'!U5*GOOGLEFINANCE(""Currency:GBPEUR""), IF($D5=""Iene"",'Original Data'!U5*GOOGLEFINANCE(""Currency:JPYEUR""), IF($D5=""HKD"",'Original Data'!U5*GOOGLEFINANCE(""Currency:HKDEUR""), IF($D5=""KRW"",'Original Data'!U5*GOOGLEFINANCE(""Currency:KRWEU"&"R""),""""))))))))"),8.197479999999999) -> 8.19748 | V5: =IFERROR(__xludf.DUMMYFUNCTION("IF('Original Data'!V5=""-"",""-"", IF($D5=""Euro"",'Original Data'!V5, IF($D5=""Dolar"",'Original Data'!V5*GOOGLEFINANCE(""Currency:USDEUR""), IF($D5=""Franco Suíço"",'Original Data'!V5*GOOGLEFINANCE(""Currency:CHFEUR""), IF($D5=""Libra Esterlina"", 'Orig"&"inal Data'!V5*GOOGLEFINANCE(""Currency:GBPEUR""), IF($D5=""Iene"",'Original Data'!V5*GOOGLEFINANCE(""Currency:JPYEUR""), IF($D5=""HKD"",'Original Data'!V5*GOOGLEFINANCE(""Currency:HKDEUR""), IF($D5=""KRW"",'Original Data'!V5*GOOGLEFINANCE(""Currency:KRWEU"&"R""),""""))))))))"),8.133149999999999) -> 8.13315 | W5: B- | X5: B | Y5: Not Scored | Z5: Not Scored | AA5: - | AB5: - | AC5: 14 | AD5: 0.1 | AE5: 7.1 | AF5: 7.2 | AG5: 2
A6: ACCENTURE PLC-A | B6: ACN US Equity | C6: IE00B4BNMY34 | D6: Dolar | E6: =IFERROR(__xludf.DUMMYFUNCTION("IF($D6=""Euro"",'Original Data'!E6, IF($D6=""Dolar"",'Original Data'!E6*GOOGLEFINANCE(""Currency:USDEUR""), IF($D6=""Franco Suíço"",'Original Data'!E6*GOOGLEFINANCE(""Currency:CHFEUR""), IF($D6=""Libra Esterlina"", 'Original Data'!E6*GOOGLEFINANCE(""Curre"&"ncy:GBPEUR""), IF($D6=""Iene"",'Original Data'!E6*GOOGLEFINANCE(""Currency:JPYEUR""), IF($D6=""HKD"",'Original Data'!E6*GOOGLEFINANCE(""Currency:HKDEUR""), IF($D6=""KRW"",'Original Data'!E6*GOOGLEFINANCE(""Currency:KRWEUR""),"""")))))))"),16.82689) -> 16.82689 | F6: =IFERROR(__xludf.DUMMYFUNCTION("IF($D6=""Euro"",'Original Data'!F6, IF($D6=""Dolar"",'Original Data'!F6*GOOGLEFINANCE(""Currency:USDEUR""), IF($D6=""Franco Suíço"",'Original Data'!F6*GOOGLEFINANCE(""Currency:CHFEUR""), IF($D6=""Libra Esterlina"", 'Original Data'!F6*GOOGLEFINANCE(""Curre"&"ncy:GBPEUR""), IF($D6=""Iene"",'Original Data'!F6*GOOGLEFINANCE(""Currency:JPYEUR""), IF($D6=""HKD"",'Original Data'!F6*GOOGLEFINANCE(""Currency:HKDEUR""), IF($D6=""KRW"",'Original Data'!F6*GOOGLEFINANCE(""Currency:KRWEUR""),"""")))))))"),298.27063999999996) -> 298.27064 | G6: =IFERROR(__xludf.DUMMYFUNCTION("IF($D6=""Euro"",'Original Data'!G6, IF($D6=""Dolar"",'Original Data'!G6*GOOGLEFINANCE(""Currency:USDEUR""), IF($D6=""Franco Suíço"",'Original Data'!G6*GOOGLEFINANCE(""Currency:CHFEUR""), IF($D6=""Libra Esterlina"", 'Original Data'!G6*GOOGLEFINANCE(""Curre"&"ncy:GBPEUR""), IF($D6=""Iene"",'Original Data'!G6*GOOGLEFINANCE(""Currency:JPYEUR""), IF($D6=""HKD"",'Original Data'!G6*GOOGLEFINANCE(""Currency:HKDEUR""), IF($D6=""KRW"",'Original Data'!G6*GOOGLEFINANCE(""Currency:KRWEUR""),"""")))))))"),197.54824) -> 197.54824 | H6: 2.86 | I6: 33 | J6: 0.0118 | K6: 0.2756 | L6: 0.1648 | M6: 0.3653 | N6: =IFERROR(__xludf.DUMMYFUNCTION("IF('Original Data'!N6=""-"",""-"", IF($D6=""Euro"",'Original Data'!N6, IF($D6=""Dolar"",'Original Data'!N6*GOOGLEFINANCE(""Currency:USDEUR""), IF($D6=""Franco Suíço"",'Original Data'!N6*GOOGLEFINANCE(""Currency:CHFEUR""), IF($D6=""Libra Esterlina"", 'Orig"&"inal Data'!N6*GOOGLEFINANCE(""Currency:GBPEUR""), IF($D6=""Iene"",'Original Data'!N6*GOOGLEFINANCE(""Currency:JPYEUR""), IF($D6=""HKD"",'Original Data'!N6*GOOGLEFINANCE(""Currency:HKDEUR""), IF($D6=""KRW"",'Original Data'!N6*GOOGLEFINANCE(""Currency:KRWEU"&"R""),""""))))))))"),9.11648) -> 9.11648 | O6: =IFERROR(__xludf.DUMMYFUNCTION("IF('Original Data'!O6=""-"",""-"", IF($D6=""Euro"",'Original Data'!O6, IF($D6=""Dolar"",'Original Data'!O6*GOOGLEFINANCE(""Currency:USDEUR""), IF($D6=""Franco Suíço"",'Original Data'!O6*GOOGLEFINANCE(""Currency:CHFEUR""), IF($D6=""Libra Esterlina"", 'Orig"&"inal Data'!O6*GOOGLEFINANCE(""Currency:GBPEUR""), IF($D6=""Iene"",'Original Data'!O6*GOOGLEFINANCE(""Currency:JPYEUR""), IF($D6=""HKD"",'Original Data'!O6*GOOGLEFINANCE(""Currency:HKDEUR""), IF($D6=""KRW"",'Original Data'!O6*GOOGLEFINANCE(""Currency:KRWEU"&"R""),""""))))))))"),37.66981) -> 37.66981 | P6: =IFERROR(__xludf.DUMMYFUNCTION("IF('Original Data'!P6=""-"",""-"", IF($D6=""Euro"",'Original Data'!P6, IF($D6=""Dolar"",'Original Data'!P6*GOOGLEFINANCE(""Currency:USDEUR""), IF($D6=""Franco Suíço"",'Original Data'!P6*GOOGLEFINANCE(""Currency:CHFEUR""), IF($D6=""Libra Esterlina"", 'Orig"&"inal Data'!P6*GOOGLEFINANCE(""Currency:GBPEUR""), IF($D6=""Iene"",'Original Data'!P6*GOOGLEFINANCE(""Currency:JPYEUR""), IF($D6=""HKD"",'Original Data'!P6*GOOGLEFINANCE(""Currency:HKDEUR""), IF($D6=""KRW"",'Original Data'!P6*GOOGLEFINANCE(""Currency:KRWEU"&"R""),""""))))))))"),39.719179999999994) -> 39.71918 | Q6: =IFERROR(__xludf.DUMMYFUNCTION("IF('Original Data'!Q6=""-"",""-"", IF($D6=""Euro"",'Original Data'!Q6, IF($D6=""Dolar"",'Original Data'!Q6*GOOGLEFINANCE(""Currency:USDEUR""), IF($D6=""Franco Suíço"",'Original Data'!Q6*GOOGLEFINANCE(""Currency:CHFEUR""), IF($D6=""Libra Esterlina"", 'Orig"&"inal Data'!Q6*GOOGLEFINANCE(""Currency:GBPEUR""), IF($D6=""Iene"",'Original Data'!Q6*GOOGLEFINANCE(""Currency:JPYEUR""), IF($D6=""HKD"",'Original Data'!Q6*GOOGLEFINANCE(""Currency:HKDEUR""), IF($D6=""KRW"",'Original Data'!Q6*GOOGLEFINANCE(""Currency:KRWEU"&"R""),""""))))))))"),40.73927) -> 40.73927 | R6: =IFERROR(__xludf.DUMMYFUNCTION("IF('Original Data'!R6=""-"",""-"", IF($D6=""Euro"",'Original Data'!R6, IF($D6=""Dolar"",'Original Data'!R6*GOOGLEFINANCE(""Currency:USDEUR""), IF($D6=""Franco Suíço"",'Original Data'!R6*GOOGLEFINANCE(""Currency:CHFEUR""), IF($D6=""Libra Esterlina"", 'Orig"&"inal Data'!R6*GOOGLEFINANCE(""Currency:GBPEUR""), IF($D6=""Iene"",'Original Data'!R6*GOOGLEFINANCE(""Currency:JPYEUR""), IF($D6=""HKD"",'Original Data'!R6*GOOGLEFINANCE(""Currency:HKDEUR""), IF($D6=""KRW"",'Original Data'!R6*GOOGLEFINANCE(""Currency:KRWEU"&"R""),""""))))))))"),46.43707) -> 46.43707 | S6: =IFERROR(__xludf.DUMMYFUNCTION("IF('Original Data'!S6=""-"",""-"", IF($D6=""Euro"",'Original Data'!S6, IF($D6=""Dolar"",'Original Data'!S6*GOOGLEFINANCE(""Currency:USDEUR""), IF($D6=""Franco Suíço"",'Original Data'!S6*GOOGLEFINANCE(""Currency:CHFEUR""), IF($D6=""Libra Esterlina"", 'Orig"&"inal Data'!S6*GOOGLEFINANCE(""Currency:GBPEUR""), IF($D6=""Iene"",'Original Data'!S6*GOOGLEFINANCE(""Currency:JPYEUR""), IF($D6=""HKD"",'Original Data'!S6*GOOGLEFINANCE(""Currency:HKDEUR""), IF($D6=""KRW"",'Original Data'!S6*GOOGLEFINANCE(""Currency:KRWEU"&"R""),""""))))))))"),6.35948) -> 6.35948 | T6: =IFERROR(__xludf.DUMMYFUNCTION("IF('Original Data'!T6=""-"",""-"", IF($D6=""Euro"",'Original Data'!T6, IF($D6=""Dolar"",'Original Data'!T6*GOOGLEFINANCE(""Currency:USDEUR""), IF($D6=""Franco Suíço"",'Original Data'!T6*GOOGLEFINANCE(""Currency:CHFEUR""), IF($D6=""Libra Esterlina"", 'Orig"&"inal Data'!T6*GOOGLEFINANCE(""Currency:GBPEUR""), IF($D6=""Iene"",'Original Data'!T6*GOOGLEFINANCE(""Currency:JPYEUR""), IF($D6=""HKD"",'Original Data'!T6*GOOGLEFINANCE(""Currency:HKDEUR""), IF($D6=""KRW"",'Original Data'!T6*GOOGLEFINANCE(""Currency:KRWEU"&"R""),""""))))))))"),6.662749999999999) -> 6.66275 | U6: =IFERROR(__xludf.DUMMYFUNCTION("IF('Original Data'!U6=""-"",""-"", IF($D6=""Euro"",'Original Data'!U6, IF($D6=""Dolar"",'Original Data'!U6*GOOGLEFINANCE(""Currency:USDEUR""), IF($D6=""Franco Suíço"",'Original Data'!U6*GOOGLEFINANCE(""Currency:CHFEUR""), IF($D6=""Libra Esterlina"", 'Orig"&"inal Data'!U6*GOOGLEFINANCE(""Currency:GBPEUR""), IF($D6=""Iene"",'Original Data'!U6*GOOGLEFINANCE(""Currency:JPYEUR""), IF($D6=""HKD"",'Original Data'!U6*GOOGLEFINANCE(""Currency:HKDEUR""), IF($D6=""KRW"",'Original Data'!U6*GOOGLEFINANCE(""Currency:KRWEU"&"R""),""""))))))))"),7.664459999999999) -> 7.66446 | V6: =IFERROR(__xludf.DUMMYFUNCTION("IF('Original Data'!V6=""-"",""-"", IF($D6=""Euro"",'Original Data'!V6, IF($D6=""Dolar"",'Original Data'!V6*GOOGLEFINANCE(""Currency:USDEUR""), IF($D6=""Franco Suíço"",'Original Data'!V6*GOOGLEFINANCE(""Currency:CHFEUR""), IF($D6=""Libra Esterlina"", 'Orig"&"inal Data'!V6*GOOGLEFINANCE(""Currency:GBPEUR""), IF($D6=""Iene"",'Original Data'!V6*GOOGLEFINANCE(""Currency:JPYEUR""), IF($D6=""HKD"",'Original Data'!V6*GOOGLEFINANCE(""Currency:HKDEUR""), IF($D6=""KRW"",'Original Data'!V6*GOOGLEFINANCE(""Currency:KRWEU"&"R""),""""))))))))"),8.840779999999999) -> 8.84078 | W6: A | X6: A- | Y6: - | Z6: - | AA6: - | AB6: - | AC6: 9 | AD6: 0.3 | AE6: 4.3 | AF6: 4.8 | AG6: 2
A7: MCDONALDS CORP | B7: MCD US Equity | C7: US5801351017 | D7: Dolar | E7: =IFERROR(__xludf.DUMMYFUNCTION("IF($D7=""Euro"",'Original Data'!E7, IF($D7=""Dolar"",'Original Data'!E7*GOOGLEFINANCE(""Currency:USDEUR""), IF($D7=""Franco Suíço"",'Original Data'!E7*GOOGLEFINANCE(""Currency:CHFEUR""), IF($D7=""Libra Esterlina"", 'Original Data'!E7*GOOGLEFINANCE(""Curre"&"ncy:GBPEUR""), IF($D7=""Iene"",'Original Data'!E7*GOOGLEFINANCE(""Currency:JPYEUR""), IF($D7=""HKD"",'Original Data'!E7*GOOGLEFINANCE(""Currency:HKDEUR""), IF($D7=""KRW"",'Original Data'!E7*GOOGLEFINANCE(""Currency:KRWEUR""),"""")))))))"),0.74439) -> 0.74439 | F7: =IFERROR(__xludf.DUMMYFUNCTION("IF($D7=""Euro"",'Original Data'!F7, IF($D7=""Dolar"",'Original Data'!F7*GOOGLEFINANCE(""Currency:USDEUR""), IF($D7=""Franco Suíço"",'Original Data'!F7*GOOGLEFINANCE(""Currency:CHFEUR""), IF($D7=""Libra Esterlina"", 'Original Data'!F7*GOOGLEFINANCE(""Curre"&"ncy:GBPEUR""), IF($D7=""Iene"",'Original Data'!F7*GOOGLEFINANCE(""Currency:JPYEUR""), IF($D7=""HKD"",'Original Data'!F7*GOOGLEFINANCE(""Currency:HKDEUR""), IF($D7=""KRW"",'Original Data'!F7*GOOGLEFINANCE(""Currency:KRWEUR""),"""")))))))"),216.25907999999998) -> 216.25908 | G7: =IFERROR(__xludf.DUMMYFUNCTION("IF($D7=""Euro"",'Original Data'!G7, IF($D7=""Dolar"",'Original Data'!G7*GOOGLEFINANCE(""Currency:USDEUR""), IF($D7=""Franco Suíço"",'Original Data'!G7*GOOGLEFINANCE(""Currency:CHFEUR""), IF($D7=""Libra Esterlina"", 'Original Data'!G7*GOOGLEFINANCE(""Curre"&"ncy:GBPEUR""), IF($D7=""Iene"",'Original Data'!G7*GOOGLEFINANCE(""Currency:JPYEUR""), IF($D7=""HKD"",'Original Data'!G7*GOOGLEFINANCE(""Currency:HKDEUR""), IF($D7=""KRW"",'Original Data'!G7*GOOGLEFINANCE(""Currency:KRWEUR""),"""")))))))"),162.71813999999998) -> 162.71814 | H7: 4.02 | I7: 23.73 | J7: 0.0232 | K7: 0.1595 | L7: 0.1447 | M7: -% | N7: =IFERROR(__xludf.DUMMYFUNCTION("IF('Original Data'!N7=""-"",""-"", IF($D7=""Euro"",'Original Data'!N7, IF($D7=""Dolar"",'Original Data'!N7*GOOGLEFINANCE(""Currency:USDEUR""), IF($D7=""Franco Suíço"",'Original Data'!N7*GOOGLEFINANCE(""Currency:CHFEUR""), IF($D7=""Libra Esterlina"", 'Orig"&"inal Data'!N7*GOOGLEFINANCE(""Currency:GBPEUR""), IF($D7=""Iene"",'Original Data'!N7*GOOGLEFINANCE(""Currency:JPYEUR""), IF($D7=""HKD"",'Original Data'!N7*GOOGLEFINANCE(""Currency:HKDEUR""), IF($D7=""KRW"",'Original Data'!N7*GOOGLEFINANCE(""Currency:KRWEU"&"R""),""""))))))))"),9.226759999999999) -> 9.22676 | O7: =IFERROR(__xludf.DUMMYFUNCTION("IF('Original Data'!O7=""-"",""-"", IF($D7=""Euro"",'Original Data'!O7, IF($D7=""Dolar"",'Original Data'!O7*GOOGLEFINANCE(""Currency:USDEUR""), IF($D7=""Franco Suíço"",'Original Data'!O7*GOOGLEFINANCE(""Currency:CHFEUR""), IF($D7=""Libra Esterlina"", 'Orig"&"inal Data'!O7*GOOGLEFINANCE(""Currency:GBPEUR""), IF($D7=""Iene"",'Original Data'!O7*GOOGLEFINANCE(""Currency:JPYEUR""), IF($D7=""HKD"",'Original Data'!O7*GOOGLEFINANCE(""Currency:HKDEUR""), IF($D7=""KRW"",'Original Data'!O7*GOOGLEFINANCE(""Currency:KRWEU"&"R""),""""))))))))"),19.32657) -> 19.32657 | P7: =IFERROR(__xludf.DUMMYFUNCTION("IF('Original Data'!P7=""-"",""-"", IF($D7=""Euro"",'Original Data'!P7, IF($D7=""Dolar"",'Original Data'!P7*GOOGLEFINANCE(""Currency:USDEUR""), IF($D7=""Franco Suíço"",'Original Data'!P7*GOOGLEFINANCE(""Currency:CHFEUR""), IF($D7=""Libra Esterlina"", 'Orig"&"inal Data'!P7*GOOGLEFINANCE(""Currency:GBPEUR""), IF($D7=""Iene"",'Original Data'!P7*GOOGLEFINANCE(""Currency:JPYEUR""), IF($D7=""HKD"",'Original Data'!P7*GOOGLEFINANCE(""Currency:HKDEUR""), IF($D7=""KRW"",'Original Data'!P7*GOOGLEFINANCE(""Currency:KRWEU"&"R""),""""))))))))"),19.629839999999998) -> 19.62984 | Q7: =IFERROR(__xludf.DUMMYFUNCTION("IF('Original Data'!Q7=""-"",""-"", IF($D7=""Euro"",'Original Data'!Q7, IF($D7=""Dolar"",'Original Data'!Q7*GOOGLEFINANCE(""Currency:USDEUR""), IF($D7=""Franco Suíço"",'Original Data'!Q7*GOOGLEFINANCE(""Currency:CHFEUR""), IF($D7=""Libra Esterlina"", 'Orig"&"inal Data'!Q7*GOOGLEFINANCE(""Currency:GBPEUR""), IF($D7=""Iene"",'Original Data'!Q7*GOOGLEFINANCE(""Currency:JPYEUR""), IF($D7=""HKD"",'Original Data'!Q7*GOOGLEFINANCE(""Currency:HKDEUR""), IF($D7=""KRW"",'Original Data'!Q7*GOOGLEFINANCE(""Currency:KRWEU"&"R""),""""))))))))"),17.65399) -> 17.65399 | R7: =IFERROR(__xludf.DUMMYFUNCTION("IF('Original Data'!R7=""-"",""-"", IF($D7=""Euro"",'Original Data'!R7, IF($D7=""Dolar"",'Original Data'!R7*GOOGLEFINANCE(""Currency:USDEUR""), IF($D7=""Franco Suíço"",'Original Data'!R7*GOOGLEFINANCE(""Currency:CHFEUR""), IF($D7=""Libra Esterlina"", 'Orig"&"inal Data'!R7*GOOGLEFINANCE(""Currency:GBPEUR""), IF($D7=""Iene"",'Original Data'!R7*GOOGLEFINANCE(""Currency:JPYEUR""), IF($D7=""HKD"",'Original Data'!R7*GOOGLEFINANCE(""Currency:HKDEUR""), IF($D7=""KRW"",'Original Data'!R7*GOOGLEFINANCE(""Currency:KRWEU"&"R""),""""))))))))"),21.33918) -> 21.33918 | S7: =IFERROR(__xludf.DUMMYFUNCTION("IF('Original Data'!S7=""-"",""-"", IF($D7=""Euro"",'Original Data'!S7, IF($D7=""Dolar"",'Original Data'!S7*GOOGLEFINANCE(""Currency:USDEUR""), IF($D7=""Franco Suíço"",'Original Data'!S7*GOOGLEFINANCE(""Currency:CHFEUR""), IF($D7=""Libra Esterlina"", 'Orig"&"inal Data'!S7*GOOGLEFINANCE(""Currency:GBPEUR""), IF($D7=""Iene"",'Original Data'!S7*GOOGLEFINANCE(""Currency:JPYEUR""), IF($D7=""HKD"",'Original Data'!S7*GOOGLEFINANCE(""Currency:HKDEUR""), IF($D7=""KRW"",'Original Data'!S7*GOOGLEFINANCE(""Currency:KRWEU"&"R""),""""))))))))"),9.25433) -> 9.25433 | T7: =IFERROR(__xludf.DUMMYFUNCTION("IF('Original Data'!T7=""-"",""-"", IF($D7=""Euro"",'Original Data'!T7, IF($D7=""Dolar"",'Original Data'!T7*GOOGLEFINANCE(""Currency:USDEUR""), IF($D7=""Franco Suíço"",'Original Data'!T7*GOOGLEFINANCE(""Currency:CHFEUR""), IF($D7=""Libra Esterlina"", 'Orig"&"inal Data'!T7*GOOGLEFINANCE(""Currency:GBPEUR""), IF($D7=""Iene"",'Original Data'!T7*GOOGLEFINANCE(""Currency:JPYEUR""), IF($D7=""HKD"",'Original Data'!T7*GOOGLEFINANCE(""Currency:HKDEUR""), IF($D7=""KRW"",'Original Data'!T7*GOOGLEFINANCE(""Currency:KRWEU"&"R""),""""))))))))"),9.6495) -> 9.6495 | U7: =IFERROR(__xludf.DUMMYFUNCTION("IF('Original Data'!U7=""-"",""-"", IF($D7=""Euro"",'Original Data'!U7, IF($D7=""Dolar"",'Original Data'!U7*GOOGLEFINANCE(""Currency:USDEUR""), IF($D7=""Franco Suíço"",'Original Data'!U7*GOOGLEFINANCE(""Currency:CHFEUR""), IF($D7=""Libra Esterlina"", 'Orig"&"inal Data'!U7*GOOGLEFINANCE(""Currency:GBPEUR""), IF($D7=""Iene"",'Original Data'!U7*GOOGLEFINANCE(""Currency:JPYEUR""), IF($D7=""HKD"",'Original Data'!U7*GOOGLEFINANCE(""Currency:HKDEUR""), IF($D7=""KRW"",'Original Data'!U7*GOOGLEFINANCE(""Currency:KRWEU"&"R""),""""))))))))"),8.18829) -> 8.18829 | V7: =IFERROR(__xludf.DUMMYFUNCTION("IF('Original Data'!V7=""-"",""-"", IF($D7=""Euro"",'Original Data'!V7, IF($D7=""Dolar"",'Original Data'!V7*GOOGLEFINANCE(""Currency:USDEUR""), IF($D7=""Franco Suíço"",'Original Data'!V7*GOOGLEFINANCE(""Currency:CHFEUR""), IF($D7=""Libra Esterlina"", 'Orig"&"inal Data'!V7*GOOGLEFINANCE(""Currency:GBPEUR""), IF($D7=""Iene"",'Original Data'!V7*GOOGLEFINANCE(""Currency:JPYEUR""), IF($D7=""HKD"",'Original Data'!V7*GOOGLEFINANCE(""Currency:HKDEUR""), IF($D7=""KRW"",'Original Data'!V7*GOOGLEFINANCE(""Currency:KRWEU"&"R""),""""))))))))"),10.69716) -> 10.69716 | W7: C | X7: C | Y7: D/C | Z7: B-/B | AA7: C | AB7: D | AC7: 24 | AD7: 4.1 | AE7: 14.4 | AF7: 5.9 | AG7: 3
A8: HYUNDAI MOTO-GDR | B8: HYUD LI Equity | C8: USY384721251 | D8: Dolar | E8: =IFERROR(__xludf.DUMMYFUNCTION("IF($D8=""Euro"",'Original Data'!E8, IF($D8=""Dolar"",'Original Data'!E8*GOOGLEFINANCE(""Currency:USDEUR""), IF($D8=""Franco Suíço"",'Original Data'!E8*GOOGLEFINANCE(""Currency:CHFEUR""), IF($D8=""Libra Esterlina"", 'Original Data'!E8*GOOGLEFINANCE(""Curre"&"ncy:GBPEUR""), IF($D8=""Iene"",'Original Data'!E8*GOOGLEFINANCE(""Currency:JPYEUR""), IF($D8=""HKD"",'Original Data'!E8*GOOGLEFINANCE(""Currency:HKDEUR""), IF($D8=""KRW"",'Original Data'!E8*GOOGLEFINANCE(""Currency:KRWEUR""),"""")))))))"),2.9408) -> 2.9408 | F8: =IFERROR(__xludf.DUMMYFUNCTION("IF($D8=""Euro"",'Original Data'!F8, IF($D8=""Dolar"",'Original Data'!F8*GOOGLEFINANCE(""Currency:USDEUR""), IF($D8=""Franco Suíço"",'Original Data'!F8*GOOGLEFINANCE(""Currency:CHFEUR""), IF($D8=""Libra Esterlina"", 'Original Data'!F8*GOOGLEFINANCE(""Curre"&"ncy:GBPEUR""), IF($D8=""Iene"",'Original Data'!F8*GOOGLEFINANCE(""Currency:JPYEUR""), IF($D8=""HKD"",'Original Data'!F8*GOOGLEFINANCE(""Currency:HKDEUR""), IF($D8=""KRW"",'Original Data'!F8*GOOGLEFINANCE(""Currency:KRWEUR""),"""")))))))"),31.337899999999998) -> 31.3379 | G8: =IFERROR(__xludf.DUMMYFUNCTION("IF($D8=""Euro"",'Original Data'!G8, IF($D8=""Dolar"",'Original Data'!G8*GOOGLEFINANCE(""Currency:USDEUR""), IF($D8=""Franco Suíço"",'Original Data'!G8*GOOGLEFINANCE(""Currency:CHFEUR""), IF($D8=""Libra Esterlina"", 'Original Data'!G8*GOOGLEFINANCE(""Curre"&"ncy:GBPEUR""), IF($D8=""Iene"",'Original Data'!G8*GOOGLEFINANCE(""Currency:JPYEUR""), IF($D8=""HKD"",'Original Data'!G8*GOOGLEFINANCE(""Currency:HKDEUR""), IF($D8=""KRW"",'Original Data'!G8*GOOGLEFINANCE(""Currency:KRWEUR""),"""")))))))"),29.69289) -> 29.69289 | H8: 0.007846 | I8: - | J8: 0.0521 | K8: 0.025 | L8: 0.0175 | M8: 0.0428 | N8: =IFERROR(__xludf.DUMMYFUNCTION("'Original Data'!N8*GOOGLEFINANCE(""Currency:KRWEUR"")"),14.282486201516004) -> 14.282486 | O8: =IFERROR(__xludf.DUMMYFUNCTION("'Original Data'!O8*GOOGLEFINANCE(""Currency:KRWEUR"")"),72.804408277503) -> 72.804408 | P8: =IFERROR(__xludf.DUMMYFUNCTION("'Original Data'!P8*GOOGLEFINANCE(""Currency:KRWEUR"")"),79.52759193622501) -> 79.527592 | Q8: =IFERROR(__xludf.DUMMYFUNCTION("'Original Data'!Q8*GOOGLEFINANCE(""Currency:KRWEUR"")"),78.2115324952) -> 78.211533 | R8: =IFERROR(__xludf.DUMMYFUNCTION("'Original Data'!R8*GOOGLEFINANCE(""Currency:KRWEUR"")"),88.4474668105093) -> 88.447467 | S8: =IFERROR(__xludf.DUMMYFUNCTION("'Original Data'!S8*GOOGLEFINANCE(""Currency:KRWEUR"")"),4.647569911734) -> 4.6475699 | T8: =IFERROR(__xludf.DUMMYFUNCTION("'Original Data'!T8*GOOGLEFINANCE(""Currency:KRWEUR"")"),5.730498823206) -> 5.7304988 | U8: =IFERROR(__xludf.DUMMYFUNCTION("'Original Data'!U8*GOOGLEFINANCE(""Currency:KRWEUR"")"),5.098790291514) -> 5.0987903 | V8: =IFERROR(__xludf.DUMMYFUNCTION("'Original Data'!V8*GOOGLEFINANCE(""Currency:KRWEUR"")"),8.603268574472) -> 8.6032686 | W8: A- | X8: B | Y8: No Response | Z8: No Response | AA8: A- | AB8: A- | AC8: - | AD8: - | AE8: - | AF8: - | AG8: -
A9: CATERPILLAR INC | B9: CAT US Equity | C9: US1491231015 | D9: Dolar | E9: =IFERROR(__xludf.DUMMYFUNCTION("IF($D9=""Euro"",'Original Data'!E9, IF($D9=""Dolar"",'Original Data'!E9*GOOGLEFINANCE(""Currency:USDEUR""), IF($D9=""Franco Suíço"",'Original Data'!E9*GOOGLEFINANCE(""Currency:CHFEUR""), IF($D9=""Libra Esterlina"", 'Original Data'!E9*GOOGLEFINANCE(""Curre"&"ncy:GBPEUR""), IF($D9=""Iene"",'Original Data'!E9*GOOGLEFINANCE(""Currency:JPYEUR""), IF($D9=""HKD"",'Original Data'!E9*GOOGLEFINANCE(""Currency:HKDEUR""), IF($D9=""KRW"",'Original Data'!E9*GOOGLEFINANCE(""Currency:KRWEUR""),"""")))))))"),5.54157) -> 5.54157 | F9: =IFERROR(__xludf.DUMMYFUNCTION("IF($D9=""Euro"",'Original Data'!F9, IF($D9=""Dolar"",'Original Data'!F9*GOOGLEFINANCE(""Currency:USDEUR""), IF($D9=""Franco Suíço"",'Original Data'!F9*GOOGLEFINANCE(""Currency:CHFEUR""), IF($D9=""Libra Esterlina"", 'Original Data'!F9*GOOGLEFINANCE(""Curre"&"ncy:GBPEUR""), IF($D9=""Iene"",'Original Data'!F9*GOOGLEFINANCE(""Currency:JPYEUR""), IF($D9=""HKD"",'Original Data'!F9*GOOGLEFINANCE(""Currency:HKDEUR""), IF($D9=""KRW"",'Original Data'!F9*GOOGLEFINANCE(""Currency:KRWEUR""),"""")))))))"),205.55272999999997) -> 205.55273 | G9: =IFERROR(__xludf.DUMMYFUNCTION("IF($D9=""Euro"",'Original Data'!G9, IF($D9=""Dolar"",'Original Data'!G9*GOOGLEFINANCE(""Currency:USDEUR""), IF($D9=""Franco Suíço"",'Original Data'!G9*GOOGLEFINANCE(""Currency:CHFEUR""), IF($D9=""Libra Esterlina"", 'Original Data'!G9*GOOGLEFINANCE(""Curre"&"ncy:GBPEUR""), IF($D9=""Iene"",'Original Data'!G9*GOOGLEFINANCE(""Currency:JPYEUR""), IF($D9=""HKD"",'Original Data'!G9*GOOGLEFINANCE(""Currency:HKDEUR""), IF($D9=""KRW"",'Original Data'!G9*GOOGLEFINANCE(""Currency:KRWEUR""),"""")))))))"),110.16971999999998) -> 110.16972 | H9: 4.2 | I9: 18.93 | J9: 0.0199 | K9: 0.0954 | L9: 0.0623 | M9: 0.3375 | N9: =IFERROR(__xludf.DUMMYFUNCTION("IF('Original Data'!N9=""-"",""-"", IF($D9=""Euro"",'Original Data'!N9, IF($D9=""Dolar"",'Original Data'!N9*GOOGLEFINANCE(""Currency:USDEUR""), IF($D9=""Franco Suíço"",'Original Data'!N9*GOOGLEFINANCE(""Currency:CHFEUR""), IF($D9=""Libra Esterlina"", 'Orig"&"inal Data'!N9*GOOGLEFINANCE(""Currency:GBPEUR""), IF($D9=""Iene"",'Original Data'!N9*GOOGLEFINANCE(""Currency:JPYEUR""), IF($D9=""HKD"",'Original Data'!N9*GOOGLEFINANCE(""Currency:HKDEUR""), IF($D9=""KRW"",'Original Data'!N9*GOOGLEFINANCE(""Currency:KRWEU"&"R""),""""))))))))"),10.899339999999999) -> 10.89934 | O9: =IFERROR(__xludf.DUMMYFUNCTION("IF('Original Data'!O9=""-"",""-"", IF($D9=""Euro"",'Original Data'!O9, IF($D9=""Dolar"",'Original Data'!O9*GOOGLEFINANCE(""Currency:USDEUR""), IF($D9=""Franco Suíço"",'Original Data'!O9*GOOGLEFINANCE(""Currency:CHFEUR""), IF($D9=""Libra Esterlina"", 'Orig"&"inal Data'!O9*GOOGLEFINANCE(""Currency:GBPEUR""), IF($D9=""Iene"",'Original Data'!O9*GOOGLEFINANCE(""Currency:JPYEUR""), IF($D9=""HKD"",'Original Data'!O9*GOOGLEFINANCE(""Currency:HKDEUR""), IF($D9=""KRW"",'Original Data'!O9*GOOGLEFINANCE(""Currency:KRWEU"&"R""),""""))))))))"),50.287679999999995) -> 50.28768 | P9: =IFERROR(__xludf.DUMMYFUNCTION("IF('Original Data'!P9=""-"",""-"", IF($D9=""Euro"",'Original Data'!P9, IF($D9=""Dolar"",'Original Data'!P9*GOOGLEFINANCE(""Currency:USDEUR""), IF($D9=""Franco Suíço"",'Original Data'!P9*GOOGLEFINANCE(""Currency:CHFEUR""), IF($D9=""Libra Esterlina"", 'Orig"&"inal Data'!P9*GOOGLEFINANCE(""Currency:GBPEUR""), IF($D9=""Iene"",'Original Data'!P9*GOOGLEFINANCE(""Currency:JPYEUR""), IF($D9=""HKD"",'Original Data'!P9*GOOGLEFINANCE(""Currency:HKDEUR""), IF($D9=""KRW"",'Original Data'!P9*GOOGLEFINANCE(""Currency:KRWEU"&"R""),""""))))))))"),49.433009999999996) -> 49.43301 | Q9: =IFERROR(__xludf.DUMMYFUNCTION("IF('Original Data'!Q9=""-"",""-"", IF($D9=""Euro"",'Original Data'!Q9, IF($D9=""Dolar"",'Original Data'!Q9*GOOGLEFINANCE(""Currency:USDEUR""), IF($D9=""Franco Suíço"",'Original Data'!Q9*GOOGLEFINANCE(""Currency:CHFEUR""), IF($D9=""Libra Esterlina"", 'Orig"&"inal Data'!Q9*GOOGLEFINANCE(""Currency:GBPEUR""), IF($D9=""Iene"",'Original Data'!Q9*GOOGLEFINANCE(""Currency:JPYEUR""), IF($D9=""HKD"",'Original Data'!Q9*GOOGLEFINANCE(""Currency:HKDEUR""), IF($D9=""KRW"",'Original Data'!Q9*GOOGLEFINANCE(""Currency:KRWEU"&"R""),""""))))))))"),38.368249999999996) -> 38.36825 | R9: =IFERROR(__xludf.DUMMYFUNCTION("IF('Original Data'!R9=""-"",""-"", IF($D9=""Euro"",'Original Data'!R9, IF($D9=""Dolar"",'Original Data'!R9*GOOGLEFINANCE(""Currency:USDEUR""), IF($D9=""Franco Suíço"",'Original Data'!R9*GOOGLEFINANCE(""Currency:CHFEUR""), IF($D9=""Libra Esterlina"", 'Orig"&"inal Data'!R9*GOOGLEFINANCE(""Currency:GBPEUR""), IF($D9=""Iene"",'Original Data'!R9*GOOGLEFINANCE(""Currency:JPYEUR""), IF($D9=""HKD"",'Original Data'!R9*GOOGLEFINANCE(""Currency:HKDEUR""), IF($D9=""KRW"",'Original Data'!R9*GOOGLEFINANCE(""Currency:KRWEU"&"R""),""""))))))))"),46.85061999999999) -> 46.85062 | S9: =IFERROR(__xludf.DUMMYFUNCTION("IF('Original Data'!S9=""-"",""-"", IF($D9=""Euro"",'Original Data'!S9, IF($D9=""Dolar"",'Original Data'!S9*GOOGLEFINANCE(""Currency:USDEUR""), IF($D9=""Franco Suíço"",'Original Data'!S9*GOOGLEFINANCE(""Currency:CHFEUR""), IF($D9=""Libra Esterlina"", 'Orig"&"inal Data'!S9*GOOGLEFINANCE(""Currency:GBPEUR""), IF($D9=""Iene"",'Original Data'!S9*GOOGLEFINANCE(""Currency:JPYEUR""), IF($D9=""HKD"",'Original Data'!S9*GOOGLEFINANCE(""Currency:HKDEUR""), IF($D9=""KRW"",'Original Data'!S9*GOOGLEFINANCE(""Currency:KRWEU"&"R""),""""))))))))"),10.504169999999998) -> 10.50417 | T9: =IFERROR(__xludf.DUMMYFUNCTION("IF('Original Data'!T9=""-"",""-"", IF($D9=""Euro"",'Original Data'!T9, IF($D9=""Dolar"",'Original Data'!T9*GOOGLEFINANCE(""Currency:USDEUR""), IF($D9=""Franco Suíço"",'Original Data'!T9*GOOGLEFINANCE(""Currency:CHFEUR""), IF($D9=""Libra Esterlina"", 'Orig"&"inal Data'!T9*GOOGLEFINANCE(""Currency:GBPEUR""), IF($D9=""Iene"",'Original Data'!T9*GOOGLEFINANCE(""Currency:JPYEUR""), IF($D9=""HKD"",'Original Data'!T9*GOOGLEFINANCE(""Currency:HKDEUR""), IF($D9=""KRW"",'Original Data'!T9*GOOGLEFINANCE(""Currency:KRWEU"&"R""),""""))))))))"),10.17333) -> 10.17333 | U9: =IFERROR(__xludf.DUMMYFUNCTION("IF('Original Data'!U9=""-"",""-"", IF($D9=""Euro"",'Original Data'!U9, IF($D9=""Dolar"",'Original Data'!U9*GOOGLEFINANCE(""Currency:USDEUR""), IF($D9=""Franco Suíço"",'Original Data'!U9*GOOGLEFINANCE(""Currency:CHFEUR""), IF($D9=""Libra Esterlina"", 'Orig"&"inal Data'!U9*GOOGLEFINANCE(""Currency:GBPEUR""), IF($D9=""Iene"",'Original Data'!U9*GOOGLEFINANCE(""Currency:JPYEUR""), IF($D9=""HKD"",'Original Data'!U9*GOOGLEFINANCE(""Currency:HKDEUR""), IF($D9=""KRW"",'Original Data'!U9*GOOGLEFINANCE(""Currency:KRWEU"&"R""),""""))))))))"),6.80979) -> 6.80979 | V9: =IFERROR(__xludf.DUMMYFUNCTION("IF('Original Data'!V9=""-"",""-"", IF($D9=""Euro"",'Original Data'!V9, IF($D9=""Dolar"",'Original Data'!V9*GOOGLEFINANCE(""Currency:USDEUR""), IF($D9=""Franco Suíço"",'Original Data'!V9*GOOGLEFINANCE(""Currency:CHFEUR""), IF($D9=""Libra Esterlina"", 'Orig"&"inal Data'!V9*GOOGLEFINANCE(""Currency:GBPEUR""), IF($D9=""Iene"",'Original Data'!V9*GOOGLEFINANCE(""Currency:JPYEUR""), IF($D9=""HKD"",'Original Data'!V9*GOOGLEFINANCE(""Currency:HKDEUR""), IF($D9=""KRW"",'Original Data'!V9*GOOGLEFINANCE(""Currency:KRWEU"&"R""),""""))))))))"),8.56508) -> 8.56508 | W9: No Response | X9: No Response | Y9: - | Z9: - | AA9: No Response | AB9: No Response | AC9: 34 | AD9: 7.2 | AE9: 18.5 | AF9: 8.6 | AG9: 4
A10: ALIBABA GRP-ADR | B10: BABA US Equity | C10: US01609W1027 | D10: Dolar | E10: =IFERROR(__xludf.DUMMYFUNCTION("IF($D10=""Euro"",'Original Data'!E10, IF($D10=""Dolar"",'Original Data'!E10*GOOGLEFINANCE(""Currency:USDEUR""), IF($D10=""Franco Suíço"",'Original Data'!E10*GOOGLEFINANCE(""Currency:CHFEUR""), IF($D10=""Libra Esterlina"", 'Original Data'!E10*GOOGLEFINANCE"&"(""Currency:GBPEUR""), IF($D10=""Iene"",'Original Data'!E10*GOOGLEFINANCE(""Currency:JPYEUR""), IF($D10=""HKD"",'Original Data'!E10*GOOGLEFINANCE(""Currency:HKDEUR""), IF($D10=""KRW"",'Original Data'!E10*GOOGLEFINANCE(""Currency:KRWEUR""),"""")))))))"),78.92371999999999) -> 78.92372 | F10: =IFERROR(__xludf.DUMMYFUNCTION("IF($D10=""Euro"",'Original Data'!F10, IF($D10=""Dolar"",'Original Data'!F10*GOOGLEFINANCE(""Currency:USDEUR""), IF($D10=""Franco Suíço"",'Original Data'!F10*GOOGLEFINANCE(""Currency:CHFEUR""), IF($D10=""Libra Esterlina"", 'Original Data'!F10*GOOGLEFINANCE"&"(""Currency:GBPEUR""), IF($D10=""Iene"",'Original Data'!F10*GOOGLEFINANCE(""Currency:JPYEUR""), IF($D10=""HKD"",'Original Data'!F10*GOOGLEFINANCE(""Currency:HKDEUR""), IF($D10=""KRW"",'Original Data'!F10*GOOGLEFINANCE(""Currency:KRWEUR""),"""")))))))"),95.14407) -> 95.14407 | G10: =IFERROR(__xludf.DUMMYFUNCTION("IF($D10=""Euro"",'Original Data'!G10, IF($D10=""Dolar"",'Original Data'!G10*GOOGLEFINANCE(""Currency:USDEUR""), IF($D10=""Franco Suíço"",'Original Data'!G10*GOOGLEFINANCE(""Currency:CHFEUR""), IF($D10=""Libra Esterlina"", 'Original Data'!G10*GOOGLEFINANCE"&"(""Currency:GBPEUR""), IF($D10=""Iene"",'Original Data'!G10*GOOGLEFINANCE(""Currency:JPYEUR""), IF($D10=""HKD"",'Original Data'!G10*GOOGLEFINANCE(""Currency:HKDEUR""), IF($D10=""KRW"",'Original Data'!G10*GOOGLEFINANCE(""Currency:KRWEUR""),"""")))))))"),259.00176999999996) -> 259.00177 | H10: 35.92 | I10: 30.63 | J10: -% | K10: 0.153 | L10: 0.1083 | M10: 0.2004 | N10: =IFERROR(__xludf.DUMMYFUNCTION("'Original Data'!N10*GOOGLEFINANCE(""Currency:CNYEUR"")"),1.26430772475) -> 1.2643077 | O10: =IFERROR(__xludf.DUMMYFUNCTION("'Original Data'!O10*GOOGLEFINANCE(""Currency:CNYEUR"")"),36.161512804832405) -> 36.161513 | P10: =IFERROR(__xludf.DUMMYFUNCTION("'Original Data'!P10*GOOGLEFINANCE(""Currency:CNYEUR"")"),54.451060597221606) -> 54.451061 | Q10: =IFERROR(__xludf.DUMMYFUNCTION("'Original Data'!Q10*GOOGLEFINANCE(""Currency:CNYEUR"")"),73.6493205360054) -> 73.649321 | R10: =IFERROR(__xludf.DUMMYFUNCTION("'Original Data'!R10*GOOGLEFINANCE(""Currency:CNYEUR"")"),103.6427455517946) -> 103.64275 | S10: =IFERROR(__xludf.DUMMYFUNCTION("'Original Data'!S10*GOOGLEFINANCE(""Currency:CNYEUR"")"),15.748217019486) -> 15.748217 | T10: =IFERROR(__xludf.DUMMYFUNCTION("'Original Data'!T10*GOOGLEFINANCE(""Currency:CNYEUR"")"),17.6198259290502) -> 17.619826 | U10: =IFERROR(__xludf.DUMMYFUNCTION("'Original Data'!U10*GOOGLEFINANCE(""Currency:CNYEUR"")"),22.780513323012602) -> 22.780513 | V10: =IFERROR(__xludf.DUMMYFUNCTION("'Original Data'!V10*GOOGLEFINANCE(""Currency:CNYEUR"")"),28.442155560598806) -> 28.442156 | W10: No Response | X10: No Response | Y10: No Response | Z10: No Response | AA10: - | AB10: - | AC10: - | AD10: - | AE10: - | AF10: - | AG10: -
A11: STARBUCKS CORP | B11: SBUX US Equity | C11: US8552441094 | D11: Dolar | E11: =IFERROR(__xludf.DUMMYFUNCTION("IF($D11=""Euro"",'Original Data'!E11, IF($D11=""Dolar"",'Original Data'!E11*GOOGLEFINANCE(""Currency:USDEUR""), IF($D11=""Franco Suíço"",'Original Data'!E11*GOOGLEFINANCE(""Currency:CHFEUR""), IF($D11=""Libra Esterlina"", 'Original Data'!E11*GOOGLEFINANCE"&"(""Currency:GBPEUR""), IF($D11=""Iene"",'Original Data'!E11*GOOGLEFINANCE(""Currency:JPYEUR""), IF($D11=""HKD"",'Original Data'!E11*GOOGLEFINANCE(""Currency:HKDEUR""), IF($D11=""KRW"",'Original Data'!E11*GOOGLEFINANCE(""Currency:KRWEUR""),"""")))))))"),0.29408) -> 0.29408 | F11: =IFERROR(__xludf.DUMMYFUNCTION("IF($D11=""Euro"",'Original Data'!F11, IF($D11=""Dolar"",'Original Data'!F11*GOOGLEFINANCE(""Currency:USDEUR""), IF($D11=""Franco Suíço"",'Original Data'!F11*GOOGLEFINANCE(""Currency:CHFEUR""), IF($D11=""Libra Esterlina"", 'Original Data'!F11*GOOGLEFINANCE"&"(""Currency:GBPEUR""), IF($D11=""Iene"",'Original Data'!F11*GOOGLEFINANCE(""Currency:JPYEUR""), IF($D11=""HKD"",'Original Data'!F11*GOOGLEFINANCE(""Currency:HKDEUR""), IF($D11=""KRW"",'Original Data'!F11*GOOGLEFINANCE(""Currency:KRWEUR""),"""")))))))"),79.82433999999999) -> 79.82434 | G11: =IFERROR(__xludf.DUMMYFUNCTION("IF($D11=""Euro"",'Original Data'!G11, IF($D11=""Dolar"",'Original Data'!G11*GOOGLEFINANCE(""Currency:USDEUR""), IF($D11=""Franco Suíço"",'Original Data'!G11*GOOGLEFINANCE(""Currency:CHFEUR""), IF($D11=""Libra Esterlina"", 'Original Data'!G11*GOOGLEFINANCE"&"(""Currency:GBPEUR""), IF($D11=""Iene"",'Original Data'!G11*GOOGLEFINANCE(""Currency:JPYEUR""), IF($D11=""HKD"",'Original Data'!G11*GOOGLEFINANCE(""Currency:HKDEUR""), IF($D11=""KRW"",'Original Data'!G11*GOOGLEFINANCE(""Currency:KRWEUR""),"""")))))))"),91.82647999999999) -> 91.82648 | H11: 10.13 | I11: 23.71 | J11: 0.0223 | K11: 0.2031 | L11: 0.1481 | M11: -% | N11: =IFERROR(__xludf.DUMMYFUNCTION("IF('Original Data'!N11=""-"",""-"", IF($D11=""Euro"",'Original Data'!N11, IF($D11=""Dolar"",'Original Data'!N11*GOOGLEFINANCE(""Currency:USDEUR""), IF($D11=""Franco Suíço"",'Original Data'!N11*GOOGLEFINANCE(""Currency:CHFEUR""), IF($D11=""Libra Esterlina"&""", 'Original Data'!N11*GOOGLEFINANCE(""Currency:GBPEUR""), IF($D11=""Iene"",'Original Data'!N11*GOOGLEFINANCE(""Currency:JPYEUR""), IF($D11=""HKD"",'Original Data'!N11*GOOGLEFINANCE(""Currency:HKDEUR""), IF($D11=""KRW"",'Original Data'!N11*GOOGLEFINANCE("&"""Currency:KRWEUR""),""""))))))))"),3.2808299999999995) -> 3.28083 | O11: =IFERROR(__xludf.DUMMYFUNCTION("IF('Original Data'!O11=""-"",""-"", IF($D11=""Euro"",'Original Data'!O11, IF($D11=""Dolar"",'Original Data'!O11*GOOGLEFINANCE(""Currency:USDEUR""), IF($D11=""Franco Suíço"",'Original Data'!O11*GOOGLEFINANCE(""Currency:CHFEUR""), IF($D11=""Libra Esterlina"&""", 'Original Data'!O11*GOOGLEFINANCE(""Currency:GBPEUR""), IF($D11=""Iene"",'Original Data'!O11*GOOGLEFINANCE(""Currency:JPYEUR""), IF($D11=""HKD"",'Original Data'!O11*GOOGLEFINANCE(""Currency:HKDEUR""), IF($D11=""KRW"",'Original Data'!O11*GOOGLEFINANCE("&"""Currency:KRWEUR""),""""))))))))"),22.717679999999998) -> 22.71768 | P11: =IFERROR(__xludf.DUMMYFUNCTION("IF('Original Data'!P11=""-"",""-"", IF($D11=""Euro"",'Original Data'!P11, IF($D11=""Dolar"",'Original Data'!P11*GOOGLEFINANCE(""Currency:USDEUR""), IF($D11=""Franco Suíço"",'Original Data'!P11*GOOGLEFINANCE(""Currency:CHFEUR""), IF($D11=""Libra Esterlina"&""", 'Original Data'!P11*GOOGLEFINANCE(""Currency:GBPEUR""), IF($D11=""Iene"",'Original Data'!P11*GOOGLEFINANCE(""Currency:JPYEUR""), IF($D11=""HKD"",'Original Data'!P11*GOOGLEFINANCE(""Currency:HKDEUR""), IF($D11=""KRW"",'Original Data'!P11*GOOGLEFINANCE("&"""Currency:KRWEUR""),""""))))))))"),24.353499999999997) -> 24.3535 | Q11: =IFERROR(__xludf.DUMMYFUNCTION("IF('Original Data'!Q11=""-"",""-"", IF($D11=""Euro"",'Original Data'!Q11, IF($D11=""Dolar"",'Original Data'!Q11*GOOGLEFINANCE(""Currency:USDEUR""), IF($D11=""Franco Suíço"",'Original Data'!Q11*GOOGLEFINANCE(""Currency:CHFEUR""), IF($D11=""Libra Esterlina"&""", 'Original Data'!Q11*GOOGLEFINANCE(""Currency:GBPEUR""), IF($D11=""Iene"",'Original Data'!Q11*GOOGLEFINANCE(""Currency:JPYEUR""), IF($D11=""HKD"",'Original Data'!Q11*GOOGLEFINANCE(""Currency:HKDEUR""), IF($D11=""KRW"",'Original Data'!Q11*GOOGLEFINANCE("&"""Currency:KRWEUR""),""""))))))))"),21.60569) -> 21.60569 | R11: =IFERROR(__xludf.DUMMYFUNCTION("IF('Original Data'!R11=""-"",""-"", IF($D11=""Euro"",'Original Data'!R11, IF($D11=""Dolar"",'Original Data'!R11*GOOGLEFINANCE(""Currency:USDEUR""), IF($D11=""Franco Suíço"",'Original Data'!R11*GOOGLEFINANCE(""Currency:CHFEUR""), IF($D11=""Libra Esterlina"&""", 'Original Data'!R11*GOOGLEFINANCE(""Currency:GBPEUR""), IF($D11=""Iene"",'Original Data'!R11*GOOGLEFINANCE(""Currency:JPYEUR""), IF($D11=""HKD"",'Original Data'!R11*GOOGLEFINANCE(""Currency:HKDEUR""), IF($D11=""KRW"",'Original Data'!R11*GOOGLEFINANCE("&"""Currency:KRWEUR""),""""))))))))"),26.706139999999998) -> 26.70614 | S11: =IFERROR(__xludf.DUMMYFUNCTION("IF('Original Data'!S11=""-"",""-"", IF($D11=""Euro"",'Original Data'!S11, IF($D11=""Dolar"",'Original Data'!S11*GOOGLEFINANCE(""Currency:USDEUR""), IF($D11=""Franco Suíço"",'Original Data'!S11*GOOGLEFINANCE(""Currency:CHFEUR""), IF($D11=""Libra Esterlina"&""", 'Original Data'!S11*GOOGLEFINANCE(""Currency:GBPEUR""), IF($D11=""Iene"",'Original Data'!S11*GOOGLEFINANCE(""Currency:JPYEUR""), IF($D11=""HKD"",'Original Data'!S11*GOOGLEFINANCE(""Currency:HKDEUR""), IF($D11=""KRW"",'Original Data'!S11*GOOGLEFINANCE("&"""Currency:KRWEUR""),""""))))))))"),4.75123) -> 4.75123 | T11: =IFERROR(__xludf.DUMMYFUNCTION("IF('Original Data'!T11=""-"",""-"", IF($D11=""Euro"",'Original Data'!T11, IF($D11=""Dolar"",'Original Data'!T11*GOOGLEFINANCE(""Currency:USDEUR""), IF($D11=""Franco Suíço"",'Original Data'!T11*GOOGLEFINANCE(""Currency:CHFEUR""), IF($D11=""Libra Esterlina"&""", 'Original Data'!T11*GOOGLEFINANCE(""Currency:GBPEUR""), IF($D11=""Iene"",'Original Data'!T11*GOOGLEFINANCE(""Currency:JPYEUR""), IF($D11=""HKD"",'Original Data'!T11*GOOGLEFINANCE(""Currency:HKDEUR""), IF($D11=""KRW"",'Original Data'!T11*GOOGLEFINANCE("&"""Currency:KRWEUR""),""""))))))))"),4.916649999999999) -> 4.91665 | U11: =IFERROR(__xludf.DUMMYFUNCTION("IF('Original Data'!U11=""-"",""-"", IF($D11=""Euro"",'Original Data'!U11, IF($D11=""Dolar"",'Original Data'!U11*GOOGLEFINANCE(""Currency:USDEUR""), IF($D11=""Franco Suíço"",'Original Data'!U11*GOOGLEFINANCE(""Currency:CHFEUR""), IF($D11=""Libra Esterlina"&""", 'Original Data'!U11*GOOGLEFINANCE(""Currency:GBPEUR""), IF($D11=""Iene"",'Original Data'!U11*GOOGLEFINANCE(""Currency:JPYEUR""), IF($D11=""HKD"",'Original Data'!U11*GOOGLEFINANCE(""Currency:HKDEUR""), IF($D11=""KRW"",'Original Data'!U11*GOOGLEFINANCE("&"""Currency:KRWEUR""),""""))))))))"),3.8781799999999995) -> 3.87818 | V11: =IFERROR(__xludf.DUMMYFUNCTION("IF('Original Data'!V11=""-"",""-"", IF($D11=""Euro"",'Original Data'!V11, IF($D11=""Dolar"",'Original Data'!V11*GOOGLEFINANCE(""Currency:USDEUR""), IF($D11=""Franco Suíço"",'Original Data'!V11*GOOGLEFINANCE(""Currency:CHFEUR""), IF($D11=""Libra Esterlina"&""", 'Original Data'!V11*GOOGLEFINANCE(""Currency:GBPEUR""), IF($D11=""Iene"",'Original Data'!V11*GOOGLEFINANCE(""Currency:JPYEUR""), IF($D11=""HKD"",'Original Data'!V11*GOOGLEFINANCE(""Currency:HKDEUR""), IF($D11=""KRW"",'Original Data'!V11*GOOGLEFINANCE("&"""Currency:KRWEUR""),""""))))))))"),6.837359999999999) -> 6.83736 | W11: D | X11: B | Y11: D/C | Z11: D/B- | AA11: B- | AB11: B | AC11: 25 | AD11: 6.1 | AE11: 14.2 | AF11: 4.3 | AG11: 2
A12: VIDRALA | B12: VID SM Equity | C12: ES0183746314 | D12: Euro | E12: =IFERROR(__xludf.DUMMYFUNCTION("IF($D12=""Euro"",'Original Data'!E12, IF($D12=""Dolar"",'Original Data'!E12*GOOGLEFINANCE(""Currency:USDEUR""), IF($D12=""Franco Suíço"",'Original Data'!E12*GOOGLEFINANCE(""Currency:CHFEUR""), IF($D12=""Libra Esterlina"", 'Original Data'!E12*GOOGLEFINANCE"&"(""Currency:GBPEUR""), IF($D12=""Iene"",'Original Data'!E12*GOOGLEFINANCE(""Currency:JPYEUR""), IF($D12=""HKD"",'Original Data'!E12*GOOGLEFINANCE(""Currency:HKDEUR""), IF($D12=""KRW"",'Original Data'!E12*GOOGLEFINANCE(""Currency:KRWEUR""),"""")))))))"),4.6) -> 4.6 | F12: =IFERROR(__xludf.DUMMYFUNCTION("IF($D12=""Euro"",'Original Data'!F12, IF($D12=""Dolar"",'Original Data'!F12*GOOGLEFINANCE(""Currency:USDEUR""), IF($D12=""Franco Suíço"",'Original Data'!F12*GOOGLEFINANCE(""Currency:CHFEUR""), IF($D12=""Libra Esterlina"", 'Original Data'!F12*GOOGLEFINANCE"&"(""Currency:GBPEUR""), IF($D12=""Iene"",'Original Data'!F12*GOOGLEFINANCE(""Currency:JPYEUR""), IF($D12=""HKD"",'Original Data'!F12*GOOGLEFINANCE(""Currency:HKDEUR""), IF($D12=""KRW"",'Original Data'!F12*GOOGLEFINANCE(""Currency:KRWEUR""),"""")))))))"),64.8) -> 64.8 | G12: =IFERROR(__xludf.DUMMYFUNCTION("IF($D12=""Euro"",'Original Data'!G12, IF($D12=""Dolar"",'Original Data'!G12*GOOGLEFINANCE(""Currency:USDEUR""), IF($D12=""Franco Suíço"",'Original Data'!G12*GOOGLEFINANCE(""Currency:CHFEUR""), IF($D12=""Libra Esterlina"", 'Original Data'!G12*GOOGLEFINANCE"&"(""Currency:GBPEUR""), IF($D12=""Iene"",'Original Data'!G12*GOOGLEFINANCE(""Currency:JPYEUR""), IF($D12=""HKD"",'Original Data'!G12*GOOGLEFINANCE(""Currency:HKDEUR""), IF($D12=""KRW"",'Original Data'!G12*GOOGLEFINANCE(""Currency:KRWEUR""),"""")))))))"),1.93) -> 1.93 | H12: 0.03867 | I12: 13.52 | J12: 0.0176 | K12: 0.1195 | L12: 0.0908 | M12: 0.1921 | N12: =IFERROR(__xludf.DUMMYFUNCTION("IF('Original Data'!N12=""-"",""-"", IF($D12=""Euro"",'Original Data'!N12, IF($D12=""Dolar"",'Original Data'!N12*GOOGLEFINANCE(""Currency:USDEUR""), IF($D12=""Franco Suíço"",'Original Data'!N12*GOOGLEFINANCE(""Currency:CHFEUR""), IF($D12=""Libra Esterlina"&""", 'Original Data'!N12*GOOGLEFINANCE(""Currency:GBPEUR""), IF($D12=""Iene"",'Original Data'!N12*GOOGLEFINANCE(""Currency:JPYEUR""), IF($D12=""HKD"",'Original Data'!N12*GOOGLEFINANCE(""Currency:HKDEUR""), IF($D12=""KRW"",'Original Data'!N12*GOOGLEFINANCE("&"""Currency:KRWEUR""),""""))))))))"),4.88) -> 4.88 | O12: =IFERROR(__xludf.DUMMYFUNCTION("IF('Original Data'!O12=""-"",""-"", IF($D12=""Euro"",'Original Data'!O12, IF($D12=""Dolar"",'Original Data'!O12*GOOGLEFINANCE(""Currency:USDEUR""), IF($D12=""Franco Suíço"",'Original Data'!O12*GOOGLEFINANCE(""Currency:CHFEUR""), IF($D12=""Libra Esterlina"&""", 'Original Data'!O12*GOOGLEFINANCE(""Currency:GBPEUR""), IF($D12=""Iene"",'Original Data'!O12*GOOGLEFINANCE(""Currency:JPYEUR""), IF($D12=""HKD"",'Original Data'!O12*GOOGLEFINANCE(""Currency:HKDEUR""), IF($D12=""KRW"",'Original Data'!O12*GOOGLEFINANCE("&"""Currency:KRWEUR""),""""))))))))"),0.95543) -> 0.95543 | P12: =IFERROR(__xludf.DUMMYFUNCTION("IF('Original Data'!P12=""-"",""-"", IF($D12=""Euro"",'Original Data'!P12, IF($D12=""Dolar"",'Original Data'!P12*GOOGLEFINANCE(""Currency:USDEUR""), IF($D12=""Franco Suíço"",'Original Data'!P12*GOOGLEFINANCE(""Currency:CHFEUR""), IF($D12=""Libra Esterlina"&""", 'Original Data'!P12*GOOGLEFINANCE(""Currency:GBPEUR""), IF($D12=""Iene"",'Original Data'!P12*GOOGLEFINANCE(""Currency:JPYEUR""), IF($D12=""HKD"",'Original Data'!P12*GOOGLEFINANCE(""Currency:HKDEUR""), IF($D12=""KRW"",'Original Data'!P12*GOOGLEFINANCE("&"""Currency:KRWEUR""),""""))))))))"),1.01) -> 1.01 | Q12: =IFERROR(__xludf.DUMMYFUNCTION("IF('Original Data'!Q12=""-"",""-"", IF($D12=""Euro"",'Original Data'!Q12, IF($D12=""Dolar"",'Original Data'!Q12*GOOGLEFINANCE(""Currency:USDEUR""), IF($D12=""Franco Suíço"",'Original Data'!Q12*GOOGLEFINANCE(""Currency:CHFEUR""), IF($D12=""Libra Esterlina"&""", 'Original Data'!Q12*GOOGLEFINANCE(""Currency:GBPEUR""), IF($D12=""Iene"",'Original Data'!Q12*GOOGLEFINANCE(""Currency:JPYEUR""), IF($D12=""HKD"",'Original Data'!Q12*GOOGLEFINANCE(""Currency:HKDEUR""), IF($D12=""KRW"",'Original Data'!Q12*GOOGLEFINANCE("&"""Currency:KRWEUR""),""""))))))))"),0.98892) -> 0.98892 | R12: =IFERROR(__xludf.DUMMYFUNCTION("IF('Original Data'!R12=""-"",""-"", IF($D12=""Euro"",'Original Data'!R12, IF($D12=""Dolar"",'Original Data'!R12*GOOGLEFINANCE(""Currency:USDEUR""), IF($D12=""Franco Suíço"",'Original Data'!R12*GOOGLEFINANCE(""Currency:CHFEUR""), IF($D12=""Libra Esterlina"&""", 'Original Data'!R12*GOOGLEFINANCE(""Currency:GBPEUR""), IF($D12=""Iene"",'Original Data'!R12*GOOGLEFINANCE(""Currency:JPYEUR""), IF($D12=""HKD"",'Original Data'!R12*GOOGLEFINANCE(""Currency:HKDEUR""), IF($D12=""KRW"",'Original Data'!R12*GOOGLEFINANCE("&"""Currency:KRWEUR""),""""))))))))"),1.08) -> 1.08 | S12: =IFERROR(__xludf.DUMMYFUNCTION("IF('Original Data'!S12=""-"",""-"", IF($D12=""Euro"",'Original Data'!S12, IF($D12=""Dolar"",'Original Data'!S12*GOOGLEFINANCE(""Currency:USDEUR""), IF($D12=""Franco Suíço"",'Original Data'!S12*GOOGLEFINANCE(""Currency:CHFEUR""), IF($D12=""Libra Esterlina"&""", 'Original Data'!S12*GOOGLEFINANCE(""Currency:GBPEUR""), IF($D12=""Iene"",'Original Data'!S12*GOOGLEFINANCE(""Currency:JPYEUR""), IF($D12=""HKD"",'Original Data'!S12*GOOGLEFINANCE(""Currency:HKDEUR""), IF($D12=""KRW"",'Original Data'!S12*GOOGLEFINANCE("&"""Currency:KRWEUR""),""""))))))))"),0.21737) -> 0.21737 | T12: =IFERROR(__xludf.DUMMYFUNCTION("IF('Original Data'!T12=""-"",""-"", IF($D12=""Euro"",'Original Data'!T12, IF($D12=""Dolar"",'Original Data'!T12*GOOGLEFINANCE(""Currency:USDEUR""), IF($D12=""Franco Suíço"",'Original Data'!T12*GOOGLEFINANCE(""Currency:CHFEUR""), IF($D12=""Libra Esterlina"&""", 'Original Data'!T12*GOOGLEFINANCE(""Currency:GBPEUR""), IF($D12=""Iene"",'Original Data'!T12*GOOGLEFINANCE(""Currency:JPYEUR""), IF($D12=""HKD"",'Original Data'!T12*GOOGLEFINANCE(""Currency:HKDEUR""), IF($D12=""KRW"",'Original Data'!T12*GOOGLEFINANCE("&"""Currency:KRWEUR""),""""))))))))"),0.25832) -> 0.25832 | U12: =IFERROR(__xludf.DUMMYFUNCTION("IF('Original Data'!U12=""-"",""-"", IF($D12=""Euro"",'Original Data'!U12, IF($D12=""Dolar"",'Original Data'!U12*GOOGLEFINANCE(""Currency:USDEUR""), IF($D12=""Franco Suíço"",'Original Data'!U12*GOOGLEFINANCE(""Currency:CHFEUR""), IF($D12=""Libra Esterlina"&""", 'Original Data'!U12*GOOGLEFINANCE(""Currency:GBPEUR""), IF($D12=""Iene"",'Original Data'!U12*GOOGLEFINANCE(""Currency:JPYEUR""), IF($D12=""HKD"",'Original Data'!U12*GOOGLEFINANCE(""Currency:HKDEUR""), IF($D12=""KRW"",'Original Data'!U12*GOOGLEFINANCE("&"""Currency:KRWEUR""),""""))))))))"),0.25789) -> 0.25789 | V12: =IFERROR(__xludf.DUMMYFUNCTION("IF('Original Data'!V12=""-"",""-"", IF($D12=""Euro"",'Original Data'!V12, IF($D12=""Dolar"",'Original Data'!V12*GOOGLEFINANCE(""Currency:USDEUR""), IF($D12=""Franco Suíço"",'Original Data'!V12*GOOGLEFINANCE(""Currency:CHFEUR""), IF($D12=""Libra Esterlina"&""", 'Original Data'!V12*GOOGLEFINANCE(""Currency:GBPEUR""), IF($D12=""Iene"",'Original Data'!V12*GOOGLEFINANCE(""Currency:JPYEUR""), IF($D12=""HKD"",'Original Data'!V12*GOOGLEFINANCE(""Currency:HKDEUR""), IF($D12=""KRW"",'Original Data'!V12*GOOGLEFINANCE("&"""Currency:KRWEUR""),""""))))))))"),0.23076) -> 0.23076 | W12: No Response | X12: B | Y12: - | Z12: - | AA12: No Response | AB12: B | AC12: - | AD12: - | AE12: - | AF12: - | AG12: -
A13: ROYAL DUTCH SH-A | B13: RDSA NA Equity | C13: GB00B03MLX29 | D13: Euro | E13: =IFERROR(__xludf.DUMMYFUNCTION("IF($D13=""Euro"",'Original Data'!E13, IF($D13=""Dolar"",'Original Data'!E13*GOOGLEFINANCE(""Currency:USDEUR""), IF($D13=""Franco Suíço"",'Original Data'!E13*GOOGLEFINANCE(""Currency:CHFEUR""), IF($D13=""Libra Esterlina"", 'Original Data'!E13*GOOGLEFINANCE"&"(""Currency:GBPEUR""), IF($D13=""Iene"",'Original Data'!E13*GOOGLEFINANCE(""Currency:JPYEUR""), IF($D13=""HKD"",'Original Data'!E13*GOOGLEFINANCE(""Currency:HKDEUR""), IF($D13=""KRW"",'Original Data'!E13*GOOGLEFINANCE(""Currency:KRWEUR""),"""")))))))"),26.44) -> 26.44 | F13: =IFERROR(__xludf.DUMMYFUNCTION("IF($D13=""Euro"",'Original Data'!F13, IF($D13=""Dolar"",'Original Data'!F13*GOOGLEFINANCE(""Currency:USDEUR""), IF($D13=""Franco Suíço"",'Original Data'!F13*GOOGLEFINANCE(""Currency:CHFEUR""), IF($D13=""Libra Esterlina"", 'Original Data'!F13*GOOGLEFINANCE"&"(""Currency:GBPEUR""), IF($D13=""Iene"",'Original Data'!F13*GOOGLEFINANCE(""Currency:JPYEUR""), IF($D13=""HKD"",'Original Data'!F13*GOOGLEFINANCE(""Currency:HKDEUR""), IF($D13=""KRW"",'Original Data'!F13*GOOGLEFINANCE(""Currency:KRWEUR""),"""")))))))"),24.14) -> 24.14 | G13: =IFERROR(__xludf.DUMMYFUNCTION("IF($D13=""Euro"",'Original Data'!G13, IF($D13=""Dolar"",'Original Data'!G13*GOOGLEFINANCE(""Currency:USDEUR""), IF($D13=""Franco Suíço"",'Original Data'!G13*GOOGLEFINANCE(""Currency:CHFEUR""), IF($D13=""Libra Esterlina"", 'Original Data'!G13*GOOGLEFINANCE"&"(""Currency:GBPEUR""), IF($D13=""Iene"",'Original Data'!G13*GOOGLEFINANCE(""Currency:JPYEUR""), IF($D13=""HKD"",'Original Data'!G13*GOOGLEFINANCE(""Currency:HKDEUR""), IF($D13=""KRW"",'Original Data'!G13*GOOGLEFINANCE(""Currency:KRWEUR""),"""")))))))"),189.846) -> 189.846 | H13: 15.264 | I13: 10.72 | J13: 0.0321 | K13: 0.0246 | L13: 0.0197 | M13: 0.0401 | N13: =IFERROR(__xludf.DUMMYFUNCTION("'Original Data'!N13*GOOGLEFINANCE(""Currency:USDEUR"")"),2.14127) -> 2.14127 | O13: =IFERROR(__xludf.DUMMYFUNCTION("'Original Data'!O13*GOOGLEFINANCE(""Currency:USDEUR"")"),356.920301) -> 356.9203 | P13: =IFERROR(__xludf.DUMMYFUNCTION("'Original Data'!P13*GOOGLEFINANCE(""Currency:USDEUR"")"),316.941963) -> 316.94196 | Q13: =IFERROR(__xludf.DUMMYFUNCTION("'Original Data'!Q13*GOOGLEFINANCE(""Currency:USDEUR"")"),165.919017) -> 165.91902 | R13: =IFERROR(__xludf.DUMMYFUNCTION("'Original Data'!R13*GOOGLEFINANCE(""Currency:USDEUR"")"),240.32217599999998) -> 240.32218 | S13: =IFERROR(__xludf.DUMMYFUNCTION("'Original Data'!S13*GOOGLEFINANCE(""Currency:USDEUR"")"),33.780602) -> 33.780602 | T13: =IFERROR(__xludf.DUMMYFUNCTION("'Original Data'!T13*GOOGLEFINANCE(""Currency:USDEUR"")"),19.709792999999998) -> 19.709793 | U13: =IFERROR(__xludf.DUMMYFUNCTION("'Original Data'!U13*GOOGLEFINANCE(""Currency:USDEUR"")"),9.886601999999998) -> 9.886602 | V13: =IFERROR(__xludf.DUMMYFUNCTION("'Original Data'!V13*GOOGLEFINANCE(""Currency:USDEUR"")"),29.163546) -> 29.163546 | W13: B | X13: B | Y13: No Response | Z13: No Response | AA13: No Response | AB13: No Response | AC13: 35 | AD13: 19.4 | AE13: 8.2 | AF13: 7.9 | AG13: 4
A14: HOLCIM LTD | B14: HOLN SW Equity | C14: CH0012214059 | D14: Franco Suíço | E14: =IFERROR(__xludf.DUMMYFUNCTION("IF($D14=""Euro"",'Original Data'!E14, IF($D14=""Dolar"",'Original Data'!E14*GOOGLEFINANCE(""Currency:USDEUR""), IF($D14=""Franco Suíço"",'Original Data'!E14*GOOGLEFINANCE(""Currency:CHFEUR""), IF($D14=""Libra Esterlina"", 'Original Data'!E14*GOOGLEFINANCE"&"(""Currency:GBPEUR""), IF($D14=""Iene"",'Original Data'!E14*GOOGLEFINANCE(""Currency:JPYEUR""), IF($D14=""HKD"",'Original Data'!E14*GOOGLEFINANCE(""Currency:HKDEUR""), IF($D14=""KRW"",'Original Data'!E14*GOOGLEFINANCE(""Currency:KRWEUR""),"""")))))))"),29.42868980541) -> 29.42869 | F14: =IFERROR(__xludf.DUMMYFUNCTION("IF($D14=""Euro"",'Original Data'!F14, IF($D14=""Dolar"",'Original Data'!F14*GOOGLEFINANCE(""Currency:USDEUR""), IF($D14=""Franco Suíço"",'Original Data'!F14*GOOGLEFINANCE(""Currency:CHFEUR""), IF($D14=""Libra Esterlina"", 'Original Data'!F14*GOOGLEFINANCE"&"(""Currency:GBPEUR""), IF($D14=""Iene"",'Original Data'!F14*GOOGLEFINANCE(""Currency:JPYEUR""), IF($D14=""HKD"",'Original Data'!F14*GOOGLEFINANCE(""Currency:HKDEUR""), IF($D14=""KRW"",'Original Data'!F14*GOOGLEFINANCE(""Currency:KRWEUR""),"""")))))))"),45.43687379518) -> 45.436874 | G14: =IFERROR(__xludf.DUMMYFUNCTION("IF($D14=""Euro"",'Original Data'!G14, IF($D14=""Dolar"",'Original Data'!G14*GOOGLEFINANCE(""Currency:USDEUR""), IF($D14=""Franco Suíço"",'Original Data'!G14*GOOGLEFINANCE(""Currency:CHFEUR""), IF($D14=""Libra Esterlina"", 'Original Data'!G14*GOOGLEFINANCE"&"(""Currency:GBPEUR""), IF($D14=""Iene"",'Original Data'!G14*GOOGLEFINANCE(""Currency:JPYEUR""), IF($D14=""HKD"",'Original Data'!G14*GOOGLEFINANCE(""Currency:HKDEUR""), IF($D14=""KRW"",'Original Data'!G14*GOOGLEFINANCE(""Currency:KRWEUR""),"""")))))))"),27.98234497044) -> 27.982345 | H14: 2.5 | I14: 12.31 | J14: -% | K14: 0.0308 | L14: 0.024 | M14: 0.0434 | N14: =IFERROR(__xludf.DUMMYFUNCTION("IF('Original Data'!N14=""-"",""-"", IF($D14=""Euro"",'Original Data'!N14, IF($D14=""Dolar"",'Original Data'!N14*GOOGLEFINANCE(""Currency:USDEUR""), IF($D14=""Franco Suíço"",'Original Data'!N14*GOOGLEFINANCE(""Currency:CHFEUR""), IF($D14=""Libra Esterlina"&""", 'Original Data'!N14*GOOGLEFINANCE(""Currency:GBPEUR""), IF($D14=""Iene"",'Original Data'!N14*GOOGLEFINANCE(""Currency:JPYEUR""), IF($D14=""HKD"",'Original Data'!N14*GOOGLEFINANCE(""Currency:HKDEUR""), IF($D14=""KRW"",'Original Data'!N14*GOOGLEFINANCE("&"""Currency:KRWEUR""),""""))))))))"),3.66997703023) -> 3.669977 | O14: =IFERROR(__xludf.DUMMYFUNCTION("IF('Original Data'!O14=""-"",""-"", IF($D14=""Euro"",'Original Data'!O14, IF($D14=""Dolar"",'Original Data'!O14*GOOGLEFINANCE(""Currency:USDEUR""), IF($D14=""Franco Suíço"",'Original Data'!O14*GOOGLEFINANCE(""Currency:CHFEUR""), IF($D14=""Libra Esterlina"&""", 'Original Data'!O14*GOOGLEFINANCE(""Currency:GBPEUR""), IF($D14=""Iene"",'Original Data'!O14*GOOGLEFINANCE(""Currency:JPYEUR""), IF($D14=""HKD"",'Original Data'!O14*GOOGLEFINANCE(""Currency:HKDEUR""), IF($D14=""KRW"",'Original Data'!O14*GOOGLEFINANCE("&"""Currency:KRWEUR""),""""))))))))"),27.027954160969998) -> 27.027954 | P14: =IFERROR(__xludf.DUMMYFUNCTION("IF('Original Data'!P14=""-"",""-"", IF($D14=""Euro"",'Original Data'!P14, IF($D14=""Dolar"",'Original Data'!P14*GOOGLEFINANCE(""Currency:USDEUR""), IF($D14=""Franco Suíço"",'Original Data'!P14*GOOGLEFINANCE(""Currency:CHFEUR""), IF($D14=""Libra Esterlina"&""", 'Original Data'!P14*GOOGLEFINANCE(""Currency:GBPEUR""), IF($D14=""Iene"",'Original Data'!P14*GOOGLEFINANCE(""Currency:JPYEUR""), IF($D14=""HKD"",'Original Data'!P14*GOOGLEFINANCE(""Currency:HKDEUR""), IF($D14=""KRW"",'Original Data'!P14*GOOGLEFINANCE("&"""Currency:KRWEUR""),""""))))))))"),26.290023122719997) -> 26.290023 | Q14: =IFERROR(__xludf.DUMMYFUNCTION("IF('Original Data'!Q14=""-"",""-"", IF($D14=""Euro"",'Original Data'!Q14, IF($D14=""Dolar"",'Original Data'!Q14*GOOGLEFINANCE(""Currency:USDEUR""), IF($D14=""Franco Suíço"",'Original Data'!Q14*GOOGLEFINANCE(""Currency:CHFEUR""), IF($D14=""Libra Esterlina"&""", 'Original Data'!Q14*GOOGLEFINANCE(""Currency:GBPEUR""), IF($D14=""Iene"",'Original Data'!Q14*GOOGLEFINANCE(""Currency:JPYEUR""), IF($D14=""HKD"",'Original Data'!Q14*GOOGLEFINANCE(""Currency:HKDEUR""), IF($D14=""KRW"",'Original Data'!Q14*GOOGLEFINANCE("&"""Currency:KRWEUR""),""""))))))))"),22.76763230014) -> 22.767632 | R14: =IFERROR(__xludf.DUMMYFUNCTION("IF('Original Data'!R14=""-"",""-"", IF($D14=""Euro"",'Original Data'!R14, IF($D14=""Dolar"",'Original Data'!R14*GOOGLEFINANCE(""Currency:USDEUR""), IF($D14=""Franco Suíço"",'Original Data'!R14*GOOGLEFINANCE(""Currency:CHFEUR""), IF($D14=""Libra Esterlina"&""", 'Original Data'!R14*GOOGLEFINANCE(""Currency:GBPEUR""), IF($D14=""Iene"",'Original Data'!R14*GOOGLEFINANCE(""Currency:JPYEUR""), IF($D14=""HKD"",'Original Data'!R14*GOOGLEFINANCE(""Currency:HKDEUR""), IF($D14=""KRW"",'Original Data'!R14*GOOGLEFINANCE("&"""Currency:KRWEUR""),""""))))))))"),26.39825300833) -> 26.398253 | S14: =IFERROR(__xludf.DUMMYFUNCTION("IF('Original Data'!S14=""-"",""-"", IF($D14=""Euro"",'Original Data'!S14, IF($D14=""Dolar"",'Original Data'!S14*GOOGLEFINANCE(""Currency:USDEUR""), IF($D14=""Franco Suíço"",'Original Data'!S14*GOOGLEFINANCE(""Currency:CHFEUR""), IF($D14=""Libra Esterlina"&""", 'Original Data'!S14*GOOGLEFINANCE(""Currency:GBPEUR""), IF($D14=""Iene"",'Original Data'!S14*GOOGLEFINANCE(""Currency:JPYEUR""), IF($D14=""HKD"",'Original Data'!S14*GOOGLEFINANCE(""Currency:HKDEUR""), IF($D14=""KRW"",'Original Data'!S14*GOOGLEFINANCE("&"""Currency:KRWEUR""),""""))))))))"),5.4114942805) -> 5.4114943 | T14: =IFERROR(__xludf.DUMMYFUNCTION("IF('Original Data'!T14=""-"",""-"", IF($D14=""Euro"",'Original Data'!T14, IF($D14=""Dolar"",'Original Data'!T14*GOOGLEFINANCE(""Currency:USDEUR""), IF($D14=""Franco Suíço"",'Original Data'!T14*GOOGLEFINANCE(""Currency:CHFEUR""), IF($D14=""Libra Esterlina"&""", 'Original Data'!T14*GOOGLEFINANCE(""Currency:GBPEUR""), IF($D14=""Iene"",'Original Data'!T14*GOOGLEFINANCE(""Currency:JPYEUR""), IF($D14=""HKD"",'Original Data'!T14*GOOGLEFINANCE(""Currency:HKDEUR""), IF($D14=""KRW"",'Original Data'!T14*GOOGLEFINANCE("&"""Currency:KRWEUR""),""""))))))))"),6.1002299162) -> 6.1002299 | U14: =IFERROR(__xludf.DUMMYFUNCTION("IF('Original Data'!U14=""-"",""-"", IF($D14=""Euro"",'Original Data'!U14, IF($D14=""Dolar"",'Original Data'!U14*GOOGLEFINANCE(""Currency:USDEUR""), IF($D14=""Franco Suíço"",'Original Data'!U14*GOOGLEFINANCE(""Currency:CHFEUR""), IF($D14=""Libra Esterlina"&""", 'Original Data'!U14*GOOGLEFINANCE(""Currency:GBPEUR""), IF($D14=""Iene"",'Original Data'!U14*GOOGLEFINANCE(""Currency:JPYEUR""), IF($D14=""HKD"",'Original Data'!U14*GOOGLEFINANCE(""Currency:HKDEUR""), IF($D14=""KRW"",'Original Data'!U14*GOOGLEFINANCE("&"""Currency:KRWEUR""),""""))))))))"),5.3918161194800005) -> 5.3918161 | V14: =IFERROR(__xludf.DUMMYFUNCTION("IF('Original Data'!V14=""-"",""-"", IF($D14=""Euro"",'Original Data'!V14, IF($D14=""Dolar"",'Original Data'!V14*GOOGLEFINANCE(""Currency:USDEUR""), IF($D14=""Franco Suíço"",'Original Data'!V14*GOOGLEFINANCE(""Currency:CHFEUR""), IF($D14=""Libra Esterlina"&""", 'Original Data'!V14*GOOGLEFINANCE(""Currency:GBPEUR""), IF($D14=""Iene"",'Original Data'!V14*GOOGLEFINANCE(""Currency:JPYEUR""), IF($D14=""HKD"",'Original Data'!V14*GOOGLEFINANCE(""Currency:HKDEUR""), IF($D14=""KRW"",'Original Data'!V14*GOOGLEFINANCE("&"""Currency:KRWEUR""),""""))))))))"),6.31668968742) -> 6.3166897 | W14: A | X14: A | Y14: - | Z14: - | AA14: A- | AB14: A- | AC14: 21 | AD14: 11.9 | AE14: 3 | AF14: 6.3 | AG14: 3
A15: MICHELIN | B15: ML FP Equity | C15: FR0000121261 | D15: Euro | E15: =IFERROR(__xludf.DUMMYFUNCTION("IF($D15=""Euro"",'Original Data'!E15, IF($D15=""Dolar"",'Original Data'!E15*GOOGLEFINANCE(""Currency:USDEUR""), IF($D15=""Franco Suíço"",'Original Data'!E15*GOOGLEFINANCE(""Currency:CHFEUR""), IF($D15=""Libra Esterlina"", 'Original Data'!E15*GOOGLEFINANCE"&"(""Currency:GBPEUR""), IF($D15=""Iene"",'Original Data'!E15*GOOGLEFINANCE(""Currency:JPYEUR""), IF($D15=""HKD"",'Original Data'!E15*GOOGLEFINANCE(""Currency:HKDEUR""), IF($D15=""KRW"",'Original Data'!E15*GOOGLEFINANCE(""Currency:KRWEUR""),"""")))))))"),31.34) -> 31.34 | F15: =IFERROR(__xludf.DUMMYFUNCTION("IF($D15=""Euro"",'Original Data'!F15, IF($D15=""Dolar"",'Original Data'!F15*GOOGLEFINANCE(""Currency:USDEUR""), IF($D15=""Franco Suíço"",'Original Data'!F15*GOOGLEFINANCE(""Currency:CHFEUR""), IF($D15=""Libra Esterlina"", 'Original Data'!F15*GOOGLEFINANCE"&"(""Currency:GBPEUR""), IF($D15=""Iene"",'Original Data'!F15*GOOGLEFINANCE(""Currency:JPYEUR""), IF($D15=""HKD"",'Original Data'!F15*GOOGLEFINANCE(""Currency:HKDEUR""), IF($D15=""KRW"",'Original Data'!F15*GOOGLEFINANCE(""Currency:KRWEUR""),"""")))))))"),123.25) -> 123.25 | G15: =IFERROR(__xludf.DUMMYFUNCTION("IF($D15=""Euro"",'Original Data'!G15, IF($D15=""Dolar"",'Original Data'!G15*GOOGLEFINANCE(""Currency:USDEUR""), IF($D15=""Franco Suíço"",'Original Data'!G15*GOOGLEFINANCE(""Currency:CHFEUR""), IF($D15=""Libra Esterlina"", 'Original Data'!G15*GOOGLEFINANCE"&"(""Currency:GBPEUR""), IF($D15=""Iene"",'Original Data'!G15*GOOGLEFINANCE(""Currency:JPYEUR""), IF($D15=""HKD"",'Original Data'!G15*GOOGLEFINANCE(""Currency:HKDEUR""), IF($D15=""KRW"",'Original Data'!G15*GOOGLEFINANCE(""Currency:KRWEUR""),"""")))))))"),21.97) -> 21.97 | H15: 0.058393 | I15: 12.4 | J15: 0.0365 | K15: 0.0664 | L15: 0.0508 | M15: 0.1219 | N15: =IFERROR(__xludf.DUMMYFUNCTION("IF('Original Data'!N15=""-"",""-"", IF($D15=""Euro"",'Original Data'!N15, IF($D15=""Dolar"",'Original Data'!N15*GOOGLEFINANCE(""Currency:USDEUR""), IF($D15=""Franco Suíço"",'Original Data'!N15*GOOGLEFINANCE(""Currency:CHFEUR""), IF($D15=""Libra Esterlina"&""", 'Original Data'!N15*GOOGLEFINANCE(""Currency:GBPEUR""), IF($D15=""Iene"",'Original Data'!N15*GOOGLEFINANCE(""Currency:JPYEUR""), IF($D15=""HKD"",'Original Data'!N15*GOOGLEFINANCE(""Currency:HKDEUR""), IF($D15=""KRW"",'Original Data'!N15*GOOGLEFINANCE("&"""Currency:KRWEUR""),""""))))))))"),10.31) -> 10.31 | O15: =IFERROR(__xludf.DUMMYFUNCTION("IF('Original Data'!O15=""-"",""-"", IF($D15=""Euro"",'Original Data'!O15, IF($D15=""Dolar"",'Original Data'!O15*GOOGLEFINANCE(""Currency:USDEUR""), IF($D15=""Franco Suíço"",'Original Data'!O15*GOOGLEFINANCE(""Currency:CHFEUR""), IF($D15=""Libra Esterlina"&""", 'Original Data'!O15*GOOGLEFINANCE(""Currency:GBPEUR""), IF($D15=""Iene"",'Original Data'!O15*GOOGLEFINANCE(""Currency:JPYEUR""), IF($D15=""HKD"",'Original Data'!O15*GOOGLEFINANCE(""Currency:HKDEUR""), IF($D15=""KRW"",'Original Data'!O15*GOOGLEFINANCE("&"""Currency:KRWEUR""),""""))))))))"),22.03) -> 22.03 | P15: =IFERROR(__xludf.DUMMYFUNCTION("IF('Original Data'!P15=""-"",""-"", IF($D15=""Euro"",'Original Data'!P15, IF($D15=""Dolar"",'Original Data'!P15*GOOGLEFINANCE(""Currency:USDEUR""), IF($D15=""Franco Suíço"",'Original Data'!P15*GOOGLEFINANCE(""Currency:CHFEUR""), IF($D15=""Libra Esterlina"&""", 'Original Data'!P15*GOOGLEFINANCE(""Currency:GBPEUR""), IF($D15=""Iene"",'Original Data'!P15*GOOGLEFINANCE(""Currency:JPYEUR""), IF($D15=""HKD"",'Original Data'!P15*GOOGLEFINANCE(""Currency:HKDEUR""), IF($D15=""KRW"",'Original Data'!P15*GOOGLEFINANCE("&"""Currency:KRWEUR""),""""))))))))"),24.14) -> 24.14 | Q15: =IFERROR(__xludf.DUMMYFUNCTION("IF('Original Data'!Q15=""-"",""-"", IF($D15=""Euro"",'Original Data'!Q15, IF($D15=""Dolar"",'Original Data'!Q15*GOOGLEFINANCE(""Currency:USDEUR""), IF($D15=""Franco Suíço"",'Original Data'!Q15*GOOGLEFINANCE(""Currency:CHFEUR""), IF($D15=""Libra Esterlina"&""", 'Original Data'!Q15*GOOGLEFINANCE(""Currency:GBPEUR""), IF($D15=""Iene"",'Original Data'!Q15*GOOGLEFINANCE(""Currency:JPYEUR""), IF($D15=""HKD"",'Original Data'!Q15*GOOGLEFINANCE(""Currency:HKDEUR""), IF($D15=""KRW"",'Original Data'!Q15*GOOGLEFINANCE("&"""Currency:KRWEUR""),""""))))))))"),20.47) -> 20.47 | R15: =IFERROR(__xludf.DUMMYFUNCTION("IF('Original Data'!R15=""-"",""-"", IF($D15=""Euro"",'Original Data'!R15, IF($D15=""Dolar"",'Original Data'!R15*GOOGLEFINANCE(""Currency:USDEUR""), IF($D15=""Franco Suíço"",'Original Data'!R15*GOOGLEFINANCE(""Currency:CHFEUR""), IF($D15=""Libra Esterlina"&""", 'Original Data'!R15*GOOGLEFINANCE(""Currency:GBPEUR""), IF($D15=""Iene"",'Original Data'!R15*GOOGLEFINANCE(""Currency:JPYEUR""), IF($D15=""HKD"",'Original Data'!R15*GOOGLEFINANCE(""Currency:HKDEUR""), IF($D15=""KRW"",'Original Data'!R15*GOOGLEFINANCE("&"""Currency:KRWEUR""),""""))))))))"),23.8) -> 23.8 | S15: =IFERROR(__xludf.DUMMYFUNCTION("IF('Original Data'!S15=""-"",""-"", IF($D15=""Euro"",'Original Data'!S15, IF($D15=""Dolar"",'Original Data'!S15*GOOGLEFINANCE(""Currency:USDEUR""), IF($D15=""Franco Suíço"",'Original Data'!S15*GOOGLEFINANCE(""Currency:CHFEUR""), IF($D15=""Libra Esterlina"&""", 'Original Data'!S15*GOOGLEFINANCE(""Currency:GBPEUR""), IF($D15=""Iene"",'Original Data'!S15*GOOGLEFINANCE(""Currency:JPYEUR""), IF($D15=""HKD"",'Original Data'!S15*GOOGLEFINANCE(""Currency:HKDEUR""), IF($D15=""KRW"",'Original Data'!S15*GOOGLEFINANCE("&"""Currency:KRWEUR""),""""))))))))"),4.12) -> 4.12 | T15: =IFERROR(__xludf.DUMMYFUNCTION("IF('Original Data'!T15=""-"",""-"", IF($D15=""Euro"",'Original Data'!T15, IF($D15=""Dolar"",'Original Data'!T15*GOOGLEFINANCE(""Currency:USDEUR""), IF($D15=""Franco Suíço"",'Original Data'!T15*GOOGLEFINANCE(""Currency:CHFEUR""), IF($D15=""Libra Esterlina"&""", 'Original Data'!T15*GOOGLEFINANCE(""Currency:GBPEUR""), IF($D15=""Iene"",'Original Data'!T15*GOOGLEFINANCE(""Currency:JPYEUR""), IF($D15=""HKD"",'Original Data'!T15*GOOGLEFINANCE(""Currency:HKDEUR""), IF($D15=""KRW"",'Original Data'!T15*GOOGLEFINANCE("&"""Currency:KRWEUR""),""""))))))))"),4.76) -> 4.76 | U15: =IFERROR(__xludf.DUMMYFUNCTION("IF('Original Data'!U15=""-"",""-"", IF($D15=""Euro"",'Original Data'!U15, IF($D15=""Dolar"",'Original Data'!U15*GOOGLEFINANCE(""Currency:USDEUR""), IF($D15=""Franco Suíço"",'Original Data'!U15*GOOGLEFINANCE(""Currency:CHFEUR""), IF($D15=""Libra Esterlina"&""", 'Original Data'!U15*GOOGLEFINANCE(""Currency:GBPEUR""), IF($D15=""Iene"",'Original Data'!U15*GOOGLEFINANCE(""Currency:JPYEUR""), IF($D15=""HKD"",'Original Data'!U15*GOOGLEFINANCE(""Currency:HKDEUR""), IF($D15=""KRW"",'Original Data'!U15*GOOGLEFINANCE("&"""Currency:KRWEUR""),""""))))))))"),3.73) -> 3.73 | V15: =IFERROR(__xludf.DUMMYFUNCTION("IF('Original Data'!V15=""-"",""-"", IF($D15=""Euro"",'Original Data'!V15, IF($D15=""Dolar"",'Original Data'!V15*GOOGLEFINANCE(""Currency:USDEUR""), IF($D15=""Franco Suíço"",'Original Data'!V15*GOOGLEFINANCE(""Currency:CHFEUR""), IF($D15=""Libra Esterlina"&""", 'Original Data'!V15*GOOGLEFINANCE(""Currency:GBPEUR""), IF($D15=""Iene"",'Original Data'!V15*GOOGLEFINANCE(""Currency:JPYEUR""), IF($D15=""HKD"",'Original Data'!V15*GOOGLEFINANCE(""Currency:HKDEUR""), IF($D15=""KRW"",'Original Data'!V15*GOOGLEFINANCE("&"""Currency:KRWEUR""),""""))))))))"),"-") -> - | W15: A- | X15: A | Y15: No Responde | Z15: Not Scored | AA15: A- | AB15: B | AC15: 13 | AD15: 3 | AE15: 4.2 | AF15: 5.4 | AG15: 2
A16: RYANAIR HLDGS | B16: RYA ID Equity | C16: IE00BYTBXV33 | D16: Euro | E16: =IFERROR(__xludf.DUMMYFUNCTION("IF($D16=""Euro"",'Original Data'!E16, IF($D16=""Dolar"",'Original Data'!E16*GOOGLEFINANCE(""Currency:USDEUR""), IF($D16=""Franco Suíço"",'Original Data'!E16*GOOGLEFINANCE(""Currency:CHFEUR""), IF($D16=""Libra Esterlina"", 'Original Data'!E16*GOOGLEFINANCE"&"(""Currency:GBPEUR""), IF($D16=""Iene"",'Original Data'!E16*GOOGLEFINANCE(""Currency:JPYEUR""), IF($D16=""HKD"",'Original Data'!E16*GOOGLEFINANCE(""Currency:HKDEUR""), IF($D16=""KRW"",'Original Data'!E16*GOOGLEFINANCE(""Currency:KRWEUR""),"""")))))))"),1.97) -> 1.97 | F16: =IFERROR(__xludf.DUMMYFUNCTION("IF($D16=""Euro"",'Original Data'!F16, IF($D16=""Dolar"",'Original Data'!F16*GOOGLEFINANCE(""Currency:USDEUR""), IF($D16=""Franco Suíço"",'Original Data'!F16*GOOGLEFINANCE(""Currency:CHFEUR""), IF($D16=""Libra Esterlina"", 'Original Data'!F16*GOOGLEFINANCE"&"(""Currency:GBPEUR""), IF($D16=""Iene"",'Original Data'!F16*GOOGLEFINANCE(""Currency:JPYEUR""), IF($D16=""HKD"",'Original Data'!F16*GOOGLEFINANCE(""Currency:HKDEUR""), IF($D16=""KRW"",'Original Data'!F16*GOOGLEFINANCE(""Currency:KRWEUR""),"""")))))))"),13.7) -> 13.7 | G16: =IFERROR(__xludf.DUMMYFUNCTION("IF($D16=""Euro"",'Original Data'!G16, IF($D16=""Dolar"",'Original Data'!G16*GOOGLEFINANCE(""Currency:USDEUR""), IF($D16=""Franco Suíço"",'Original Data'!G16*GOOGLEFINANCE(""Currency:CHFEUR""), IF($D16=""Libra Esterlina"", 'Original Data'!G16*GOOGLEFINANCE"&"(""Currency:GBPEUR""), IF($D16=""Iene"",'Original Data'!G16*GOOGLEFINANCE(""Currency:JPYEUR""), IF($D16=""HKD"",'Original Data'!G16*GOOGLEFINANCE(""Currency:HKDEUR""), IF($D16=""KRW"",'Original Data'!G16*GOOGLEFINANCE(""Currency:KRWEUR""),"""")))))))"),15.51) -> 15.51 | H16: 2.67 | I16: - | J16: -% | K16: 0.0737 | L16: 0.0512 | M16: 0.1419 | N16: =IFERROR(__xludf.DUMMYFUNCTION("IF('Original Data'!N16=""-"",""-"", IF($D16=""Euro"",'Original Data'!N16, IF($D16=""Dolar"",'Original Data'!N16*GOOGLEFINANCE(""Currency:USDEUR""), IF($D16=""Franco Suíço"",'Original Data'!N16*GOOGLEFINANCE(""Currency:CHFEUR""), IF($D16=""Libra Esterlina"&""", 'Original Data'!N16*GOOGLEFINANCE(""Currency:GBPEUR""), IF($D16=""Iene"",'Original Data'!N16*GOOGLEFINANCE(""Currency:JPYEUR""), IF($D16=""HKD"",'Original Data'!N16*GOOGLEFINANCE(""Currency:HKDEUR""), IF($D16=""KRW"",'Original Data'!N16*GOOGLEFINANCE("&"""Currency:KRWEUR""),""""))))))))"),-0.91) -> -0.91 | O16: =IFERROR(__xludf.DUMMYFUNCTION("IF('Original Data'!O16=""-"",""-"", IF($D16=""Euro"",'Original Data'!O16, IF($D16=""Dolar"",'Original Data'!O16*GOOGLEFINANCE(""Currency:USDEUR""), IF($D16=""Franco Suíço"",'Original Data'!O16*GOOGLEFINANCE(""Currency:CHFEUR""), IF($D16=""Libra Esterlina"&""", 'Original Data'!O16*GOOGLEFINANCE(""Currency:GBPEUR""), IF($D16=""Iene"",'Original Data'!O16*GOOGLEFINANCE(""Currency:JPYEUR""), IF($D16=""HKD"",'Original Data'!O16*GOOGLEFINANCE(""Currency:HKDEUR""), IF($D16=""KRW"",'Original Data'!O16*GOOGLEFINANCE("&"""Currency:KRWEUR""),""""))))))))"),7.15) -> 7.15 | P16: =IFERROR(__xludf.DUMMYFUNCTION("IF('Original Data'!P16=""-"",""-"", IF($D16=""Euro"",'Original Data'!P16, IF($D16=""Dolar"",'Original Data'!P16*GOOGLEFINANCE(""Currency:USDEUR""), IF($D16=""Franco Suíço"",'Original Data'!P16*GOOGLEFINANCE(""Currency:CHFEUR""), IF($D16=""Libra Esterlina"&""", 'Original Data'!P16*GOOGLEFINANCE(""Currency:GBPEUR""), IF($D16=""Iene"",'Original Data'!P16*GOOGLEFINANCE(""Currency:JPYEUR""), IF($D16=""HKD"",'Original Data'!P16*GOOGLEFINANCE(""Currency:HKDEUR""), IF($D16=""KRW"",'Original Data'!P16*GOOGLEFINANCE("&"""Currency:KRWEUR""),""""))))))))"),7.7) -> 7.7 | Q16: =IFERROR(__xludf.DUMMYFUNCTION("IF('Original Data'!Q16=""-"",""-"", IF($D16=""Euro"",'Original Data'!Q16, IF($D16=""Dolar"",'Original Data'!Q16*GOOGLEFINANCE(""Currency:USDEUR""), IF($D16=""Franco Suíço"",'Original Data'!Q16*GOOGLEFINANCE(""Currency:CHFEUR""), IF($D16=""Libra Esterlina"&""", 'Original Data'!Q16*GOOGLEFINANCE(""Currency:GBPEUR""), IF($D16=""Iene"",'Original Data'!Q16*GOOGLEFINANCE(""Currency:JPYEUR""), IF($D16=""HKD"",'Original Data'!Q16*GOOGLEFINANCE(""Currency:HKDEUR""), IF($D16=""KRW"",'Original Data'!Q16*GOOGLEFINANCE("&"""Currency:KRWEUR""),""""))))))))"),8.49) -> 8.49 | R16: =IFERROR(__xludf.DUMMYFUNCTION("IF('Original Data'!R16=""-"",""-"", IF($D16=""Euro"",'Original Data'!R16, IF($D16=""Dolar"",'Original Data'!R16*GOOGLEFINANCE(""Currency:USDEUR""), IF($D16=""Franco Suíço"",'Original Data'!R16*GOOGLEFINANCE(""Currency:CHFEUR""), IF($D16=""Libra Esterlina"&""", 'Original Data'!R16*GOOGLEFINANCE(""Currency:GBPEUR""), IF($D16=""Iene"",'Original Data'!R16*GOOGLEFINANCE(""Currency:JPYEUR""), IF($D16=""HKD"",'Original Data'!R16*GOOGLEFINANCE(""Currency:HKDEUR""), IF($D16=""KRW"",'Original Data'!R16*GOOGLEFINANCE("&"""Currency:KRWEUR""),""""))))))))"),1.64) -> 1.64 | S16: =IFERROR(__xludf.DUMMYFUNCTION("IF('Original Data'!S16=""-"",""-"", IF($D16=""Euro"",'Original Data'!S16, IF($D16=""Dolar"",'Original Data'!S16*GOOGLEFINANCE(""Currency:USDEUR""), IF($D16=""Franco Suíço"",'Original Data'!S16*GOOGLEFINANCE(""Currency:CHFEUR""), IF($D16=""Libra Esterlina"&""", 'Original Data'!S16*GOOGLEFINANCE(""Currency:GBPEUR""), IF($D16=""Iene"",'Original Data'!S16*GOOGLEFINANCE(""Currency:JPYEUR""), IF($D16=""HKD"",'Original Data'!S16*GOOGLEFINANCE(""Currency:HKDEUR""), IF($D16=""KRW"",'Original Data'!S16*GOOGLEFINANCE("&"""Currency:KRWEUR""),""""))))))))"),2.23) -> 2.23 | T16: =IFERROR(__xludf.DUMMYFUNCTION("IF('Original Data'!T16=""-"",""-"", IF($D16=""Euro"",'Original Data'!T16, IF($D16=""Dolar"",'Original Data'!T16*GOOGLEFINANCE(""Currency:USDEUR""), IF($D16=""Franco Suíço"",'Original Data'!T16*GOOGLEFINANCE(""Currency:CHFEUR""), IF($D16=""Libra Esterlina"&""", 'Original Data'!T16*GOOGLEFINANCE(""Currency:GBPEUR""), IF($D16=""Iene"",'Original Data'!T16*GOOGLEFINANCE(""Currency:JPYEUR""), IF($D16=""HKD"",'Original Data'!T16*GOOGLEFINANCE(""Currency:HKDEUR""), IF($D16=""KRW"",'Original Data'!T16*GOOGLEFINANCE("&"""Currency:KRWEUR""),""""))))))))"),1.66) -> 1.66 | U16: =IFERROR(__xludf.DUMMYFUNCTION("IF('Original Data'!U16=""-"",""-"", IF($D16=""Euro"",'Original Data'!U16, IF($D16=""Dolar"",'Original Data'!U16*GOOGLEFINANCE(""Currency:USDEUR""), IF($D16=""Franco Suíço"",'Original Data'!U16*GOOGLEFINANCE(""Currency:CHFEUR""), IF($D16=""Libra Esterlina"&""", 'Original Data'!U16*GOOGLEFINANCE(""Currency:GBPEUR""), IF($D16=""Iene"",'Original Data'!U16*GOOGLEFINANCE(""Currency:JPYEUR""), IF($D16=""HKD"",'Original Data'!U16*GOOGLEFINANCE(""Currency:HKDEUR""), IF($D16=""KRW"",'Original Data'!U16*GOOGLEFINANCE("&"""Currency:KRWEUR""),""""))))))))"),1.88) -> 1.88 | V16: =IFERROR(__xludf.DUMMYFUNCTION("IF('Original Data'!V16=""-"",""-"", IF($D16=""Euro"",'Original Data'!V16, IF($D16=""Dolar"",'Original Data'!V16*GOOGLEFINANCE(""Currency:USDEUR""), IF($D16=""Franco Suíço"",'Original Data'!V16*GOOGLEFINANCE(""Currency:CHFEUR""), IF($D16=""Libra Esterlina"&""", 'Original Data'!V16*GOOGLEFINANCE(""Currency:GBPEUR""), IF($D16=""Iene"",'Original Data'!V16*GOOGLEFINANCE(""Currency:JPYEUR""), IF($D16=""HKD"",'Original Data'!V16*GOOGLEFINANCE(""Currency:HKDEUR""), IF($D16=""KRW"",'Original Data'!V16*GOOGLEFINANCE("&"""Currency:KRWEUR""),""""))))))))"),"-") -> - | W16: B- | X16: B | Y16: - | Z16: - | AA16: - | AB16: - | AC16: 30 | AD16: 8.8 | AE16: 15.3 | AF16: 5.4 | AG16: 3
A17: TRIGANO SA | B17: TRI FP Equity | C17: FR0005691656 | D17: Euro | E17: =IFERROR(__xludf.DUMMYFUNCTION("IF($D17=""Euro"",'Original Data'!E17, IF($D17=""Dolar"",'Original Data'!E17*GOOGLEFINANCE(""Currency:USDEUR""), IF($D17=""Franco Suíço"",'Original Data'!E17*GOOGLEFINANCE(""Currency:CHFEUR""), IF($D17=""Libra Esterlina"", 'Original Data'!E17*GOOGLEFINANCE"&"(""Currency:GBPEUR""), IF($D17=""Iene"",'Original Data'!E17*GOOGLEFINANCE(""Currency:JPYEUR""), IF($D17=""HKD"",'Original Data'!E17*GOOGLEFINANCE(""Currency:HKDEUR""), IF($D17=""KRW"",'Original Data'!E17*GOOGLEFINANCE(""Currency:KRWEUR""),"""")))))))"),2.9) -> 2.9 | F17: =IFERROR(__xludf.DUMMYFUNCTION("IF($D17=""Euro"",'Original Data'!F17, IF($D17=""Dolar"",'Original Data'!F17*GOOGLEFINANCE(""Currency:USDEUR""), IF($D17=""Franco Suíço"",'Original Data'!F17*GOOGLEFINANCE(""Currency:CHFEUR""), IF($D17=""Libra Esterlina"", 'Original Data'!F17*GOOGLEFINANCE"&"(""Currency:GBPEUR""), IF($D17=""Iene"",'Original Data'!F17*GOOGLEFINANCE(""Currency:JPYEUR""), IF($D17=""HKD"",'Original Data'!F17*GOOGLEFINANCE(""Currency:HKDEUR""), IF($D17=""KRW"",'Original Data'!F17*GOOGLEFINANCE(""Currency:KRWEUR""),"""")))))))"),139.7) -> 139.7 | G17: =IFERROR(__xludf.DUMMYFUNCTION("IF($D17=""Euro"",'Original Data'!G17, IF($D17=""Dolar"",'Original Data'!G17*GOOGLEFINANCE(""Currency:USDEUR""), IF($D17=""Franco Suíço"",'Original Data'!G17*GOOGLEFINANCE(""Currency:CHFEUR""), IF($D17=""Libra Esterlina"", 'Original Data'!G17*GOOGLEFINANCE"&"(""Currency:GBPEUR""), IF($D17=""Iene"",'Original Data'!G17*GOOGLEFINANCE(""Currency:JPYEUR""), IF($D17=""HKD"",'Original Data'!G17*GOOGLEFINANCE(""Currency:HKDEUR""), IF($D17=""KRW"",'Original Data'!G17*GOOGLEFINANCE(""Currency:KRWEUR""),"""")))))))"),2.73) -> 2.73 | H17: 31.07 | I17: 12.08 | J17: 0.0308 | K17: 0.1656 | L17: 0.1101 | M17: 0.207 | N17: =IFERROR(__xludf.DUMMYFUNCTION("IF('Original Data'!N17=""-"",""-"", IF($D17=""Euro"",'Original Data'!N17, IF($D17=""Dolar"",'Original Data'!N17*GOOGLEFINANCE(""Currency:USDEUR""), IF($D17=""Franco Suíço"",'Original Data'!N17*GOOGLEFINANCE(""Currency:CHFEUR""), IF($D17=""Libra Esterlina"&""", 'Original Data'!N17*GOOGLEFINANCE(""Currency:GBPEUR""), IF($D17=""Iene"",'Original Data'!N17*GOOGLEFINANCE(""Currency:JPYEUR""), IF($D17=""HKD"",'Original Data'!N17*GOOGLEFINANCE(""Currency:HKDEUR""), IF($D17=""KRW"",'Original Data'!N17*GOOGLEFINANCE("&"""Currency:KRWEUR""),""""))))))))"),11.55) -> 11.55 | O17: =IFERROR(__xludf.DUMMYFUNCTION("IF('Original Data'!O17=""-"",""-"", IF($D17=""Euro"",'Original Data'!O17, IF($D17=""Dolar"",'Original Data'!O17*GOOGLEFINANCE(""Currency:USDEUR""), IF($D17=""Franco Suíço"",'Original Data'!O17*GOOGLEFINANCE(""Currency:CHFEUR""), IF($D17=""Libra Esterlina"&""", 'Original Data'!O17*GOOGLEFINANCE(""Currency:GBPEUR""), IF($D17=""Iene"",'Original Data'!O17*GOOGLEFINANCE(""Currency:JPYEUR""), IF($D17=""HKD"",'Original Data'!O17*GOOGLEFINANCE(""Currency:HKDEUR""), IF($D17=""KRW"",'Original Data'!O17*GOOGLEFINANCE("&"""Currency:KRWEUR""),""""))))))))"),2.31) -> 2.31 | P17: =IFERROR(__xludf.DUMMYFUNCTION("IF('Original Data'!P17=""-"",""-"", IF($D17=""Euro"",'Original Data'!P17, IF($D17=""Dolar"",'Original Data'!P17*GOOGLEFINANCE(""Currency:USDEUR""), IF($D17=""Franco Suíço"",'Original Data'!P17*GOOGLEFINANCE(""Currency:CHFEUR""), IF($D17=""Libra Esterlina"&""", 'Original Data'!P17*GOOGLEFINANCE(""Currency:GBPEUR""), IF($D17=""Iene"",'Original Data'!P17*GOOGLEFINANCE(""Currency:JPYEUR""), IF($D17=""HKD"",'Original Data'!P17*GOOGLEFINANCE(""Currency:HKDEUR""), IF($D17=""KRW"",'Original Data'!P17*GOOGLEFINANCE("&"""Currency:KRWEUR""),""""))))))))"),2.33) -> 2.33 | Q17: =IFERROR(__xludf.DUMMYFUNCTION("IF('Original Data'!Q17=""-"",""-"", IF($D17=""Euro"",'Original Data'!Q17, IF($D17=""Dolar"",'Original Data'!Q17*GOOGLEFINANCE(""Currency:USDEUR""), IF($D17=""Franco Suíço"",'Original Data'!Q17*GOOGLEFINANCE(""Currency:CHFEUR""), IF($D17=""Libra Esterlina"&""", 'Original Data'!Q17*GOOGLEFINANCE(""Currency:GBPEUR""), IF($D17=""Iene"",'Original Data'!Q17*GOOGLEFINANCE(""Currency:JPYEUR""), IF($D17=""HKD"",'Original Data'!Q17*GOOGLEFINANCE(""Currency:HKDEUR""), IF($D17=""KRW"",'Original Data'!Q17*GOOGLEFINANCE("&"""Currency:KRWEUR""),""""))))))))"),2.18) -> 2.18 | R17: =IFERROR(__xludf.DUMMYFUNCTION("IF('Original Data'!R17=""-"",""-"", IF($D17=""Euro"",'Original Data'!R17, IF($D17=""Dolar"",'Original Data'!R17*GOOGLEFINANCE(""Currency:USDEUR""), IF($D17=""Franco Suíço"",'Original Data'!R17*GOOGLEFINANCE(""Currency:CHFEUR""), IF($D17=""Libra Esterlina"&""", 'Original Data'!R17*GOOGLEFINANCE(""Currency:GBPEUR""), IF($D17=""Iene"",'Original Data'!R17*GOOGLEFINANCE(""Currency:JPYEUR""), IF($D17=""HKD"",'Original Data'!R17*GOOGLEFINANCE(""Currency:HKDEUR""), IF($D17=""KRW"",'Original Data'!R17*GOOGLEFINANCE("&"""Currency:KRWEUR""),""""))))))))"),2.93) -> 2.93 | S17: =IFERROR(__xludf.DUMMYFUNCTION("IF('Original Data'!S17=""-"",""-"", IF($D17=""Euro"",'Original Data'!S17, IF($D17=""Dolar"",'Original Data'!S17*GOOGLEFINANCE(""Currency:USDEUR""), IF($D17=""Franco Suíço"",'Original Data'!S17*GOOGLEFINANCE(""Currency:CHFEUR""), IF($D17=""Libra Esterlina"&""", 'Original Data'!S17*GOOGLEFINANCE(""Currency:GBPEUR""), IF($D17=""Iene"",'Original Data'!S17*GOOGLEFINANCE(""Currency:JPYEUR""), IF($D17=""HKD"",'Original Data'!S17*GOOGLEFINANCE(""Currency:HKDEUR""), IF($D17=""KRW"",'Original Data'!S17*GOOGLEFINANCE("&"""Currency:KRWEUR""),""""))))))))"),0.25342) -> 0.25342 | T17: =IFERROR(__xludf.DUMMYFUNCTION("IF('Original Data'!T17=""-"",""-"", IF($D17=""Euro"",'Original Data'!T17, IF($D17=""Dolar"",'Original Data'!T17*GOOGLEFINANCE(""Currency:USDEUR""), IF($D17=""Franco Suíço"",'Original Data'!T17*GOOGLEFINANCE(""Currency:CHFEUR""), IF($D17=""Libra Esterlina"&""", 'Original Data'!T17*GOOGLEFINANCE(""Currency:GBPEUR""), IF($D17=""Iene"",'Original Data'!T17*GOOGLEFINANCE(""Currency:JPYEUR""), IF($D17=""HKD"",'Original Data'!T17*GOOGLEFINANCE(""Currency:HKDEUR""), IF($D17=""KRW"",'Original Data'!T17*GOOGLEFINANCE("&"""Currency:KRWEUR""),""""))))))))"),0.23584) -> 0.23584 | U17: =IFERROR(__xludf.DUMMYFUNCTION("IF('Original Data'!U17=""-"",""-"", IF($D17=""Euro"",'Original Data'!U17, IF($D17=""Dolar"",'Original Data'!U17*GOOGLEFINANCE(""Currency:USDEUR""), IF($D17=""Franco Suíço"",'Original Data'!U17*GOOGLEFINANCE(""Currency:CHFEUR""), IF($D17=""Libra Esterlina"&""", 'Original Data'!U17*GOOGLEFINANCE(""Currency:GBPEUR""), IF($D17=""Iene"",'Original Data'!U17*GOOGLEFINANCE(""Currency:JPYEUR""), IF($D17=""HKD"",'Original Data'!U17*GOOGLEFINANCE(""Currency:HKDEUR""), IF($D17=""KRW"",'Original Data'!U17*GOOGLEFINANCE("&"""Currency:KRWEUR""),""""))))))))"),0.23776) -> 0.23776 | V17: =IFERROR(__xludf.DUMMYFUNCTION("IF('Original Data'!V17=""-"",""-"", IF($D17=""Euro"",'Original Data'!V17, IF($D17=""Dolar"",'Original Data'!V17*GOOGLEFINANCE(""Currency:USDEUR""), IF($D17=""Franco Suíço"",'Original Data'!V17*GOOGLEFINANCE(""Currency:CHFEUR""), IF($D17=""Libra Esterlina"&""", 'Original Data'!V17*GOOGLEFINANCE(""Currency:GBPEUR""), IF($D17=""Iene"",'Original Data'!V17*GOOGLEFINANCE(""Currency:JPYEUR""), IF($D17=""HKD"",'Original Data'!V17*GOOGLEFINANCE(""Currency:HKDEUR""), IF($D17=""KRW"",'Original Data'!V17*GOOGLEFINANCE("&"""Currency:KRWEUR""),""""))))))))"),0.42454) -> 0.42454 | W17: No Response | X17: No Response | Y17: - | Z17: - | AA17: - | AB17: - | AC17: - | AD17: - | AE17: - | AF17: - | AG17: -
A18: BENETEAU | B18: BEN FP Equity | C18: FR0000035164 | D18: Euro | E18: =IFERROR(__xludf.DUMMYFUNCTION("IF($D18=""Euro"",'Original Data'!E18, IF($D18=""Dolar"",'Original Data'!E18*GOOGLEFINANCE(""Currency:USDEUR""), IF($D18=""Franco Suíço"",'Original Data'!E18*GOOGLEFINANCE(""Currency:CHFEUR""), IF($D18=""Libra Esterlina"", 'Original Data'!E18*GOOGLEFINANCE"&"(""Currency:GBPEUR""), IF($D18=""Iene"",'Original Data'!E18*GOOGLEFINANCE(""Currency:JPYEUR""), IF($D18=""HKD"",'Original Data'!E18*GOOGLEFINANCE(""Currency:HKDEUR""), IF($D18=""KRW"",'Original Data'!E18*GOOGLEFINANCE(""Currency:KRWEUR""),"""")))))))"),0.18) -> 0.18 | F18: =IFERROR(__xludf.DUMMYFUNCTION("IF($D18=""Euro"",'Original Data'!F18, IF($D18=""Dolar"",'Original Data'!F18*GOOGLEFINANCE(""Currency:USDEUR""), IF($D18=""Franco Suíço"",'Original Data'!F18*GOOGLEFINANCE(""Currency:CHFEUR""), IF($D18=""Libra Esterlina"", 'Original Data'!F18*GOOGLEFINANCE"&"(""Currency:GBPEUR""), IF($D18=""Iene"",'Original Data'!F18*GOOGLEFINANCE(""Currency:JPYEUR""), IF($D18=""HKD"",'Original Data'!F18*GOOGLEFINANCE(""Currency:HKDEUR""), IF($D18=""KRW"",'Original Data'!F18*GOOGLEFINANCE(""Currency:KRWEUR""),"""")))))))"),14.16) -> 14.16 | G18: =IFERROR(__xludf.DUMMYFUNCTION("IF($D18=""Euro"",'Original Data'!G18, IF($D18=""Dolar"",'Original Data'!G18*GOOGLEFINANCE(""Currency:USDEUR""), IF($D18=""Franco Suíço"",'Original Data'!G18*GOOGLEFINANCE(""Currency:CHFEUR""), IF($D18=""Libra Esterlina"", 'Original Data'!G18*GOOGLEFINANCE"&"(""Currency:GBPEUR""), IF($D18=""Iene"",'Original Data'!G18*GOOGLEFINANCE(""Currency:JPYEUR""), IF($D18=""HKD"",'Original Data'!G18*GOOGLEFINANCE(""Currency:HKDEUR""), IF($D18=""KRW"",'Original Data'!G18*GOOGLEFINANCE(""Currency:KRWEUR""),"""")))))))"),1.2) -> 1.2 | H18: 0.101 | I18: - | J18: -% | K18: -% | L18: -% | M18: -% | N18: =IFERROR(__xludf.DUMMYFUNCTION("IF('Original Data'!N18=""-"",""-"", IF($D18=""Euro"",'Original Data'!N18, IF($D18=""Dolar"",'Original Data'!N18*GOOGLEFINANCE(""Currency:USDEUR""), IF($D18=""Franco Suíço"",'Original Data'!N18*GOOGLEFINANCE(""Currency:CHFEUR""), IF($D18=""Libra Esterlina"&""", 'Original Data'!N18*GOOGLEFINANCE(""Currency:GBPEUR""), IF($D18=""Iene"",'Original Data'!N18*GOOGLEFINANCE(""Currency:JPYEUR""), IF($D18=""HKD"",'Original Data'!N18*GOOGLEFINANCE(""Currency:HKDEUR""), IF($D18=""KRW"",'Original Data'!N18*GOOGLEFINANCE("&"""Currency:KRWEUR""),""""))))))))"),"-") -> - | O18: =IFERROR(__xludf.DUMMYFUNCTION("IF('Original Data'!O18=""-"",""-"", IF($D18=""Euro"",'Original Data'!O18, IF($D18=""Dolar"",'Original Data'!O18*GOOGLEFINANCE(""Currency:USDEUR""), IF($D18=""Franco Suíço"",'Original Data'!O18*GOOGLEFINANCE(""Currency:CHFEUR""), IF($D18=""Libra Esterlina"&""", 'Original Data'!O18*GOOGLEFINANCE(""Currency:GBPEUR""), IF($D18=""Iene"",'Original Data'!O18*GOOGLEFINANCE(""Currency:JPYEUR""), IF($D18=""HKD"",'Original Data'!O18*GOOGLEFINANCE(""Currency:HKDEUR""), IF($D18=""KRW"",'Original Data'!O18*GOOGLEFINANCE("&"""Currency:KRWEUR""),""""))))))))"),1.29) -> 1.29 | P18: =IFERROR(__xludf.DUMMYFUNCTION("IF('Original Data'!P18=""-"",""-"", IF($D18=""Euro"",'Original Data'!P18, IF($D18=""Dolar"",'Original Data'!P18*GOOGLEFINANCE(""Currency:USDEUR""), IF($D18=""Franco Suíço"",'Original Data'!P18*GOOGLEFINANCE(""Currency:CHFEUR""), IF($D18=""Libra Esterlina"&""", 'Original Data'!P18*GOOGLEFINANCE(""Currency:GBPEUR""), IF($D18=""Iene"",'Original Data'!P18*GOOGLEFINANCE(""Currency:JPYEUR""), IF($D18=""HKD"",'Original Data'!P18*GOOGLEFINANCE(""Currency:HKDEUR""), IF($D18=""KRW"",'Original Data'!P18*GOOGLEFINANCE("&"""Currency:KRWEUR""),""""))))))))"),1.34) -> 1.34 | Q18: =IFERROR(__xludf.DUMMYFUNCTION("IF('Original Data'!Q18=""-"",""-"", IF($D18=""Euro"",'Original Data'!Q18, IF($D18=""Dolar"",'Original Data'!Q18*GOOGLEFINANCE(""Currency:USDEUR""), IF($D18=""Franco Suíço"",'Original Data'!Q18*GOOGLEFINANCE(""Currency:CHFEUR""), IF($D18=""Libra Esterlina"&""", 'Original Data'!Q18*GOOGLEFINANCE(""Currency:GBPEUR""), IF($D18=""Iene"",'Original Data'!Q18*GOOGLEFINANCE(""Currency:JPYEUR""), IF($D18=""HKD"",'Original Data'!Q18*GOOGLEFINANCE(""Currency:HKDEUR""), IF($D18=""KRW"",'Original Data'!Q18*GOOGLEFINANCE("&"""Currency:KRWEUR""),""""))))))))"),1.01) -> 1.01 | R18: =IFERROR(__xludf.DUMMYFUNCTION("IF('Original Data'!R18=""-"",""-"", IF($D18=""Euro"",'Original Data'!R18, IF($D18=""Dolar"",'Original Data'!R18*GOOGLEFINANCE(""Currency:USDEUR""), IF($D18=""Franco Suíço"",'Original Data'!R18*GOOGLEFINANCE(""Currency:CHFEUR""), IF($D18=""Libra Esterlina"&""", 'Original Data'!R18*GOOGLEFINANCE(""Currency:GBPEUR""), IF($D18=""Iene"",'Original Data'!R18*GOOGLEFINANCE(""Currency:JPYEUR""), IF($D18=""HKD"",'Original Data'!R18*GOOGLEFINANCE(""Currency:HKDEUR""), IF($D18=""KRW"",'Original Data'!R18*GOOGLEFINANCE("&"""Currency:KRWEUR""),""""))))))))"),1.23) -> 1.23 | S18: =IFERROR(__xludf.DUMMYFUNCTION("IF('Original Data'!S18=""-"",""-"", IF($D18=""Euro"",'Original Data'!S18, IF($D18=""Dolar"",'Original Data'!S18*GOOGLEFINANCE(""Currency:USDEUR""), IF($D18=""Franco Suíço"",'Original Data'!S18*GOOGLEFINANCE(""Currency:CHFEUR""), IF($D18=""Libra Esterlina"&""", 'Original Data'!S18*GOOGLEFINANCE(""Currency:GBPEUR""), IF($D18=""Iene"",'Original Data'!S18*GOOGLEFINANCE(""Currency:JPYEUR""), IF($D18=""HKD"",'Original Data'!S18*GOOGLEFINANCE(""Currency:HKDEUR""), IF($D18=""KRW"",'Original Data'!S18*GOOGLEFINANCE("&"""Currency:KRWEUR""),""""))))))))"),0.1536) -> 0.1536 | T18: =IFERROR(__xludf.DUMMYFUNCTION("IF('Original Data'!T18=""-"",""-"", IF($D18=""Euro"",'Original Data'!T18, IF($D18=""Dolar"",'Original Data'!T18*GOOGLEFINANCE(""Currency:USDEUR""), IF($D18=""Franco Suíço"",'Original Data'!T18*GOOGLEFINANCE(""Currency:CHFEUR""), IF($D18=""Libra Esterlina"&""", 'Original Data'!T18*GOOGLEFINANCE(""Currency:GBPEUR""), IF($D18=""Iene"",'Original Data'!T18*GOOGLEFINANCE(""Currency:JPYEUR""), IF($D18=""HKD"",'Original Data'!T18*GOOGLEFINANCE(""Currency:HKDEUR""), IF($D18=""KRW"",'Original Data'!T18*GOOGLEFINANCE("&"""Currency:KRWEUR""),""""))))))))"),0.15511) -> 0.15511 | U18: =IFERROR(__xludf.DUMMYFUNCTION("IF('Original Data'!U18=""-"",""-"", IF($D18=""Euro"",'Original Data'!U18, IF($D18=""Dolar"",'Original Data'!U18*GOOGLEFINANCE(""Currency:USDEUR""), IF($D18=""Franco Suíço"",'Original Data'!U18*GOOGLEFINANCE(""Currency:CHFEUR""), IF($D18=""Libra Esterlina"&""", 'Original Data'!U18*GOOGLEFINANCE(""Currency:GBPEUR""), IF($D18=""Iene"",'Original Data'!U18*GOOGLEFINANCE(""Currency:JPYEUR""), IF($D18=""HKD"",'Original Data'!U18*GOOGLEFINANCE(""Currency:HKDEUR""), IF($D18=""KRW"",'Original Data'!U18*GOOGLEFINANCE("&"""Currency:KRWEUR""),""""))))))))"),0.07146) -> 0.07146 | V18: =IFERROR(__xludf.DUMMYFUNCTION("IF('Original Data'!V18=""-"",""-"", IF($D18=""Euro"",'Original Data'!V18, IF($D18=""Dolar"",'Original Data'!V18*GOOGLEFINANCE(""Currency:USDEUR""), IF($D18=""Franco Suíço"",'Original Data'!V18*GOOGLEFINANCE(""Currency:CHFEUR""), IF($D18=""Libra Esterlina"&""", 'Original Data'!V18*GOOGLEFINANCE(""Currency:GBPEUR""), IF($D18=""Iene"",'Original Data'!V18*GOOGLEFINANCE(""Currency:JPYEUR""), IF($D18=""HKD"",'Original Data'!V18*GOOGLEFINANCE(""Currency:HKDEUR""), IF($D18=""KRW"",'Original Data'!V18*GOOGLEFINANCE("&"""Currency:KRWEUR""),""""))))))))"),"-") -> - | W18: No Response | X18: No Response | Y18: - | Z18: - | AA18: - | AB18: - | AC18: - | AD18: - | AE18: - | AF18: - | AG18: -
A19: SAINT GOBAIN | B19: SGO FP Equity | C19: FR0000125007 | D19: Euro | E19: =IFERROR(__xludf.DUMMYFUNCTION("IF($D19=""Euro"",'Original Data'!E19, IF($D19=""Dolar"",'Original Data'!E19*GOOGLEFINANCE(""Currency:USDEUR""), IF($D19=""Franco Suíço"",'Original Data'!E19*GOOGLEFINANCE(""Currency:CHFEUR""), IF($D19=""Libra Esterlina"", 'Original Data'!E19*GOOGLEFINANCE"&"(""Currency:GBPEUR""), IF($D19=""Iene"",'Original Data'!E19*GOOGLEFINANCE(""Currency:JPYEUR""), IF($D19=""HKD"",'Original Data'!E19*GOOGLEFINANCE(""Currency:HKDEUR""), IF($D19=""KRW"",'Original Data'!E19*GOOGLEFINANCE(""Currency:KRWEUR""),"""")))))))"),36.13) -> 36.13 | F19: =IFERROR(__xludf.DUMMYFUNCTION("IF($D19=""Euro"",'Original Data'!F19, IF($D19=""Dolar"",'Original Data'!F19*GOOGLEFINANCE(""Currency:USDEUR""), IF($D19=""Franco Suíço"",'Original Data'!F19*GOOGLEFINANCE(""Currency:CHFEUR""), IF($D19=""Libra Esterlina"", 'Original Data'!F19*GOOGLEFINANCE"&"(""Currency:GBPEUR""), IF($D19=""Iene"",'Original Data'!F19*GOOGLEFINANCE(""Currency:JPYEUR""), IF($D19=""HKD"",'Original Data'!F19*GOOGLEFINANCE(""Currency:HKDEUR""), IF($D19=""KRW"",'Original Data'!F19*GOOGLEFINANCE(""Currency:KRWEUR""),"""")))))))"),57.88) -> 57.88 | G19: =IFERROR(__xludf.DUMMYFUNCTION("IF($D19=""Euro"",'Original Data'!G19, IF($D19=""Dolar"",'Original Data'!G19*GOOGLEFINANCE(""Currency:USDEUR""), IF($D19=""Franco Suíço"",'Original Data'!G19*GOOGLEFINANCE(""Currency:CHFEUR""), IF($D19=""Libra Esterlina"", 'Original Data'!G19*GOOGLEFINANCE"&"(""Currency:GBPEUR""), IF($D19=""Iene"",'Original Data'!G19*GOOGLEFINANCE(""Currency:JPYEUR""), IF($D19=""HKD"",'Original Data'!G19*GOOGLEFINANCE(""Currency:HKDEUR""), IF($D19=""KRW"",'Original Data'!G19*GOOGLEFINANCE(""Currency:KRWEUR""),"""")))))))"),29.72) -> 29.72 | H19: 1.46 | I19: 12.17 | J19: 0.0287 | K19: 0.0391 | L19: 0.0279 | M19: 0.0683 | N19: =IFERROR(__xludf.DUMMYFUNCTION("IF('Original Data'!N19=""-"",""-"", IF($D19=""Euro"",'Original Data'!N19, IF($D19=""Dolar"",'Original Data'!N19*GOOGLEFINANCE(""Currency:USDEUR""), IF($D19=""Franco Suíço"",'Original Data'!N19*GOOGLEFINANCE(""Currency:CHFEUR""), IF($D19=""Libra Esterlina"&""", 'Original Data'!N19*GOOGLEFINANCE(""Currency:GBPEUR""), IF($D19=""Iene"",'Original Data'!N19*GOOGLEFINANCE(""Currency:JPYEUR""), IF($D19=""HKD"",'Original Data'!N19*GOOGLEFINANCE(""Currency:HKDEUR""), IF($D19=""KRW"",'Original Data'!N19*GOOGLEFINANCE("&"""Currency:KRWEUR""),""""))))))))"),4.79) -> 4.79 | O19: =IFERROR(__xludf.DUMMYFUNCTION("IF('Original Data'!O19=""-"",""-"", IF($D19=""Euro"",'Original Data'!O19, IF($D19=""Dolar"",'Original Data'!O19*GOOGLEFINANCE(""Currency:USDEUR""), IF($D19=""Franco Suíço"",'Original Data'!O19*GOOGLEFINANCE(""Currency:CHFEUR""), IF($D19=""Libra Esterlina"&""", 'Original Data'!O19*GOOGLEFINANCE(""Currency:GBPEUR""), IF($D19=""Iene"",'Original Data'!O19*GOOGLEFINANCE(""Currency:JPYEUR""), IF($D19=""HKD"",'Original Data'!O19*GOOGLEFINANCE(""Currency:HKDEUR""), IF($D19=""KRW"",'Original Data'!O19*GOOGLEFINANCE("&"""Currency:KRWEUR""),""""))))))))"),41.77) -> 41.77 | P19: =IFERROR(__xludf.DUMMYFUNCTION("IF('Original Data'!P19=""-"",""-"", IF($D19=""Euro"",'Original Data'!P19, IF($D19=""Dolar"",'Original Data'!P19*GOOGLEFINANCE(""Currency:USDEUR""), IF($D19=""Franco Suíço"",'Original Data'!P19*GOOGLEFINANCE(""Currency:CHFEUR""), IF($D19=""Libra Esterlina"&""", 'Original Data'!P19*GOOGLEFINANCE(""Currency:GBPEUR""), IF($D19=""Iene"",'Original Data'!P19*GOOGLEFINANCE(""Currency:JPYEUR""), IF($D19=""HKD"",'Original Data'!P19*GOOGLEFINANCE(""Currency:HKDEUR""), IF($D19=""KRW"",'Original Data'!P19*GOOGLEFINANCE("&"""Currency:KRWEUR""),""""))))))))"),42.57) -> 42.57 | Q19: =IFERROR(__xludf.DUMMYFUNCTION("IF('Original Data'!Q19=""-"",""-"", IF($D19=""Euro"",'Original Data'!Q19, IF($D19=""Dolar"",'Original Data'!Q19*GOOGLEFINANCE(""Currency:USDEUR""), IF($D19=""Franco Suíço"",'Original Data'!Q19*GOOGLEFINANCE(""Currency:CHFEUR""), IF($D19=""Libra Esterlina"&""", 'Original Data'!Q19*GOOGLEFINANCE(""Currency:GBPEUR""), IF($D19=""Iene"",'Original Data'!Q19*GOOGLEFINANCE(""Currency:JPYEUR""), IF($D19=""HKD"",'Original Data'!Q19*GOOGLEFINANCE(""Currency:HKDEUR""), IF($D19=""KRW"",'Original Data'!Q19*GOOGLEFINANCE("&"""Currency:KRWEUR""),""""))))))))"),38.13) -> 38.13 | R19: =IFERROR(__xludf.DUMMYFUNCTION("IF('Original Data'!R19=""-"",""-"", IF($D19=""Euro"",'Original Data'!R19, IF($D19=""Dolar"",'Original Data'!R19*GOOGLEFINANCE(""Currency:USDEUR""), IF($D19=""Franco Suíço"",'Original Data'!R19*GOOGLEFINANCE(""Currency:CHFEUR""), IF($D19=""Libra Esterlina"&""", 'Original Data'!R19*GOOGLEFINANCE(""Currency:GBPEUR""), IF($D19=""Iene"",'Original Data'!R19*GOOGLEFINANCE(""Currency:JPYEUR""), IF($D19=""HKD"",'Original Data'!R19*GOOGLEFINANCE(""Currency:HKDEUR""), IF($D19=""KRW"",'Original Data'!R19*GOOGLEFINANCE("&"""Currency:KRWEUR""),""""))))))))"),44.16) -> 44.16 | S19: =IFERROR(__xludf.DUMMYFUNCTION("IF('Original Data'!S19=""-"",""-"", IF($D19=""Euro"",'Original Data'!S19, IF($D19=""Dolar"",'Original Data'!S19*GOOGLEFINANCE(""Currency:USDEUR""), IF($D19=""Franco Suíço"",'Original Data'!S19*GOOGLEFINANCE(""Currency:CHFEUR""), IF($D19=""Libra Esterlina"&""", 'Original Data'!S19*GOOGLEFINANCE(""Currency:GBPEUR""), IF($D19=""Iene"",'Original Data'!S19*GOOGLEFINANCE(""Currency:JPYEUR""), IF($D19=""HKD"",'Original Data'!S19*GOOGLEFINANCE(""Currency:HKDEUR""), IF($D19=""KRW"",'Original Data'!S19*GOOGLEFINANCE("&"""Currency:KRWEUR""),""""))))))))"),5.08) -> 5.08 | T19: =IFERROR(__xludf.DUMMYFUNCTION("IF('Original Data'!T19=""-"",""-"", IF($D19=""Euro"",'Original Data'!T19, IF($D19=""Dolar"",'Original Data'!T19*GOOGLEFINANCE(""Currency:USDEUR""), IF($D19=""Franco Suíço"",'Original Data'!T19*GOOGLEFINANCE(""Currency:CHFEUR""), IF($D19=""Libra Esterlina"&""", 'Original Data'!T19*GOOGLEFINANCE(""Currency:GBPEUR""), IF($D19=""Iene"",'Original Data'!T19*GOOGLEFINANCE(""Currency:JPYEUR""), IF($D19=""HKD"",'Original Data'!T19*GOOGLEFINANCE(""Currency:HKDEUR""), IF($D19=""KRW"",'Original Data'!T19*GOOGLEFINANCE("&"""Currency:KRWEUR""),""""))))))))"),5.27) -> 5.27 | U19: =IFERROR(__xludf.DUMMYFUNCTION("IF('Original Data'!U19=""-"",""-"", IF($D19=""Euro"",'Original Data'!U19, IF($D19=""Dolar"",'Original Data'!U19*GOOGLEFINANCE(""Currency:USDEUR""), IF($D19=""Franco Suíço"",'Original Data'!U19*GOOGLEFINANCE(""Currency:CHFEUR""), IF($D19=""Libra Esterlina"&""", 'Original Data'!U19*GOOGLEFINANCE(""Currency:GBPEUR""), IF($D19=""Iene"",'Original Data'!U19*GOOGLEFINANCE(""Currency:JPYEUR""), IF($D19=""HKD"",'Original Data'!U19*GOOGLEFINANCE(""Currency:HKDEUR""), IF($D19=""KRW"",'Original Data'!U19*GOOGLEFINANCE("&"""Currency:KRWEUR""),""""))))))))"),4.74) -> 4.74 | V19: =IFERROR(__xludf.DUMMYFUNCTION("IF('Original Data'!V19=""-"",""-"", IF($D19=""Euro"",'Original Data'!V19, IF($D19=""Dolar"",'Original Data'!V19*GOOGLEFINANCE(""Currency:USDEUR""), IF($D19=""Franco Suíço"",'Original Data'!V19*GOOGLEFINANCE(""Currency:CHFEUR""), IF($D19=""Libra Esterlina"&""", 'Original Data'!V19*GOOGLEFINANCE(""Currency:GBPEUR""), IF($D19=""Iene"",'Original Data'!V19*GOOGLEFINANCE(""Currency:JPYEUR""), IF($D19=""HKD"",'Original Data'!V19*GOOGLEFINANCE(""Currency:HKDEUR""), IF($D19=""KRW"",'Original Data'!V19*GOOGLEFINANCE("&"""Currency:KRWEUR""),""""))))))))"),6.44) -> 6.44 | W19: A- | X19: A | Y19: No Response | Z19: No Response | AA19: B | AB19: A- | AC19: 20 | AD19: 8.4 | AE19: 6.1 | AF19: 5.6 | AG19: 3
A20: BEKAERT NV | B20: BEKB BB Equity | C20: BE0974258874 | D20: Euro | E20: =IFERROR(__xludf.DUMMYFUNCTION("IF($D20=""Euro"",'Original Data'!E20, IF($D20=""Dolar"",'Original Data'!E20*GOOGLEFINANCE(""Currency:USDEUR""), IF($D20=""Franco Suíço"",'Original Data'!E20*GOOGLEFINANCE(""Currency:CHFEUR""), IF($D20=""Libra Esterlina"", 'Original Data'!E20*GOOGLEFINANCE"&"(""Currency:GBPEUR""), IF($D20=""Iene"",'Original Data'!E20*GOOGLEFINANCE(""Currency:JPYEUR""), IF($D20=""HKD"",'Original Data'!E20*GOOGLEFINANCE(""Currency:HKDEUR""), IF($D20=""KRW"",'Original Data'!E20*GOOGLEFINANCE(""Currency:KRWEUR""),"""")))))))"),18.17) -> 18.17 | F20: =IFERROR(__xludf.DUMMYFUNCTION("IF($D20=""Euro"",'Original Data'!F20, IF($D20=""Dolar"",'Original Data'!F20*GOOGLEFINANCE(""Currency:USDEUR""), IF($D20=""Franco Suíço"",'Original Data'!F20*GOOGLEFINANCE(""Currency:CHFEUR""), IF($D20=""Libra Esterlina"", 'Original Data'!F20*GOOGLEFINANCE"&"(""Currency:GBPEUR""), IF($D20=""Iene"",'Original Data'!F20*GOOGLEFINANCE(""Currency:JPYEUR""), IF($D20=""HKD"",'Original Data'!F20*GOOGLEFINANCE(""Currency:HKDEUR""), IF($D20=""KRW"",'Original Data'!F20*GOOGLEFINANCE(""Currency:KRWEUR""),"""")))))))"),36.92) -> 36.92 | G20: =IFERROR(__xludf.DUMMYFUNCTION("IF($D20=""Euro"",'Original Data'!G20, IF($D20=""Dolar"",'Original Data'!G20*GOOGLEFINANCE(""Currency:USDEUR""), IF($D20=""Franco Suíço"",'Original Data'!G20*GOOGLEFINANCE(""Currency:CHFEUR""), IF($D20=""Libra Esterlina"", 'Original Data'!G20*GOOGLEFINANCE"&"(""Currency:GBPEUR""), IF($D20=""Iene"",'Original Data'!G20*GOOGLEFINANCE(""Currency:JPYEUR""), IF($D20=""HKD"",'Original Data'!G20*GOOGLEFINANCE(""Currency:HKDEUR""), IF($D20=""KRW"",'Original Data'!G20*GOOGLEFINANCE(""Currency:KRWEUR""),"""")))))))"),2.23) -> 2.23 | H20: 0.09913 | I20: 5.2 | J20: 0.0286 | K20: 0.0446 | L20: 0.0276 | M20: 0.1079 | N20: =IFERROR(__xludf.DUMMYFUNCTION("IF('Original Data'!N20=""-"",""-"", IF($D20=""Euro"",'Original Data'!N20, IF($D20=""Dolar"",'Original Data'!N20*GOOGLEFINANCE(""Currency:USDEUR""), IF($D20=""Franco Suíço"",'Original Data'!N20*GOOGLEFINANCE(""Currency:CHFEUR""), IF($D20=""Libra Esterlina"&""", 'Original Data'!N20*GOOGLEFINANCE(""Currency:GBPEUR""), IF($D20=""Iene"",'Original Data'!N20*GOOGLEFINANCE(""Currency:JPYEUR""), IF($D20=""HKD"",'Original Data'!N20*GOOGLEFINANCE(""Currency:HKDEUR""), IF($D20=""KRW"",'Original Data'!N20*GOOGLEFINANCE("&"""Currency:KRWEUR""),""""))))))))"),7.14) -> 7.14 | O20: =IFERROR(__xludf.DUMMYFUNCTION("IF('Original Data'!O20=""-"",""-"", IF($D20=""Euro"",'Original Data'!O20, IF($D20=""Dolar"",'Original Data'!O20*GOOGLEFINANCE(""Currency:USDEUR""), IF($D20=""Franco Suíço"",'Original Data'!O20*GOOGLEFINANCE(""Currency:CHFEUR""), IF($D20=""Libra Esterlina"&""", 'Original Data'!O20*GOOGLEFINANCE(""Currency:GBPEUR""), IF($D20=""Iene"",'Original Data'!O20*GOOGLEFINANCE(""Currency:JPYEUR""), IF($D20=""HKD"",'Original Data'!O20*GOOGLEFINANCE(""Currency:HKDEUR""), IF($D20=""KRW"",'Original Data'!O20*GOOGLEFINANCE("&"""Currency:KRWEUR""),""""))))))))"),4.31) -> 4.31 | P20: =IFERROR(__xludf.DUMMYFUNCTION("IF('Original Data'!P20=""-"",""-"", IF($D20=""Euro"",'Original Data'!P20, IF($D20=""Dolar"",'Original Data'!P20*GOOGLEFINANCE(""Currency:USDEUR""), IF($D20=""Franco Suíço"",'Original Data'!P20*GOOGLEFINANCE(""Currency:CHFEUR""), IF($D20=""Libra Esterlina"&""", 'Original Data'!P20*GOOGLEFINANCE(""Currency:GBPEUR""), IF($D20=""Iene"",'Original Data'!P20*GOOGLEFINANCE(""Currency:JPYEUR""), IF($D20=""HKD"",'Original Data'!P20*GOOGLEFINANCE(""Currency:HKDEUR""), IF($D20=""KRW"",'Original Data'!P20*GOOGLEFINANCE("&"""Currency:KRWEUR""),""""))))))))"),4.32) -> 4.32 | Q20: =IFERROR(__xludf.DUMMYFUNCTION("IF('Original Data'!Q20=""-"",""-"", IF($D20=""Euro"",'Original Data'!Q20, IF($D20=""Dolar"",'Original Data'!Q20*GOOGLEFINANCE(""Currency:USDEUR""), IF($D20=""Franco Suíço"",'Original Data'!Q20*GOOGLEFINANCE(""Currency:CHFEUR""), IF($D20=""Libra Esterlina"&""", 'Original Data'!Q20*GOOGLEFINANCE(""Currency:GBPEUR""), IF($D20=""Iene"",'Original Data'!Q20*GOOGLEFINANCE(""Currency:JPYEUR""), IF($D20=""HKD"",'Original Data'!Q20*GOOGLEFINANCE(""Currency:HKDEUR""), IF($D20=""KRW"",'Original Data'!Q20*GOOGLEFINANCE("&"""Currency:KRWEUR""),""""))))))))"),3.77) -> 3.77 | R20: =IFERROR(__xludf.DUMMYFUNCTION("IF('Original Data'!R20=""-"",""-"", IF($D20=""Euro"",'Original Data'!R20, IF($D20=""Dolar"",'Original Data'!R20*GOOGLEFINANCE(""Currency:USDEUR""), IF($D20=""Franco Suíço"",'Original Data'!R20*GOOGLEFINANCE(""Currency:CHFEUR""), IF($D20=""Libra Esterlina"&""", 'Original Data'!R20*GOOGLEFINANCE(""Currency:GBPEUR""), IF($D20=""Iene"",'Original Data'!R20*GOOGLEFINANCE(""Currency:JPYEUR""), IF($D20=""HKD"",'Original Data'!R20*GOOGLEFINANCE(""Currency:HKDEUR""), IF($D20=""KRW"",'Original Data'!R20*GOOGLEFINANCE("&"""Currency:KRWEUR""),""""))))))))"),4.84) -> 4.84 | S20: =IFERROR(__xludf.DUMMYFUNCTION("IF('Original Data'!S20=""-"",""-"", IF($D20=""Euro"",'Original Data'!S20, IF($D20=""Dolar"",'Original Data'!S20*GOOGLEFINANCE(""Currency:USDEUR""), IF($D20=""Franco Suíço"",'Original Data'!S20*GOOGLEFINANCE(""Currency:CHFEUR""), IF($D20=""Libra Esterlina"&""", 'Original Data'!S20*GOOGLEFINANCE(""Currency:GBPEUR""), IF($D20=""Iene"",'Original Data'!S20*GOOGLEFINANCE(""Currency:JPYEUR""), IF($D20=""HKD"",'Original Data'!S20*GOOGLEFINANCE(""Currency:HKDEUR""), IF($D20=""KRW"",'Original Data'!S20*GOOGLEFINANCE("&"""Currency:KRWEUR""),""""))))))))"),0.32685) -> 0.32685 | T20: =IFERROR(__xludf.DUMMYFUNCTION("IF('Original Data'!T20=""-"",""-"", IF($D20=""Euro"",'Original Data'!T20, IF($D20=""Dolar"",'Original Data'!T20*GOOGLEFINANCE(""Currency:USDEUR""), IF($D20=""Franco Suíço"",'Original Data'!T20*GOOGLEFINANCE(""Currency:CHFEUR""), IF($D20=""Libra Esterlina"&""", 'Original Data'!T20*GOOGLEFINANCE(""Currency:GBPEUR""), IF($D20=""Iene"",'Original Data'!T20*GOOGLEFINANCE(""Currency:JPYEUR""), IF($D20=""HKD"",'Original Data'!T20*GOOGLEFINANCE(""Currency:HKDEUR""), IF($D20=""KRW"",'Original Data'!T20*GOOGLEFINANCE("&"""Currency:KRWEUR""),""""))))))))"),0.44446) -> 0.44446 | U20: =IFERROR(__xludf.DUMMYFUNCTION("IF('Original Data'!U20=""-"",""-"", IF($D20=""Euro"",'Original Data'!U20, IF($D20=""Dolar"",'Original Data'!U20*GOOGLEFINANCE(""Currency:USDEUR""), IF($D20=""Franco Suíço"",'Original Data'!U20*GOOGLEFINANCE(""Currency:CHFEUR""), IF($D20=""Libra Esterlina"&""", 'Original Data'!U20*GOOGLEFINANCE(""Currency:GBPEUR""), IF($D20=""Iene"",'Original Data'!U20*GOOGLEFINANCE(""Currency:JPYEUR""), IF($D20=""HKD"",'Original Data'!U20*GOOGLEFINANCE(""Currency:HKDEUR""), IF($D20=""KRW"",'Original Data'!U20*GOOGLEFINANCE("&"""Currency:KRWEUR""),""""))))))))"),0.46045) -> 0.46045 | V20: =IFERROR(__xludf.DUMMYFUNCTION("IF('Original Data'!V20=""-"",""-"", IF($D20=""Euro"",'Original Data'!V20, IF($D20=""Dolar"",'Original Data'!V20*GOOGLEFINANCE(""Currency:USDEUR""), IF($D20=""Franco Suíço"",'Original Data'!V20*GOOGLEFINANCE(""Currency:CHFEUR""), IF($D20=""Libra Esterlina"&""", 'Original Data'!V20*GOOGLEFINANCE(""Currency:GBPEUR""), IF($D20=""Iene"",'Original Data'!V20*GOOGLEFINANCE(""Currency:JPYEUR""), IF($D20=""HKD"",'Original Data'!V20*GOOGLEFINANCE(""Currency:HKDEUR""), IF($D20=""KRW"",'Original Data'!V20*GOOGLEFINANCE("&"""Currency:KRWEUR""),""""))))))))"),0.6433) -> 0.6433 | W20: D | X20: D | Y20: - | Z20: - | AA20: - | AB20: - | AC20: - | AD20: - | AE20: - | AF20: - | AG20: -
A21: STABILUS SA | B21: STM GY Equity | C21: LU1066226637 | D21: Euro | E21: =IFERROR(__xludf.DUMMYFUNCTION("IF($D21=""Euro"",'Original Data'!E21, IF($D21=""Dolar"",'Original Data'!E21*GOOGLEFINANCE(""Currency:USDEUR""), IF($D21=""Franco Suíço"",'Original Data'!E21*GOOGLEFINANCE(""Currency:CHFEUR""), IF($D21=""Libra Esterlina"", 'Original Data'!E21*GOOGLEFINANCE"&"(""Currency:GBPEUR""), IF($D21=""Iene"",'Original Data'!E21*GOOGLEFINANCE(""Currency:JPYEUR""), IF($D21=""HKD"",'Original Data'!E21*GOOGLEFINANCE(""Currency:HKDEUR""), IF($D21=""KRW"",'Original Data'!E21*GOOGLEFINANCE(""Currency:KRWEUR""),"""")))))))"),23.35) -> 23.35 | F21: =IFERROR(__xludf.DUMMYFUNCTION("IF($D21=""Euro"",'Original Data'!F21, IF($D21=""Dolar"",'Original Data'!F21*GOOGLEFINANCE(""Currency:USDEUR""), IF($D21=""Franco Suíço"",'Original Data'!F21*GOOGLEFINANCE(""Currency:CHFEUR""), IF($D21=""Libra Esterlina"", 'Original Data'!F21*GOOGLEFINANCE"&"(""Currency:GBPEUR""), IF($D21=""Iene"",'Original Data'!F21*GOOGLEFINANCE(""Currency:JPYEUR""), IF($D21=""HKD"",'Original Data'!F21*GOOGLEFINANCE(""Currency:HKDEUR""), IF($D21=""KRW"",'Original Data'!F21*GOOGLEFINANCE(""Currency:KRWEUR""),"""")))))))"),50.35) -> 50.35 | G21: =IFERROR(__xludf.DUMMYFUNCTION("IF($D21=""Euro"",'Original Data'!G21, IF($D21=""Dolar"",'Original Data'!G21*GOOGLEFINANCE(""Currency:USDEUR""), IF($D21=""Franco Suíço"",'Original Data'!G21*GOOGLEFINANCE(""Currency:CHFEUR""), IF($D21=""Libra Esterlina"", 'Original Data'!G21*GOOGLEFINANCE"&"(""Currency:GBPEUR""), IF($D21=""Iene"",'Original Data'!G21*GOOGLEFINANCE(""Currency:JPYEUR""), IF($D21=""HKD"",'Original Data'!G21*GOOGLEFINANCE(""Currency:HKDEUR""), IF($D21=""KRW"",'Original Data'!G21*GOOGLEFINANCE(""Currency:KRWEUR""),"""")))))))"),1.24) -> 1.24 | H21: 0.03112 | I21: 15.92 | J21: 0.0253 | K21: 0.0845 | L21: 0.0701 | M21: 0.1698 | N21: =IFERROR(__xludf.DUMMYFUNCTION("IF('Original Data'!N21=""-"",""-"", IF($D21=""Euro"",'Original Data'!N21, IF($D21=""Dolar"",'Original Data'!N21*GOOGLEFINANCE(""Currency:USDEUR""), IF($D21=""Franco Suíço"",'Original Data'!N21*GOOGLEFINANCE(""Currency:CHFEUR""), IF($D21=""Libra Esterlina"&""", 'Original Data'!N21*GOOGLEFINANCE(""Currency:GBPEUR""), IF($D21=""Iene"",'Original Data'!N21*GOOGLEFINANCE(""Currency:JPYEUR""), IF($D21=""HKD"",'Original Data'!N21*GOOGLEFINANCE(""Currency:HKDEUR""), IF($D21=""KRW"",'Original Data'!N21*GOOGLEFINANCE("&"""Currency:KRWEUR""),""""))))))))"),2.97) -> 2.97 | O21: =IFERROR(__xludf.DUMMYFUNCTION("IF('Original Data'!O21=""-"",""-"", IF($D21=""Euro"",'Original Data'!O21, IF($D21=""Dolar"",'Original Data'!O21*GOOGLEFINANCE(""Currency:USDEUR""), IF($D21=""Franco Suíço"",'Original Data'!O21*GOOGLEFINANCE(""Currency:CHFEUR""), IF($D21=""Libra Esterlina"&""", 'Original Data'!O21*GOOGLEFINANCE(""Currency:GBPEUR""), IF($D21=""Iene"",'Original Data'!O21*GOOGLEFINANCE(""Currency:JPYEUR""), IF($D21=""HKD"",'Original Data'!O21*GOOGLEFINANCE(""Currency:HKDEUR""), IF($D21=""KRW"",'Original Data'!O21*GOOGLEFINANCE("&"""Currency:KRWEUR""),""""))))))))"),0.96256) -> 0.96256 | P21: =IFERROR(__xludf.DUMMYFUNCTION("IF('Original Data'!P21=""-"",""-"", IF($D21=""Euro"",'Original Data'!P21, IF($D21=""Dolar"",'Original Data'!P21*GOOGLEFINANCE(""Currency:USDEUR""), IF($D21=""Franco Suíço"",'Original Data'!P21*GOOGLEFINANCE(""Currency:CHFEUR""), IF($D21=""Libra Esterlina"&""", 'Original Data'!P21*GOOGLEFINANCE(""Currency:GBPEUR""), IF($D21=""Iene"",'Original Data'!P21*GOOGLEFINANCE(""Currency:JPYEUR""), IF($D21=""HKD"",'Original Data'!P21*GOOGLEFINANCE(""Currency:HKDEUR""), IF($D21=""KRW"",'Original Data'!P21*GOOGLEFINANCE("&"""Currency:KRWEUR""),""""))))))))"),0.995134) -> 0.995134 | Q21: =IFERROR(__xludf.DUMMYFUNCTION("IF('Original Data'!Q21=""-"",""-"", IF($D21=""Euro"",'Original Data'!Q21, IF($D21=""Dolar"",'Original Data'!Q21*GOOGLEFINANCE(""Currency:USDEUR""), IF($D21=""Franco Suíço"",'Original Data'!Q21*GOOGLEFINANCE(""Currency:CHFEUR""), IF($D21=""Libra Esterlina"&""", 'Original Data'!Q21*GOOGLEFINANCE(""Currency:GBPEUR""), IF($D21=""Iene"",'Original Data'!Q21*GOOGLEFINANCE(""Currency:JPYEUR""), IF($D21=""HKD"",'Original Data'!Q21*GOOGLEFINANCE(""Currency:HKDEUR""), IF($D21=""KRW"",'Original Data'!Q21*GOOGLEFINANCE("&"""Currency:KRWEUR""),""""))))))))"),0.92213) -> 0.92213 | R21: =IFERROR(__xludf.DUMMYFUNCTION("IF('Original Data'!R21=""-"",""-"", IF($D21=""Euro"",'Original Data'!R21, IF($D21=""Dolar"",'Original Data'!R21*GOOGLEFINANCE(""Currency:USDEUR""), IF($D21=""Franco Suíço"",'Original Data'!R21*GOOGLEFINANCE(""Currency:CHFEUR""), IF($D21=""Libra Esterlina"&""", 'Original Data'!R21*GOOGLEFINANCE(""Currency:GBPEUR""), IF($D21=""Iene"",'Original Data'!R21*GOOGLEFINANCE(""Currency:JPYEUR""), IF($D21=""HKD"",'Original Data'!R21*GOOGLEFINANCE(""Currency:HKDEUR""), IF($D21=""KRW"",'Original Data'!R21*GOOGLEFINANCE("&"""Currency:KRWEUR""),""""))))))))"),0.93767) -> 0.93767 | S21: =IFERROR(__xludf.DUMMYFUNCTION("IF('Original Data'!S21=""-"",""-"", IF($D21=""Euro"",'Original Data'!S21, IF($D21=""Dolar"",'Original Data'!S21*GOOGLEFINANCE(""Currency:USDEUR""), IF($D21=""Franco Suíço"",'Original Data'!S21*GOOGLEFINANCE(""Currency:CHFEUR""), IF($D21=""Libra Esterlina"&""", 'Original Data'!S21*GOOGLEFINANCE(""Currency:GBPEUR""), IF($D21=""Iene"",'Original Data'!S21*GOOGLEFINANCE(""Currency:JPYEUR""), IF($D21=""HKD"",'Original Data'!S21*GOOGLEFINANCE(""Currency:HKDEUR""), IF($D21=""KRW"",'Original Data'!S21*GOOGLEFINANCE("&"""Currency:KRWEUR""),""""))))))))"),0.18711) -> 0.18711 | T21: =IFERROR(__xludf.DUMMYFUNCTION("IF('Original Data'!T21=""-"",""-"", IF($D21=""Euro"",'Original Data'!T21, IF($D21=""Dolar"",'Original Data'!T21*GOOGLEFINANCE(""Currency:USDEUR""), IF($D21=""Franco Suíço"",'Original Data'!T21*GOOGLEFINANCE(""Currency:CHFEUR""), IF($D21=""Libra Esterlina"&""", 'Original Data'!T21*GOOGLEFINANCE(""Currency:GBPEUR""), IF($D21=""Iene"",'Original Data'!T21*GOOGLEFINANCE(""Currency:JPYEUR""), IF($D21=""HKD"",'Original Data'!T21*GOOGLEFINANCE(""Currency:HKDEUR""), IF($D21=""KRW"",'Original Data'!T21*GOOGLEFINANCE("&"""Currency:KRWEUR""),""""))))))))"),0.17702) -> 0.17702 | U21: =IFERROR(__xludf.DUMMYFUNCTION("IF('Original Data'!U21=""-"",""-"", IF($D21=""Euro"",'Original Data'!U21, IF($D21=""Dolar"",'Original Data'!U21*GOOGLEFINANCE(""Currency:USDEUR""), IF($D21=""Franco Suíço"",'Original Data'!U21*GOOGLEFINANCE(""Currency:CHFEUR""), IF($D21=""Libra Esterlina"&""", 'Original Data'!U21*GOOGLEFINANCE(""Currency:GBPEUR""), IF($D21=""Iene"",'Original Data'!U21*GOOGLEFINANCE(""Currency:JPYEUR""), IF($D21=""HKD"",'Original Data'!U21*GOOGLEFINANCE(""Currency:HKDEUR""), IF($D21=""KRW"",'Original Data'!U21*GOOGLEFINANCE("&"""Currency:KRWEUR""),""""))))))))"),0.14744) -> 0.14744 | V21: =IFERROR(__xludf.DUMMYFUNCTION("IF('Original Data'!V21=""-"",""-"", IF($D21=""Euro"",'Original Data'!V21, IF($D21=""Dolar"",'Original Data'!V21*GOOGLEFINANCE(""Currency:USDEUR""), IF($D21=""Franco Suíço"",'Original Data'!V21*GOOGLEFINANCE(""Currency:CHFEUR""), IF($D21=""Libra Esterlina"&""", 'Original Data'!V21*GOOGLEFINANCE(""Currency:GBPEUR""), IF($D21=""Iene"",'Original Data'!V21*GOOGLEFINANCE(""Currency:JPYEUR""), IF($D21=""HKD"",'Original Data'!V21*GOOGLEFINANCE(""Currency:HKDEUR""), IF($D21=""KRW"",'Original Data'!V21*GOOGLEFINANCE("&"""Currency:KRWEUR""),""""))))))))"),0.018202) -> 0.018202 | W21: - | X21: - | Y21: - | Z21: - | AA21: - | AB21: - | AC21: - | AD21: - | AE21: - | AF21: - | AG21: -
A22: DECEUNINCK NV | B22: DECB BB Equity | C22: BE0003789063 | D22: Euro | E22: =IFERROR(__xludf.DUMMYFUNCTION("IF($D22=""Euro"",'Original Data'!E22, IF($D22=""Dolar"",'Original Data'!E22*GOOGLEFINANCE(""Currency:USDEUR""), IF($D22=""Franco Suíço"",'Original Data'!E22*GOOGLEFINANCE(""Currency:CHFEUR""), IF($D22=""Libra Esterlina"", 'Original Data'!E22*GOOGLEFINANCE"&"(""Currency:GBPEUR""), IF($D22=""Iene"",'Original Data'!E22*GOOGLEFINANCE(""Currency:JPYEUR""), IF($D22=""HKD"",'Original Data'!E22*GOOGLEFINANCE(""Currency:HKDEUR""), IF($D22=""KRW"",'Original Data'!E22*GOOGLEFINANCE(""Currency:KRWEUR""),"""")))))))"),7.01) -> 7.01 | F22: =IFERROR(__xludf.DUMMYFUNCTION("IF($D22=""Euro"",'Original Data'!F22, IF($D22=""Dolar"",'Original Data'!F22*GOOGLEFINANCE(""Currency:USDEUR""), IF($D22=""Franco Suíço"",'Original Data'!F22*GOOGLEFINANCE(""Currency:CHFEUR""), IF($D22=""Libra Esterlina"", 'Original Data'!F22*GOOGLEFINANCE"&"(""Currency:GBPEUR""), IF($D22=""Iene"",'Original Data'!F22*GOOGLEFINANCE(""Currency:JPYEUR""), IF($D22=""HKD"",'Original Data'!F22*GOOGLEFINANCE(""Currency:HKDEUR""), IF($D22=""KRW"",'Original Data'!F22*GOOGLEFINANCE(""Currency:KRWEUR""),"""")))))))"),2.83) -> 2.83 | G22: =IFERROR(__xludf.DUMMYFUNCTION("IF($D22=""Euro"",'Original Data'!G22, IF($D22=""Dolar"",'Original Data'!G22*GOOGLEFINANCE(""Currency:USDEUR""), IF($D22=""Franco Suíço"",'Original Data'!G22*GOOGLEFINANCE(""Currency:CHFEUR""), IF($D22=""Libra Esterlina"", 'Original Data'!G22*GOOGLEFINANCE"&"(""Currency:GBPEUR""), IF($D22=""Iene"",'Original Data'!G22*GOOGLEFINANCE(""Currency:JPYEUR""), IF($D22=""HKD"",'Original Data'!G22*GOOGLEFINANCE(""Currency:HKDEUR""), IF($D22=""KRW"",'Original Data'!G22*GOOGLEFINANCE(""Currency:KRWEUR""),"""")))))))"),0.381) -> 0.381 | H22: 0.22757 | I22: 11.16 | J22: -% | K22: 0.039 | L22: 0.0261 | M22: 0.0568 | N22: =IFERROR(__xludf.DUMMYFUNCTION("IF('Original Data'!N22=""-"",""-"", IF($D22=""Euro"",'Original Data'!N22, IF($D22=""Dolar"",'Original Data'!N22*GOOGLEFINANCE(""Currency:USDEUR""), IF($D22=""Franco Suíço"",'Original Data'!N22*GOOGLEFINANCE(""Currency:CHFEUR""), IF($D22=""Libra Esterlina"&""", 'Original Data'!N22*GOOGLEFINANCE(""Currency:GBPEUR""), IF($D22=""Iene"",'Original Data'!N22*GOOGLEFINANCE(""Currency:JPYEUR""), IF($D22=""HKD"",'Original Data'!N22*GOOGLEFINANCE(""Currency:HKDEUR""), IF($D22=""KRW"",'Original Data'!N22*GOOGLEFINANCE("&"""Currency:KRWEUR""),""""))))))))"),0.25) -> 0.25 | O22: =IFERROR(__xludf.DUMMYFUNCTION("IF('Original Data'!O22=""-"",""-"", IF($D22=""Euro"",'Original Data'!O22, IF($D22=""Dolar"",'Original Data'!O22*GOOGLEFINANCE(""Currency:USDEUR""), IF($D22=""Franco Suíço"",'Original Data'!O22*GOOGLEFINANCE(""Currency:CHFEUR""), IF($D22=""Libra Esterlina"&""", 'Original Data'!O22*GOOGLEFINANCE(""Currency:GBPEUR""), IF($D22=""Iene"",'Original Data'!O22*GOOGLEFINANCE(""Currency:JPYEUR""), IF($D22=""HKD"",'Original Data'!O22*GOOGLEFINANCE(""Currency:HKDEUR""), IF($D22=""KRW"",'Original Data'!O22*GOOGLEFINANCE("&"""Currency:KRWEUR""),""""))))))))"),0.67423) -> 0.67423 | P22: =IFERROR(__xludf.DUMMYFUNCTION("IF('Original Data'!P22=""-"",""-"", IF($D22=""Euro"",'Original Data'!P22, IF($D22=""Dolar"",'Original Data'!P22*GOOGLEFINANCE(""Currency:USDEUR""), IF($D22=""Franco Suíço"",'Original Data'!P22*GOOGLEFINANCE(""Currency:CHFEUR""), IF($D22=""Libra Esterlina"&""", 'Original Data'!P22*GOOGLEFINANCE(""Currency:GBPEUR""), IF($D22=""Iene"",'Original Data'!P22*GOOGLEFINANCE(""Currency:JPYEUR""), IF($D22=""HKD"",'Original Data'!P22*GOOGLEFINANCE(""Currency:HKDEUR""), IF($D22=""KRW"",'Original Data'!P22*GOOGLEFINANCE("&"""Currency:KRWEUR""),""""))))))))"),0.63381) -> 0.63381 | Q22: =IFERROR(__xludf.DUMMYFUNCTION("IF('Original Data'!Q22=""-"",""-"", IF($D22=""Euro"",'Original Data'!Q22, IF($D22=""Dolar"",'Original Data'!Q22*GOOGLEFINANCE(""Currency:USDEUR""), IF($D22=""Franco Suíço"",'Original Data'!Q22*GOOGLEFINANCE(""Currency:CHFEUR""), IF($D22=""Libra Esterlina"&""", 'Original Data'!Q22*GOOGLEFINANCE(""Currency:GBPEUR""), IF($D22=""Iene"",'Original Data'!Q22*GOOGLEFINANCE(""Currency:JPYEUR""), IF($D22=""HKD"",'Original Data'!Q22*GOOGLEFINANCE(""Currency:HKDEUR""), IF($D22=""KRW"",'Original Data'!Q22*GOOGLEFINANCE("&"""Currency:KRWEUR""),""""))))))))"),0.64219) -> 0.64219 | R22: =IFERROR(__xludf.DUMMYFUNCTION("IF('Original Data'!R22=""-"",""-"", IF($D22=""Euro"",'Original Data'!R22, IF($D22=""Dolar"",'Original Data'!R22*GOOGLEFINANCE(""Currency:USDEUR""), IF($D22=""Franco Suíço"",'Original Data'!R22*GOOGLEFINANCE(""Currency:CHFEUR""), IF($D22=""Libra Esterlina"&""", 'Original Data'!R22*GOOGLEFINANCE(""Currency:GBPEUR""), IF($D22=""Iene"",'Original Data'!R22*GOOGLEFINANCE(""Currency:JPYEUR""), IF($D22=""HKD"",'Original Data'!R22*GOOGLEFINANCE(""Currency:HKDEUR""), IF($D22=""KRW"",'Original Data'!R22*GOOGLEFINANCE("&"""Currency:KRWEUR""),""""))))))))"),0.8381) -> 0.8381 | S22: =IFERROR(__xludf.DUMMYFUNCTION("IF('Original Data'!S22=""-"",""-"", IF($D22=""Euro"",'Original Data'!S22, IF($D22=""Dolar"",'Original Data'!S22*GOOGLEFINANCE(""Currency:USDEUR""), IF($D22=""Franco Suíço"",'Original Data'!S22*GOOGLEFINANCE(""Currency:CHFEUR""), IF($D22=""Libra Esterlina"&""", 'Original Data'!S22*GOOGLEFINANCE(""Currency:GBPEUR""), IF($D22=""Iene"",'Original Data'!S22*GOOGLEFINANCE(""Currency:JPYEUR""), IF($D22=""HKD"",'Original Data'!S22*GOOGLEFINANCE(""Currency:HKDEUR""), IF($D22=""KRW"",'Original Data'!S22*GOOGLEFINANCE("&"""Currency:KRWEUR""),""""))))))))"),0.06996) -> 0.06996 | T22: =IFERROR(__xludf.DUMMYFUNCTION("IF('Original Data'!T22=""-"",""-"", IF($D22=""Euro"",'Original Data'!T22, IF($D22=""Dolar"",'Original Data'!T22*GOOGLEFINANCE(""Currency:USDEUR""), IF($D22=""Franco Suíço"",'Original Data'!T22*GOOGLEFINANCE(""Currency:CHFEUR""), IF($D22=""Libra Esterlina"&""", 'Original Data'!T22*GOOGLEFINANCE(""Currency:GBPEUR""), IF($D22=""Iene"",'Original Data'!T22*GOOGLEFINANCE(""Currency:JPYEUR""), IF($D22=""HKD"",'Original Data'!T22*GOOGLEFINANCE(""Currency:HKDEUR""), IF($D22=""KRW"",'Original Data'!T22*GOOGLEFINANCE("&"""Currency:KRWEUR""),""""))))))))"),0.04619) -> 0.04619 | U22: =IFERROR(__xludf.DUMMYFUNCTION("IF('Original Data'!U22=""-"",""-"", IF($D22=""Euro"",'Original Data'!U22, IF($D22=""Dolar"",'Original Data'!U22*GOOGLEFINANCE(""Currency:USDEUR""), IF($D22=""Franco Suíço"",'Original Data'!U22*GOOGLEFINANCE(""Currency:CHFEUR""), IF($D22=""Libra Esterlina"&""", 'Original Data'!U22*GOOGLEFINANCE(""Currency:GBPEUR""), IF($D22=""Iene"",'Original Data'!U22*GOOGLEFINANCE(""Currency:JPYEUR""), IF($D22=""HKD"",'Original Data'!U22*GOOGLEFINANCE(""Currency:HKDEUR""), IF($D22=""KRW"",'Original Data'!U22*GOOGLEFINANCE("&"""Currency:KRWEUR""),""""))))))))"),0.08) -> 0.08 | V22: =IFERROR(__xludf.DUMMYFUNCTION("IF('Original Data'!V22=""-"",""-"", IF($D22=""Euro"",'Original Data'!V22, IF($D22=""Dolar"",'Original Data'!V22*GOOGLEFINANCE(""Currency:USDEUR""), IF($D22=""Franco Suíço"",'Original Data'!V22*GOOGLEFINANCE(""Currency:CHFEUR""), IF($D22=""Libra Esterlina"&""", 'Original Data'!V22*GOOGLEFINANCE(""Currency:GBPEUR""), IF($D22=""Iene"",'Original Data'!V22*GOOGLEFINANCE(""Currency:JPYEUR""), IF($D22=""HKD"",'Original Data'!V22*GOOGLEFINANCE(""Currency:HKDEUR""), IF($D22=""KRW"",'Original Data'!V22*GOOGLEFINANCE("&"""Currency:KRWEUR""),""""))))))))"),0.08511) -> 0.08511 | W22: No Response | X22: D | Y22: - | Z22: - | AA22: - | AB22: - | AC22: - | AD22: - | AE22: - | AF22: - | AG22: -
A23: MUENCHENER RUE-R | B23: MUV2 GY Equity | C23: DE0008430026 | D23: Euro | E23: =IFERROR(__xludf.DUMMYFUNCTION("IF($D23=""Euro"",'Original Data'!E23, IF($D23=""Dolar"",'Original Data'!E23*GOOGLEFINANCE(""Currency:USDEUR""), IF($D23=""Franco Suíço"",'Original Data'!E23*GOOGLEFINANCE(""Currency:CHFEUR""), IF($D23=""Libra Esterlina"", 'Original Data'!E23*GOOGLEFINANCE"&"(""Currency:GBPEUR""), IF($D23=""Iene"",'Original Data'!E23*GOOGLEFINANCE(""Currency:JPYEUR""), IF($D23=""HKD"",'Original Data'!E23*GOOGLEFINANCE(""Currency:HKDEUR""), IF($D23=""KRW"",'Original Data'!E23*GOOGLEFINANCE(""Currency:KRWEUR""),"""")))))))"),216.89) -> 216.89 | F23: =IFERROR(__xludf.DUMMYFUNCTION("IF($D23=""Euro"",'Original Data'!F23, IF($D23=""Dolar"",'Original Data'!F23*GOOGLEFINANCE(""Currency:USDEUR""), IF($D23=""Franco Suíço"",'Original Data'!F23*GOOGLEFINANCE(""Currency:CHFEUR""), IF($D23=""Libra Esterlina"", 'Original Data'!F23*GOOGLEFINANCE"&"(""Currency:GBPEUR""), IF($D23=""Iene"",'Original Data'!F23*GOOGLEFINANCE(""Currency:JPYEUR""), IF($D23=""HKD"",'Original Data'!F23*GOOGLEFINANCE(""Currency:HKDEUR""), IF($D23=""KRW"",'Original Data'!F23*GOOGLEFINANCE(""Currency:KRWEUR""),"""")))))))"),240.0) -> 240 | G23: =IFERROR(__xludf.DUMMYFUNCTION("IF($D23=""Euro"",'Original Data'!G23, IF($D23=""Dolar"",'Original Data'!G23*GOOGLEFINANCE(""Currency:USDEUR""), IF($D23=""Franco Suíço"",'Original Data'!G23*GOOGLEFINANCE(""Currency:CHFEUR""), IF($D23=""Libra Esterlina"", 'Original Data'!G23*GOOGLEFINANCE"&"(""Currency:GBPEUR""), IF($D23=""Iene"",'Original Data'!G23*GOOGLEFINANCE(""Currency:JPYEUR""), IF($D23=""HKD"",'Original Data'!G23*GOOGLEFINANCE(""Currency:HKDEUR""), IF($D23=""KRW"",'Original Data'!G23*GOOGLEFINANCE(""Currency:KRWEUR""),"""")))))))"),33.65) -> 33.65 | H23: 0.498115 | I23: 11.47 | J23: 0.0458 | K23: -% | L23: 0.0065 | M23: 0.0695 | N23: =IFERROR(__xludf.DUMMYFUNCTION("IF('Original Data'!N23=""-"",""-"", IF($D23=""Euro"",'Original Data'!N23, IF($D23=""Dolar"",'Original Data'!N23*GOOGLEFINANCE(""Currency:USDEUR""), IF($D23=""Franco Suíço"",'Original Data'!N23*GOOGLEFINANCE(""Currency:CHFEUR""), IF($D23=""Libra Esterlina"&""", 'Original Data'!N23*GOOGLEFINANCE(""Currency:GBPEUR""), IF($D23=""Iene"",'Original Data'!N23*GOOGLEFINANCE(""Currency:JPYEUR""), IF($D23=""HKD"",'Original Data'!N23*GOOGLEFINANCE(""Currency:HKDEUR""), IF($D23=""KRW"",'Original Data'!N23*GOOGLEFINANCE("&"""Currency:KRWEUR""),""""))))))))"),20.94) -> 20.94 | O23: =IFERROR(__xludf.DUMMYFUNCTION("IF('Original Data'!O23=""-"",""-"", IF($D23=""Euro"",'Original Data'!O23, IF($D23=""Dolar"",'Original Data'!O23*GOOGLEFINANCE(""Currency:USDEUR""), IF($D23=""Franco Suíço"",'Original Data'!O23*GOOGLEFINANCE(""Currency:CHFEUR""), IF($D23=""Libra Esterlina"&""", 'Original Data'!O23*GOOGLEFINANCE(""Currency:GBPEUR""), IF($D23=""Iene"",'Original Data'!O23*GOOGLEFINANCE(""Currency:JPYEUR""), IF($D23=""HKD"",'Original Data'!O23*GOOGLEFINANCE(""Currency:HKDEUR""), IF($D23=""KRW"",'Original Data'!O23*GOOGLEFINANCE("&"""Currency:KRWEUR""),""""))))))))"),57.34) -> 57.34 | P23: =IFERROR(__xludf.DUMMYFUNCTION("IF('Original Data'!P23=""-"",""-"", IF($D23=""Euro"",'Original Data'!P23, IF($D23=""Dolar"",'Original Data'!P23*GOOGLEFINANCE(""Currency:USDEUR""), IF($D23=""Franco Suíço"",'Original Data'!P23*GOOGLEFINANCE(""Currency:CHFEUR""), IF($D23=""Libra Esterlina"&""", 'Original Data'!P23*GOOGLEFINANCE(""Currency:GBPEUR""), IF($D23=""Iene"",'Original Data'!P23*GOOGLEFINANCE(""Currency:JPYEUR""), IF($D23=""HKD"",'Original Data'!P23*GOOGLEFINANCE(""Currency:HKDEUR""), IF($D23=""KRW"",'Original Data'!P23*GOOGLEFINANCE("&"""Currency:KRWEUR""),""""))))))))"),64.85) -> 64.85 | Q23: =IFERROR(__xludf.DUMMYFUNCTION("IF('Original Data'!Q23=""-"",""-"", IF($D23=""Euro"",'Original Data'!Q23, IF($D23=""Dolar"",'Original Data'!Q23*GOOGLEFINANCE(""Currency:USDEUR""), IF($D23=""Franco Suíço"",'Original Data'!Q23*GOOGLEFINANCE(""Currency:CHFEUR""), IF($D23=""Libra Esterlina"&""", 'Original Data'!Q23*GOOGLEFINANCE(""Currency:GBPEUR""), IF($D23=""Iene"",'Original Data'!Q23*GOOGLEFINANCE(""Currency:JPYEUR""), IF($D23=""HKD"",'Original Data'!Q23*GOOGLEFINANCE(""Currency:HKDEUR""), IF($D23=""KRW"",'Original Data'!Q23*GOOGLEFINANCE("&"""Currency:KRWEUR""),""""))))))))"),66.44) -> 66.44 | R23: =IFERROR(__xludf.DUMMYFUNCTION("IF('Original Data'!R23=""-"",""-"", IF($D23=""Euro"",'Original Data'!R23, IF($D23=""Dolar"",'Original Data'!R23*GOOGLEFINANCE(""Currency:USDEUR""), IF($D23=""Franco Suíço"",'Original Data'!R23*GOOGLEFINANCE(""Currency:CHFEUR""), IF($D23=""Libra Esterlina"&""", 'Original Data'!R23*GOOGLEFINANCE(""Currency:GBPEUR""), IF($D23=""Iene"",'Original Data'!R23*GOOGLEFINANCE(""Currency:JPYEUR""), IF($D23=""HKD"",'Original Data'!R23*GOOGLEFINANCE(""Currency:HKDEUR""), IF($D23=""KRW"",'Original Data'!R23*GOOGLEFINANCE("&"""Currency:KRWEUR""),""""))))))))"),70.24) -> 70.24 | S23: =IFERROR(__xludf.DUMMYFUNCTION("IF('Original Data'!S23=""-"",""-"", IF($D23=""Euro"",'Original Data'!S23, IF($D23=""Dolar"",'Original Data'!S23*GOOGLEFINANCE(""Currency:USDEUR""), IF($D23=""Franco Suíço"",'Original Data'!S23*GOOGLEFINANCE(""Currency:CHFEUR""), IF($D23=""Libra Esterlina"&""", 'Original Data'!S23*GOOGLEFINANCE(""Currency:GBPEUR""), IF($D23=""Iene"",'Original Data'!S23*GOOGLEFINANCE(""Currency:JPYEUR""), IF($D23=""HKD"",'Original Data'!S23*GOOGLEFINANCE(""Currency:HKDEUR""), IF($D23=""KRW"",'Original Data'!S23*GOOGLEFINANCE("&"""Currency:KRWEUR""),""""))))))))"),"-") -> - | T23: =IFERROR(__xludf.DUMMYFUNCTION("IF('Original Data'!T23=""-"",""-"", IF($D23=""Euro"",'Original Data'!T23, IF($D23=""Dolar"",'Original Data'!T23*GOOGLEFINANCE(""Currency:USDEUR""), IF($D23=""Franco Suíço"",'Original Data'!T23*GOOGLEFINANCE(""Currency:CHFEUR""), IF($D23=""Libra Esterlina"&""", 'Original Data'!T23*GOOGLEFINANCE(""Currency:GBPEUR""), IF($D23=""Iene"",'Original Data'!T23*GOOGLEFINANCE(""Currency:JPYEUR""), IF($D23=""HKD"",'Original Data'!T23*GOOGLEFINANCE(""Currency:HKDEUR""), IF($D23=""KRW"",'Original Data'!T23*GOOGLEFINANCE("&"""Currency:KRWEUR""),""""))))))))"),"-") -> - | U23: =IFERROR(__xludf.DUMMYFUNCTION("IF('Original Data'!U23=""-"",""-"", IF($D23=""Euro"",'Original Data'!U23, IF($D23=""Dolar"",'Original Data'!U23*GOOGLEFINANCE(""Currency:USDEUR""), IF($D23=""Franco Suíço"",'Original Data'!U23*GOOGLEFINANCE(""Currency:CHFEUR""), IF($D23=""Libra Esterlina"&""", 'Original Data'!U23*GOOGLEFINANCE(""Currency:GBPEUR""), IF($D23=""Iene"",'Original Data'!U23*GOOGLEFINANCE(""Currency:JPYEUR""), IF($D23=""HKD"",'Original Data'!U23*GOOGLEFINANCE(""Currency:HKDEUR""), IF($D23=""KRW"",'Original Data'!U23*GOOGLEFINANCE("&"""Currency:KRWEUR""),""""))))))))"),"-") -> - | V23: =IFERROR(__xludf.DUMMYFUNCTION("IF('Original Data'!V23=""-"",""-"", IF($D23=""Euro"",'Original Data'!V23, IF($D23=""Dolar"",'Original Data'!V23*GOOGLEFINANCE(""Currency:USDEUR""), IF($D23=""Franco Suíço"",'Original Data'!V23*GOOGLEFINANCE(""Currency:CHFEUR""), IF($D23=""Libra Esterlina"&""", 'Original Data'!V23*GOOGLEFINANCE(""Currency:GBPEUR""), IF($D23=""Iene"",'Original Data'!V23*GOOGLEFINANCE(""Currency:JPYEUR""), IF($D23=""HKD"",'Original Data'!V23*GOOGLEFINANCE(""Currency:HKDEUR""), IF($D23=""KRW"",'Original Data'!V23*GOOGLEFINANCE("&"""Currency:KRWEUR""),""""))))))))"),"-") -> - | W23: B | X23: A- | Y23: - | Z23: - | AA23: - | AB23: - | AC23: 18 | AD23: 0.4 | AE23: 9.7 | AF23: 8.2 | AG23: 2
A24: AENA SME SA | B24: AENA SM Equity | C24: ES0105046009 | D24: Euro | E24: =IFERROR(__xludf.DUMMYFUNCTION("IF($D24=""Euro"",'Original Data'!E24, IF($D24=""Dolar"",'Original Data'!E24*GOOGLEFINANCE(""Currency:USDEUR""), IF($D24=""Franco Suíço"",'Original Data'!E24*GOOGLEFINANCE(""Currency:CHFEUR""), IF($D24=""Libra Esterlina"", 'Original Data'!E24*GOOGLEFINANCE"&"(""Currency:GBPEUR""), IF($D24=""Iene"",'Original Data'!E24*GOOGLEFINANCE(""Currency:JPYEUR""), IF($D24=""HKD"",'Original Data'!E24*GOOGLEFINANCE(""Currency:HKDEUR""), IF($D24=""KRW"",'Original Data'!E24*GOOGLEFINANCE(""Currency:KRWEUR""),"""")))))))"),74.0) -> 74 | F24: =IFERROR(__xludf.DUMMYFUNCTION("IF($D24=""Euro"",'Original Data'!F24, IF($D24=""Dolar"",'Original Data'!F24*GOOGLEFINANCE(""Currency:USDEUR""), IF($D24=""Franco Suíço"",'Original Data'!F24*GOOGLEFINANCE(""Currency:CHFEUR""), IF($D24=""Libra Esterlina"", 'Original Data'!F24*GOOGLEFINANCE"&"(""Currency:GBPEUR""), IF($D24=""Iene"",'Original Data'!F24*GOOGLEFINANCE(""Currency:JPYEUR""), IF($D24=""HKD"",'Original Data'!F24*GOOGLEFINANCE(""Currency:HKDEUR""), IF($D24=""KRW"",'Original Data'!F24*GOOGLEFINANCE(""Currency:KRWEUR""),"""")))))))"),145.15) -> 145.15 | G24: =IFERROR(__xludf.DUMMYFUNCTION("IF($D24=""Euro"",'Original Data'!G24, IF($D24=""Dolar"",'Original Data'!G24*GOOGLEFINANCE(""Currency:USDEUR""), IF($D24=""Franco Suíço"",'Original Data'!G24*GOOGLEFINANCE(""Currency:CHFEUR""), IF($D24=""Libra Esterlina"", 'Original Data'!G24*GOOGLEFINANCE"&"(""Currency:GBPEUR""), IF($D24=""Iene"",'Original Data'!G24*GOOGLEFINANCE(""Currency:JPYEUR""), IF($D24=""HKD"",'Original Data'!G24*GOOGLEFINANCE(""Currency:HKDEUR""), IF($D24=""KRW"",'Original Data'!G24*GOOGLEFINANCE(""Currency:KRWEUR""),"""")))))))"),21.86) -> 21.86 | H24: 0.24999 | I24: - | J24: -% | K24: 0.0551 | L24: 0.0488 | M24: 0.1281 | N24: =IFERROR(__xludf.DUMMYFUNCTION("IF('Original Data'!N24=""-"",""-"", IF($D24=""Euro"",'Original Data'!N24, IF($D24=""Dolar"",'Original Data'!N24*GOOGLEFINANCE(""Currency:USDEUR""), IF($D24=""Franco Suíço"",'Original Data'!N24*GOOGLEFINANCE(""Currency:CHFEUR""), IF($D24=""Libra Esterlina"&""", 'Original Data'!N24*GOOGLEFINANCE(""Currency:GBPEUR""), IF($D24=""Iene"",'Original Data'!N24*GOOGLEFINANCE(""Currency:JPYEUR""), IF($D24=""HKD"",'Original Data'!N24*GOOGLEFINANCE(""Currency:HKDEUR""), IF($D24=""KRW"",'Original Data'!N24*GOOGLEFINANCE("&"""Currency:KRWEUR""),""""))))))))"),-0.4) -> -0.4 | O24: =IFERROR(__xludf.DUMMYFUNCTION("IF('Original Data'!O24=""-"",""-"", IF($D24=""Euro"",'Original Data'!O24, IF($D24=""Dolar"",'Original Data'!O24*GOOGLEFINANCE(""Currency:USDEUR""), IF($D24=""Franco Suíço"",'Original Data'!O24*GOOGLEFINANCE(""Currency:CHFEUR""), IF($D24=""Libra Esterlina"&""", 'Original Data'!O24*GOOGLEFINANCE(""Currency:GBPEUR""), IF($D24=""Iene"",'Original Data'!O24*GOOGLEFINANCE(""Currency:JPYEUR""), IF($D24=""HKD"",'Original Data'!O24*GOOGLEFINANCE(""Currency:HKDEUR""), IF($D24=""KRW"",'Original Data'!O24*GOOGLEFINANCE("&"""Currency:KRWEUR""),""""))))))))"),4.2) -> 4.2 | P24: =IFERROR(__xludf.DUMMYFUNCTION("IF('Original Data'!P24=""-"",""-"", IF($D24=""Euro"",'Original Data'!P24, IF($D24=""Dolar"",'Original Data'!P24*GOOGLEFINANCE(""Currency:USDEUR""), IF($D24=""Franco Suíço"",'Original Data'!P24*GOOGLEFINANCE(""Currency:CHFEUR""), IF($D24=""Libra Esterlina"&""", 'Original Data'!P24*GOOGLEFINANCE(""Currency:GBPEUR""), IF($D24=""Iene"",'Original Data'!P24*GOOGLEFINANCE(""Currency:JPYEUR""), IF($D24=""HKD"",'Original Data'!P24*GOOGLEFINANCE(""Currency:HKDEUR""), IF($D24=""KRW"",'Original Data'!P24*GOOGLEFINANCE("&"""Currency:KRWEUR""),""""))))))))"),4.44) -> 4.44 | Q24: =IFERROR(__xludf.DUMMYFUNCTION("IF('Original Data'!Q24=""-"",""-"", IF($D24=""Euro"",'Original Data'!Q24, IF($D24=""Dolar"",'Original Data'!Q24*GOOGLEFINANCE(""Currency:USDEUR""), IF($D24=""Franco Suíço"",'Original Data'!Q24*GOOGLEFINANCE(""Currency:CHFEUR""), IF($D24=""Libra Esterlina"&""", 'Original Data'!Q24*GOOGLEFINANCE(""Currency:GBPEUR""), IF($D24=""Iene"",'Original Data'!Q24*GOOGLEFINANCE(""Currency:JPYEUR""), IF($D24=""HKD"",'Original Data'!Q24*GOOGLEFINANCE(""Currency:HKDEUR""), IF($D24=""KRW"",'Original Data'!Q24*GOOGLEFINANCE("&"""Currency:KRWEUR""),""""))))))))"),2.18) -> 2.18 | R24: =IFERROR(__xludf.DUMMYFUNCTION("IF('Original Data'!R24=""-"",""-"", IF($D24=""Euro"",'Original Data'!R24, IF($D24=""Dolar"",'Original Data'!R24*GOOGLEFINANCE(""Currency:USDEUR""), IF($D24=""Franco Suíço"",'Original Data'!R24*GOOGLEFINANCE(""Currency:CHFEUR""), IF($D24=""Libra Esterlina"&""", 'Original Data'!R24*GOOGLEFINANCE(""Currency:GBPEUR""), IF($D24=""Iene"",'Original Data'!R24*GOOGLEFINANCE(""Currency:JPYEUR""), IF($D24=""HKD"",'Original Data'!R24*GOOGLEFINANCE(""Currency:HKDEUR""), IF($D24=""KRW"",'Original Data'!R24*GOOGLEFINANCE("&"""Currency:KRWEUR""),""""))))))))"),2.32) -> 2.32 | S24: =IFERROR(__xludf.DUMMYFUNCTION("IF('Original Data'!S24=""-"",""-"", IF($D24=""Euro"",'Original Data'!S24, IF($D24=""Dolar"",'Original Data'!S24*GOOGLEFINANCE(""Currency:USDEUR""), IF($D24=""Franco Suíço"",'Original Data'!S24*GOOGLEFINANCE(""Currency:CHFEUR""), IF($D24=""Libra Esterlina"&""", 'Original Data'!S24*GOOGLEFINANCE(""Currency:GBPEUR""), IF($D24=""Iene"",'Original Data'!S24*GOOGLEFINANCE(""Currency:JPYEUR""), IF($D24=""HKD"",'Original Data'!S24*GOOGLEFINANCE(""Currency:HKDEUR""), IF($D24=""KRW"",'Original Data'!S24*GOOGLEFINANCE("&"""Currency:KRWEUR""),""""))))))))"),2.62) -> 2.62 | T24: =IFERROR(__xludf.DUMMYFUNCTION("IF('Original Data'!T24=""-"",""-"", IF($D24=""Euro"",'Original Data'!T24, IF($D24=""Dolar"",'Original Data'!T24*GOOGLEFINANCE(""Currency:USDEUR""), IF($D24=""Franco Suíço"",'Original Data'!T24*GOOGLEFINANCE(""Currency:CHFEUR""), IF($D24=""Libra Esterlina"&""", 'Original Data'!T24*GOOGLEFINANCE(""Currency:GBPEUR""), IF($D24=""Iene"",'Original Data'!T24*GOOGLEFINANCE(""Currency:JPYEUR""), IF($D24=""HKD"",'Original Data'!T24*GOOGLEFINANCE(""Currency:HKDEUR""), IF($D24=""KRW"",'Original Data'!T24*GOOGLEFINANCE("&"""Currency:KRWEUR""),""""))))))))"),2.75) -> 2.75 | U24: =IFERROR(__xludf.DUMMYFUNCTION("IF('Original Data'!U24=""-"",""-"", IF($D24=""Euro"",'Original Data'!U24, IF($D24=""Dolar"",'Original Data'!U24*GOOGLEFINANCE(""Currency:USDEUR""), IF($D24=""Franco Suíço"",'Original Data'!U24*GOOGLEFINANCE(""Currency:CHFEUR""), IF($D24=""Libra Esterlina"&""", 'Original Data'!U24*GOOGLEFINANCE(""Currency:GBPEUR""), IF($D24=""Iene"",'Original Data'!U24*GOOGLEFINANCE(""Currency:JPYEUR""), IF($D24=""HKD"",'Original Data'!U24*GOOGLEFINANCE(""Currency:HKDEUR""), IF($D24=""KRW"",'Original Data'!U24*GOOGLEFINANCE("&"""Currency:KRWEUR""),""""))))))))"),0.85121) -> 0.85121 | V24: =IFERROR(__xludf.DUMMYFUNCTION("IF('Original Data'!V24=""-"",""-"", IF($D24=""Euro"",'Original Data'!V24, IF($D24=""Dolar"",'Original Data'!V24*GOOGLEFINANCE(""Currency:USDEUR""), IF($D24=""Franco Suíço"",'Original Data'!V24*GOOGLEFINANCE(""Currency:CHFEUR""), IF($D24=""Libra Esterlina"&""", 'Original Data'!V24*GOOGLEFINANCE(""Currency:GBPEUR""), IF($D24=""Iene"",'Original Data'!V24*GOOGLEFINANCE(""Currency:JPYEUR""), IF($D24=""HKD"",'Original Data'!V24*GOOGLEFINANCE(""Currency:HKDEUR""), IF($D24=""KRW"",'Original Data'!V24*GOOGLEFINANCE("&"""Currency:KRWEUR""),""""))))))))"),0.8224) -> 0.8224 | W24: A | X24: B | Y24: - | Z24: - | AA24: - | AB24: - | AC24: 11 | AD24: 2.3 | AE24: 4.1 | AF24: 4.8 | AG24: 0
A25: CORTICEIRA AMORI | B25: COR PL Equity | C25: PTCOR0AE0006 | D25: Euro | E25: =IFERROR(__xludf.DUMMYFUNCTION("IF($D25=""Euro"",'Original Data'!E25, IF($D25=""Dolar"",'Original Data'!E25*GOOGLEFINANCE(""Currency:USDEUR""), IF($D25=""Franco Suíço"",'Original Data'!E25*GOOGLEFINANCE(""Currency:CHFEUR""), IF($D25=""Libra Esterlina"", 'Original Data'!E25*GOOGLEFINANCE"&"(""Currency:GBPEUR""), IF($D25=""Iene"",'Original Data'!E25*GOOGLEFINANCE(""Currency:JPYEUR""), IF($D25=""HKD"",'Original Data'!E25*GOOGLEFINANCE(""Currency:HKDEUR""), IF($D25=""KRW"",'Original Data'!E25*GOOGLEFINANCE(""Currency:KRWEUR""),"""")))))))"),9.35) -> 9.35 | F25: =IFERROR(__xludf.DUMMYFUNCTION("IF($D25=""Euro"",'Original Data'!F25, IF($D25=""Dolar"",'Original Data'!F25*GOOGLEFINANCE(""Currency:USDEUR""), IF($D25=""Franco Suíço"",'Original Data'!F25*GOOGLEFINANCE(""Currency:CHFEUR""), IF($D25=""Libra Esterlina"", 'Original Data'!F25*GOOGLEFINANCE"&"(""Currency:GBPEUR""), IF($D25=""Iene"",'Original Data'!F25*GOOGLEFINANCE(""Currency:JPYEUR""), IF($D25=""HKD"",'Original Data'!F25*GOOGLEFINANCE(""Currency:HKDEUR""), IF($D25=""KRW"",'Original Data'!F25*GOOGLEFINANCE(""Currency:KRWEUR""),"""")))))))"),10.1) -> 10.1 | G25: =IFERROR(__xludf.DUMMYFUNCTION("IF($D25=""Euro"",'Original Data'!G25, IF($D25=""Dolar"",'Original Data'!G25*GOOGLEFINANCE(""Currency:USDEUR""), IF($D25=""Franco Suíço"",'Original Data'!G25*GOOGLEFINANCE(""Currency:CHFEUR""), IF($D25=""Libra Esterlina"", 'Original Data'!G25*GOOGLEFINANCE"&"(""Currency:GBPEUR""), IF($D25=""Iene"",'Original Data'!G25*GOOGLEFINANCE(""Currency:JPYEUR""), IF($D25=""HKD"",'Original Data'!G25*GOOGLEFINANCE(""Currency:HKDEUR""), IF($D25=""KRW"",'Original Data'!G25*GOOGLEFINANCE(""Currency:KRWEUR""),"""")))))))"),1.32) -> 1.32 | H25: 0.10593 | I25: 17.88 | J25: -% | K25: 0.1434 | L25: 0.0938 | M25: 0.1734 | N25: =IFERROR(__xludf.DUMMYFUNCTION("IF('Original Data'!N25=""-"",""-"", IF($D25=""Euro"",'Original Data'!N25, IF($D25=""Dolar"",'Original Data'!N25*GOOGLEFINANCE(""Currency:USDEUR""), IF($D25=""Franco Suíço"",'Original Data'!N25*GOOGLEFINANCE(""Currency:CHFEUR""), IF($D25=""Libra Esterlina"&""", 'Original Data'!N25*GOOGLEFINANCE(""Currency:GBPEUR""), IF($D25=""Iene"",'Original Data'!N25*GOOGLEFINANCE(""Currency:JPYEUR""), IF($D25=""HKD"",'Original Data'!N25*GOOGLEFINANCE(""Currency:HKDEUR""), IF($D25=""KRW"",'Original Data'!N25*GOOGLEFINANCE("&"""Currency:KRWEUR""),""""))))))))"),0.48) -> 0.48 | O25: =IFERROR(__xludf.DUMMYFUNCTION("IF('Original Data'!O25=""-"",""-"", IF($D25=""Euro"",'Original Data'!O25, IF($D25=""Dolar"",'Original Data'!O25*GOOGLEFINANCE(""Currency:USDEUR""), IF($D25=""Franco Suíço"",'Original Data'!O25*GOOGLEFINANCE(""Currency:CHFEUR""), IF($D25=""Libra Esterlina"&""", 'Original Data'!O25*GOOGLEFINANCE(""Currency:GBPEUR""), IF($D25=""Iene"",'Original Data'!O25*GOOGLEFINANCE(""Currency:JPYEUR""), IF($D25=""HKD"",'Original Data'!O25*GOOGLEFINANCE(""Currency:HKDEUR""), IF($D25=""KRW"",'Original Data'!O25*GOOGLEFINANCE("&"""Currency:KRWEUR""),""""))))))))"),0.76312) -> 0.76312 | P25: =IFERROR(__xludf.DUMMYFUNCTION("IF('Original Data'!P25=""-"",""-"", IF($D25=""Euro"",'Original Data'!P25, IF($D25=""Dolar"",'Original Data'!P25*GOOGLEFINANCE(""Currency:USDEUR""), IF($D25=""Franco Suíço"",'Original Data'!P25*GOOGLEFINANCE(""Currency:CHFEUR""), IF($D25=""Libra Esterlina"&""", 'Original Data'!P25*GOOGLEFINANCE(""Currency:GBPEUR""), IF($D25=""Iene"",'Original Data'!P25*GOOGLEFINANCE(""Currency:JPYEUR""), IF($D25=""HKD"",'Original Data'!P25*GOOGLEFINANCE(""Currency:HKDEUR""), IF($D25=""KRW"",'Original Data'!P25*GOOGLEFINANCE("&"""Currency:KRWEUR""),""""))))))))"),0.78106) -> 0.78106 | Q25: =IFERROR(__xludf.DUMMYFUNCTION("IF('Original Data'!Q25=""-"",""-"", IF($D25=""Euro"",'Original Data'!Q25, IF($D25=""Dolar"",'Original Data'!Q25*GOOGLEFINANCE(""Currency:USDEUR""), IF($D25=""Franco Suíço"",'Original Data'!Q25*GOOGLEFINANCE(""Currency:CHFEUR""), IF($D25=""Libra Esterlina"&""", 'Original Data'!Q25*GOOGLEFINANCE(""Currency:GBPEUR""), IF($D25=""Iene"",'Original Data'!Q25*GOOGLEFINANCE(""Currency:JPYEUR""), IF($D25=""HKD"",'Original Data'!Q25*GOOGLEFINANCE(""Currency:HKDEUR""), IF($D25=""KRW"",'Original Data'!Q25*GOOGLEFINANCE("&"""Currency:KRWEUR""),""""))))))))"),0.74011) -> 0.74011 | R25: =IFERROR(__xludf.DUMMYFUNCTION("IF('Original Data'!R25=""-"",""-"", IF($D25=""Euro"",'Original Data'!R25, IF($D25=""Dolar"",'Original Data'!R25*GOOGLEFINANCE(""Currency:USDEUR""), IF($D25=""Franco Suíço"",'Original Data'!R25*GOOGLEFINANCE(""Currency:CHFEUR""), IF($D25=""Libra Esterlina"&""", 'Original Data'!R25*GOOGLEFINANCE(""Currency:GBPEUR""), IF($D25=""Iene"",'Original Data'!R25*GOOGLEFINANCE(""Currency:JPYEUR""), IF($D25=""HKD"",'Original Data'!R25*GOOGLEFINANCE(""Currency:HKDEUR""), IF($D25=""KRW"",'Original Data'!R25*GOOGLEFINANCE("&"""Currency:KRWEUR""),""""))))))))"),0.83782) -> 0.83782 | S25: =IFERROR(__xludf.DUMMYFUNCTION("IF('Original Data'!S25=""-"",""-"", IF($D25=""Euro"",'Original Data'!S25, IF($D25=""Dolar"",'Original Data'!S25*GOOGLEFINANCE(""Currency:USDEUR""), IF($D25=""Franco Suíço"",'Original Data'!S25*GOOGLEFINANCE(""Currency:CHFEUR""), IF($D25=""Libra Esterlina"&""", 'Original Data'!S25*GOOGLEFINANCE(""Currency:GBPEUR""), IF($D25=""Iene"",'Original Data'!S25*GOOGLEFINANCE(""Currency:JPYEUR""), IF($D25=""HKD"",'Original Data'!S25*GOOGLEFINANCE(""Currency:HKDEUR""), IF($D25=""KRW"",'Original Data'!S25*GOOGLEFINANCE("&"""Currency:KRWEUR""),""""))))))))"),0.12629) -> 0.12629 | T25: =IFERROR(__xludf.DUMMYFUNCTION("IF('Original Data'!T25=""-"",""-"", IF($D25=""Euro"",'Original Data'!T25, IF($D25=""Dolar"",'Original Data'!T25*GOOGLEFINANCE(""Currency:USDEUR""), IF($D25=""Franco Suíço"",'Original Data'!T25*GOOGLEFINANCE(""Currency:CHFEUR""), IF($D25=""Libra Esterlina"&""", 'Original Data'!T25*GOOGLEFINANCE(""Currency:GBPEUR""), IF($D25=""Iene"",'Original Data'!T25*GOOGLEFINANCE(""Currency:JPYEUR""), IF($D25=""HKD"",'Original Data'!T25*GOOGLEFINANCE(""Currency:HKDEUR""), IF($D25=""KRW"",'Original Data'!T25*GOOGLEFINANCE("&"""Currency:KRWEUR""),""""))))))))"),0.1182) -> 0.1182 | U25: =IFERROR(__xludf.DUMMYFUNCTION("IF('Original Data'!U25=""-"",""-"", IF($D25=""Euro"",'Original Data'!U25, IF($D25=""Dolar"",'Original Data'!U25*GOOGLEFINANCE(""Currency:USDEUR""), IF($D25=""Franco Suíço"",'Original Data'!U25*GOOGLEFINANCE(""Currency:CHFEUR""), IF($D25=""Libra Esterlina"&""", 'Original Data'!U25*GOOGLEFINANCE(""Currency:GBPEUR""), IF($D25=""Iene"",'Original Data'!U25*GOOGLEFINANCE(""Currency:JPYEUR""), IF($D25=""HKD"",'Original Data'!U25*GOOGLEFINANCE(""Currency:HKDEUR""), IF($D25=""KRW"",'Original Data'!U25*GOOGLEFINANCE("&"""Currency:KRWEUR""),""""))))))))"),0.10929) -> 0.10929 | V25: =IFERROR(__xludf.DUMMYFUNCTION("IF('Original Data'!V25=""-"",""-"", IF($D25=""Euro"",'Original Data'!V25, IF($D25=""Dolar"",'Original Data'!V25*GOOGLEFINANCE(""Currency:USDEUR""), IF($D25=""Franco Suíço"",'Original Data'!V25*GOOGLEFINANCE(""Currency:CHFEUR""), IF($D25=""Libra Esterlina"&""", 'Original Data'!V25*GOOGLEFINANCE(""Currency:GBPEUR""), IF($D25=""Iene"",'Original Data'!V25*GOOGLEFINANCE(""Currency:JPYEUR""), IF($D25=""HKD"",'Original Data'!V25*GOOGLEFINANCE(""Currency:HKDEUR""), IF($D25=""KRW"",'Original Data'!V25*GOOGLEFINANCE("&"""Currency:KRWEUR""),""""))))))))"),"-") -> - | W25: Declined to participate | X25: Not Available | Y25: No Response | Z25: No Response | AA25: Declined to participate | AB25: Declined to participate | AC25: - | AD25: - | AE25: - | AF25: - | AG25: -
A26: SANOFI | B26: SAN FP Equity | C26: FR0000120578 | D26: Euro | E26: =IFERROR(__xludf.DUMMYFUNCTION("IF($D26=""Euro"",'Original Data'!E26, IF($D26=""Dolar"",'Original Data'!E26*GOOGLEFINANCE(""Currency:USDEUR""), IF($D26=""Franco Suíço"",'Original Data'!E26*GOOGLEFINANCE(""Currency:CHFEUR""), IF($D26=""Libra Esterlina"", 'Original Data'!E26*GOOGLEFINANCE"&"(""Currency:GBPEUR""), IF($D26=""Iene"",'Original Data'!E26*GOOGLEFINANCE(""Currency:JPYEUR""), IF($D26=""HKD"",'Original Data'!E26*GOOGLEFINANCE(""Currency:HKDEUR""), IF($D26=""KRW"",'Original Data'!E26*GOOGLEFINANCE(""Currency:KRWEUR""),"""")))))))"),7.19) -> 7.19 | F26: =IFERROR(__xludf.DUMMYFUNCTION("IF($D26=""Euro"",'Original Data'!F26, IF($D26=""Dolar"",'Original Data'!F26*GOOGLEFINANCE(""Currency:USDEUR""), IF($D26=""Franco Suíço"",'Original Data'!F26*GOOGLEFINANCE(""Currency:CHFEUR""), IF($D26=""Libra Esterlina"", 'Original Data'!F26*GOOGLEFINANCE"&"(""Currency:GBPEUR""), IF($D26=""Iene"",'Original Data'!F26*GOOGLEFINANCE(""Currency:JPYEUR""), IF($D26=""HKD"",'Original Data'!F26*GOOGLEFINANCE(""Currency:HKDEUR""), IF($D26=""KRW"",'Original Data'!F26*GOOGLEFINANCE(""Currency:KRWEUR""),"""")))))))"),94.04) -> 94.04 | G26: =IFERROR(__xludf.DUMMYFUNCTION("IF($D26=""Euro"",'Original Data'!G26, IF($D26=""Dolar"",'Original Data'!G26*GOOGLEFINANCE(""Currency:USDEUR""), IF($D26=""Franco Suíço"",'Original Data'!G26*GOOGLEFINANCE(""Currency:CHFEUR""), IF($D26=""Libra Esterlina"", 'Original Data'!G26*GOOGLEFINANCE"&"(""Currency:GBPEUR""), IF($D26=""Iene"",'Original Data'!G26*GOOGLEFINANCE(""Currency:JPYEUR""), IF($D26=""HKD"",'Original Data'!G26*GOOGLEFINANCE(""Currency:HKDEUR""), IF($D26=""KRW"",'Original Data'!G26*GOOGLEFINANCE(""Currency:KRWEUR""),"""")))))))"),119.47) -> 119.47 | H26: 3.01 | I26: 19.08 | J26: 0.0353 | K26: 0.0623 | L26: 0.0519 | M26: 0.0975 | N26: =IFERROR(__xludf.DUMMYFUNCTION("IF('Original Data'!N26=""-"",""-"", IF($D26=""Euro"",'Original Data'!N26, IF($D26=""Dolar"",'Original Data'!N26*GOOGLEFINANCE(""Currency:USDEUR""), IF($D26=""Franco Suíço"",'Original Data'!N26*GOOGLEFINANCE(""Currency:CHFEUR""), IF($D26=""Libra Esterlina"&""", 'Original Data'!N26*GOOGLEFINANCE(""Currency:GBPEUR""), IF($D26=""Iene"",'Original Data'!N26*GOOGLEFINANCE(""Currency:JPYEUR""), IF($D26=""HKD"",'Original Data'!N26*GOOGLEFINANCE(""Currency:HKDEUR""), IF($D26=""KRW"",'Original Data'!N26*GOOGLEFINANCE("&"""Currency:KRWEUR""),""""))))))))"),4.97) -> 4.97 | O26: =IFERROR(__xludf.DUMMYFUNCTION("IF('Original Data'!O26=""-"",""-"", IF($D26=""Euro"",'Original Data'!O26, IF($D26=""Dolar"",'Original Data'!O26*GOOGLEFINANCE(""Currency:USDEUR""), IF($D26=""Franco Suíço"",'Original Data'!O26*GOOGLEFINANCE(""Currency:CHFEUR""), IF($D26=""Libra Esterlina"&""", 'Original Data'!O26*GOOGLEFINANCE(""Currency:GBPEUR""), IF($D26=""Iene"",'Original Data'!O26*GOOGLEFINANCE(""Currency:JPYEUR""), IF($D26=""HKD"",'Original Data'!O26*GOOGLEFINANCE(""Currency:HKDEUR""), IF($D26=""KRW"",'Original Data'!O26*GOOGLEFINANCE("&"""Currency:KRWEUR""),""""))))))))"),34.46) -> 34.46 | P26: =IFERROR(__xludf.DUMMYFUNCTION("IF('Original Data'!P26=""-"",""-"", IF($D26=""Euro"",'Original Data'!P26, IF($D26=""Dolar"",'Original Data'!P26*GOOGLEFINANCE(""Currency:USDEUR""), IF($D26=""Franco Suíço"",'Original Data'!P26*GOOGLEFINANCE(""Currency:CHFEUR""), IF($D26=""Libra Esterlina"&""", 'Original Data'!P26*GOOGLEFINANCE(""Currency:GBPEUR""), IF($D26=""Iene"",'Original Data'!P26*GOOGLEFINANCE(""Currency:JPYEUR""), IF($D26=""HKD"",'Original Data'!P26*GOOGLEFINANCE(""Currency:HKDEUR""), IF($D26=""KRW"",'Original Data'!P26*GOOGLEFINANCE("&"""Currency:KRWEUR""),""""))))))))"),36.13) -> 36.13 | Q26: =IFERROR(__xludf.DUMMYFUNCTION("IF('Original Data'!Q26=""-"",""-"", IF($D26=""Euro"",'Original Data'!Q26, IF($D26=""Dolar"",'Original Data'!Q26*GOOGLEFINANCE(""Currency:USDEUR""), IF($D26=""Franco Suíço"",'Original Data'!Q26*GOOGLEFINANCE(""Currency:CHFEUR""), IF($D26=""Libra Esterlina"&""", 'Original Data'!Q26*GOOGLEFINANCE(""Currency:GBPEUR""), IF($D26=""Iene"",'Original Data'!Q26*GOOGLEFINANCE(""Currency:JPYEUR""), IF($D26=""HKD"",'Original Data'!Q26*GOOGLEFINANCE(""Currency:HKDEUR""), IF($D26=""KRW"",'Original Data'!Q26*GOOGLEFINANCE("&"""Currency:KRWEUR""),""""))))))))"),36.04) -> 36.04 | R26: =IFERROR(__xludf.DUMMYFUNCTION("IF('Original Data'!R26=""-"",""-"", IF($D26=""Euro"",'Original Data'!R26, IF($D26=""Dolar"",'Original Data'!R26*GOOGLEFINANCE(""Currency:USDEUR""), IF($D26=""Franco Suíço"",'Original Data'!R26*GOOGLEFINANCE(""Currency:CHFEUR""), IF($D26=""Libra Esterlina"&""", 'Original Data'!R26*GOOGLEFINANCE(""Currency:GBPEUR""), IF($D26=""Iene"",'Original Data'!R26*GOOGLEFINANCE(""Currency:JPYEUR""), IF($D26=""HKD"",'Original Data'!R26*GOOGLEFINANCE(""Currency:HKDEUR""), IF($D26=""KRW"",'Original Data'!R26*GOOGLEFINANCE("&"""Currency:KRWEUR""),""""))))))))"),37.76) -> 37.76 | S26: =IFERROR(__xludf.DUMMYFUNCTION("IF('Original Data'!S26=""-"",""-"", IF($D26=""Euro"",'Original Data'!S26, IF($D26=""Dolar"",'Original Data'!S26*GOOGLEFINANCE(""Currency:USDEUR""), IF($D26=""Franco Suíço"",'Original Data'!S26*GOOGLEFINANCE(""Currency:CHFEUR""), IF($D26=""Libra Esterlina"&""", 'Original Data'!S26*GOOGLEFINANCE(""Currency:GBPEUR""), IF($D26=""Iene"",'Original Data'!S26*GOOGLEFINANCE(""Currency:JPYEUR""), IF($D26=""HKD"",'Original Data'!S26*GOOGLEFINANCE(""Currency:HKDEUR""), IF($D26=""KRW"",'Original Data'!S26*GOOGLEFINANCE("&"""Currency:KRWEUR""),""""))))))))"),8.55) -> 8.55 | T26: =IFERROR(__xludf.DUMMYFUNCTION("IF('Original Data'!T26=""-"",""-"", IF($D26=""Euro"",'Original Data'!T26, IF($D26=""Dolar"",'Original Data'!T26*GOOGLEFINANCE(""Currency:USDEUR""), IF($D26=""Franco Suíço"",'Original Data'!T26*GOOGLEFINANCE(""Currency:CHFEUR""), IF($D26=""Libra Esterlina"&""", 'Original Data'!T26*GOOGLEFINANCE(""Currency:GBPEUR""), IF($D26=""Iene"",'Original Data'!T26*GOOGLEFINANCE(""Currency:JPYEUR""), IF($D26=""HKD"",'Original Data'!T26*GOOGLEFINANCE(""Currency:HKDEUR""), IF($D26=""KRW"",'Original Data'!T26*GOOGLEFINANCE("&"""Currency:KRWEUR""),""""))))))))"),9.82) -> 9.82 | U26: =IFERROR(__xludf.DUMMYFUNCTION("IF('Original Data'!U26=""-"",""-"", IF($D26=""Euro"",'Original Data'!U26, IF($D26=""Dolar"",'Original Data'!U26*GOOGLEFINANCE(""Currency:USDEUR""), IF($D26=""Franco Suíço"",'Original Data'!U26*GOOGLEFINANCE(""Currency:CHFEUR""), IF($D26=""Libra Esterlina"&""", 'Original Data'!U26*GOOGLEFINANCE(""Currency:GBPEUR""), IF($D26=""Iene"",'Original Data'!U26*GOOGLEFINANCE(""Currency:JPYEUR""), IF($D26=""HKD"",'Original Data'!U26*GOOGLEFINANCE(""Currency:HKDEUR""), IF($D26=""KRW"",'Original Data'!U26*GOOGLEFINANCE("&"""Currency:KRWEUR""),""""))))))))"),10.54) -> 10.54 | V26: =IFERROR(__xludf.DUMMYFUNCTION("IF('Original Data'!V26=""-"",""-"", IF($D26=""Euro"",'Original Data'!V26, IF($D26=""Dolar"",'Original Data'!V26*GOOGLEFINANCE(""Currency:USDEUR""), IF($D26=""Franco Suíço"",'Original Data'!V26*GOOGLEFINANCE(""Currency:CHFEUR""), IF($D26=""Libra Esterlina"&""", 'Original Data'!V26*GOOGLEFINANCE(""Currency:GBPEUR""), IF($D26=""Iene"",'Original Data'!V26*GOOGLEFINANCE(""Currency:JPYEUR""), IF($D26=""HKD"",'Original Data'!V26*GOOGLEFINANCE(""Currency:HKDEUR""), IF($D26=""KRW"",'Original Data'!V26*GOOGLEFINANCE("&"""Currency:KRWEUR""),""""))))))))"),11.8) -> 11.8 | W26: A- | X26: A | Y26: No Response | Z26: No Response | AA26: A | AB26: A | AC26: 23 | AD26: 1.6 | AE26: 13.4 | AF26: 7.9 | AG26: 4
